Workbook

Sheet Summary
A1: Status | B1: reachedathub
A2: LP | B2: BLR LOCAL
A3: scm_master_category | B3: furniture
A5: Sum of item_quantity | B5: Column Labels
A6: Row Labels | B6: Breached | C6: P0 | D6: P1 | E6: Grand Total
A7: CFR | B7: 30 | C7: 8 | D7: 5 | E7: 43
A8: Outside Service Location | B8: 16 | C8: 9 | D8: 13 | E8: 38
A9: Planned | B9: 62 | C9: 31 | D9: 1 | E9: 94
A10: CNR | B10: 51 | C10: 38 | E10: 89
A11: Capcity Filled-Not Called | D11: 140 | E11: 140
A12: Grand Total | B12: 159 | C12: 86 | D12: 159 | E12: 404

Sheet Raw
A1: Platform | B1: order_random_id | C1: cx_name | D1: address | E1: pincode | F1: mobile_number | G1: alternate_mobile_number | H1: item_sku | I1: item_dimensions | J1: scm_master_category | K1: Material_code | L1: Product_Type | M1: storage_location | N1: item_quantity | O1: payment_type | P1: invoice_number | Q1: docket_number | R1: LP | S1: Order_Type | T1: Order_Status | U1: Order_Date | V1: Order_Confirmed_Date | W1: promised_dispatch | X1: Promised_EDD | Y1: docket_timestamp | Z1: shipped_timestamp | AA1: priority_local | AB1: escalated | AC1: escalation_type | AD1: Status | AE1: Previous Reason | AF1: Previous date | AG1: Response | AH1: Planning | AI1: Date | AJ1: Retail | AK1: CES | AL1: ESC | AM1: RTS | AN1: NDR | AO1: ODA | AP1: Manual | AQ1: Remarks
A2: Wakefit_Retail | B2: ORDER202603D4JJJj | C2: Neshan Shashi | D2: 415- Purna Kumb, 415, 7th A Main Rd, HRBR Layout 1st Block, HRBR Layout, Kalyan Nagar, Bengaluru, Karnataka | E2: 560043 | F2: 9380567157 | G2: 8296928367 | H2: WDINEKOVAC1ROBBK | J2: furniture | K2: 1001026053 | L2: Metal Dining Chair | M2: FG01 | N2: 1 | O2: ONLINE | P2: 26060590010670 | Q2: WFFWI223368 | R2: BLR LOCAL | S2: Replacement | T2: Docketed | U2: 2026-04-21 | V2: 2026-04-21 | W2: 2026-05-08 | X2: 2026-05-09 | Y2: 2026-06-22T09:36:22 | AA2: Breached | AB2: 0 | AD2: =VLOOKUP(Q2,'[1]an1asv_22-06-2026_06-23-43'!$B:$OA,3,0) -> reachedathub | AE2: =VLOOKUP(Q2,'[1]an1asv_22-06-2026_06-23-43'!$B:$OA,147,0) -> 0 | AF2: =VLOOKUP(Q2,'[1]an1asv_22-06-2026_06-23-43'!$B:$OA,48,0) -> 46195 | AG2: =VLOOKUP(F2,Response!$A:$B,2,0) -> #N/A | AH2: CNR | AJ2: =VLOOKUP(B2,'Ces, Esc, RTS and Retail'!$A:$B,2,0) -> #N/A | AK2: =VLOOKUP(F2,'Ces, Esc, RTS and Retail'!$D:$F,3,0) -> #N/A | AL2: =VLOOKUP(B2,'Ces, Esc, RTS and Retail'!$H:$H,1,0) -> #N/A | AM2: =VLOOKUP(Q2,'Ces, Esc, RTS and Retail'!$J:$J,1,0) -> #N/A | AN2: =VLOOKUP(Q2,'[2]Trip Manager Report(Updated)_V2'!$I:$Z,18,0) -> #N/A | AO2: =VLOOKUP(E2,'Ces, Esc, RTS and Retail'!$L:$L,1,0) -> #N/A | AP2: =VLOOKUP(Q2,Response!$H:$M,5,0) -> #N/A
A3: Wakefit_Retail | B3: ORDER202604EIG0pk | C3: Yash Sharma | D3: 1A , PMN Nest , Kaverappa Layout , Kadubeesanhalli | E3: 560103 | F3: 7976987821 | H3: WCFTSERAVACW | J3: furniture | K3: 1007120152 | L3: Coffee Table | M3: FG01 | N3: 1 | O3: ONLINE | P3: 26050590010369 | Q3: WFFI440688 | R3: BLR LOCAL | S3: Normal Order | T3: Shipped | U3: 2026-04-25 | V3: 2026-04-25 | W3: 2026-05-03 | X3: 2026-05-04 | Y3: 2026-05-19T23:35:57 | Z3: 2026-06-14T19:15:00 | AA3: Breached | AB3: 0 | AD3: =VLOOKUP(Q3,'[1]an1asv_22-06-2026_06-23-43'!$B:$OA,3,0) -> reachedathub | AE3: =VLOOKUP(Q3,'[1]an1asv_22-06-2026_06-23-43'!$B:$OA,147,0) -> Customer Request for Future Date Delivery | AF3: =VLOOKUP(Q3,'[1]an1asv_22-06-2026_06-23-43'!$B:$OA,48,0) -> 46205 | AG3: =VLOOKUP(F3,Response!$A:$B,2,0) -> #N/A | AH3: CFR | AI3: =AF3 -> 46205 | AJ3: =VLOOKUP(B3,'Ces, Esc, RTS and Retail'!$A:$B,2,0) -> #N/A | AK3: =VLOOKUP(F3,'Ces, Esc, RTS and Retail'!$D:$F,3,0) -> #N/A | AL3: =VLOOKUP(B3,'Ces, Esc, RTS and Retail'!$H:$H,1,0) -> #N/A | AM3: =VLOOKUP(Q3,'Ces, Esc, RTS and Retail'!$J:$J,1,0) -> #N/A | AN3: =VLOOKUP(Q3,'[2]Trip Manager Report(Updated)_V2'!$I:$Z,18,0) -> #N/A | AO3: =VLOOKUP(E3,'Ces, Esc, RTS and Retail'!$L:$L,1,0) -> #N/A | AP3: =VLOOKUP(Q3,Response!$H:$M,5,0) -> #N/A
A4: Wakefit_Retail | B4: ORDER202604xD3wcq | C4: Nisarga DS | D4: 108 T John Serenity, Chunchunkuppe village Tavarekere Hobli Bangalore south taluk | E4: 562130 | F4: 7483688930 | G4: 8892415163 | H4: WEWB7872HYSTESSERCW | I4: 78x72 inch | J4: furniture | K4: 1001033589 | L4: Engineered Wood Bed | M4: FG01 | N4: 1 | O4: ONLINE | P4: 26050590010417 | Q4: WFFI440732 | R4: BLR LOCAL | S4: Normal Order | T4: Shipped | U4: 2026-04-26 | V4: 2026-04-27 | W4: 2026-05-21 | X4: 2026-05-25 | Y4: 2026-05-19T23:41:42 | Z4: 2026-06-19T21:39:56 | AA4: Breached | AB4: 0 | AD4: =VLOOKUP(Q4,'[1]an1asv_22-06-2026_06-23-43'!$B:$OA,3,0) -> reachedathub | AE4: =VLOOKUP(Q4,'[1]an1asv_22-06-2026_06-23-43'!$B:$OA,147,0) -> Outside Service Location | AF4: =VLOOKUP(Q4,'[1]an1asv_22-06-2026_06-23-43'!$B:$OA,48,0) -> 46196 | AG4: =VLOOKUP(F4,Response!$A:$B,2,0) -> #N/A | AH4: Outside Service Location | AJ4: =VLOOKUP(B4,'Ces, Esc, RTS and Retail'!$A:$B,2,0) -> #N/A | AK4: =VLOOKUP(F4,'Ces, Esc, RTS and Retail'!$D:$F,3,0) -> #N/A | AL4: =VLOOKUP(B4,'Ces, Esc, RTS and Retail'!$H:$H,1,0) -> #N/A | AM4: =VLOOKUP(Q4,'Ces, Esc, RTS and Retail'!$J:$J,1,0) -> #N/A | AN4: =VLOOKUP(Q4,'[2]Trip Manager Report(Updated)_V2'!$I:$Z,18,0) -> #N/A | AO4: =VLOOKUP(E4,'Ces, Esc, RTS and Retail'!$L:$L,1,0) -> 562130 | AP4: =VLOOKUP(Q4,Response!$H:$M,5,0) -> #N/A
A5: Flipkart | B5: OD437458319078931100 | C5: Sudhanshu Jena | D5: Flat 103 , Unnati Bhavan Maithri Layout, 3rd Cross Road, V S Reddy Colony, Kadugodi | E5: 560067 | F5: 8342061533 | H5: WEWB7860STAURUSWE | I5: 78x60 inch | J5: furniture | K5: 1001024790 | L5: Engineered Wood Bed | M5: FG01 | N5: 1 | O5: ONLINE | P5: 26050590002325 | Q5: WFFI430862 | R5: BLR LOCAL | S5: Normal Order | T5: Shipped | U5: 2026-05-02 | V5: 2026-05-02 | W5: 2026-05-06 | X5: 2026-05-07 | Y5: 2026-05-06T09:41:09 | Z5: 2026-06-01T20:16:46 | AA5: Breached | AB5: 0 | AD5: =VLOOKUP(Q5,'[1]an1asv_22-06-2026_06-23-43'!$B:$OA,3,0) -> reachedathub | AE5: =VLOOKUP(Q5,'[1]an1asv_22-06-2026_06-23-43'!$B:$OA,147,0) -> Customer Request for Future Date Delivery | AF5: =VLOOKUP(Q5,'[1]an1asv_22-06-2026_06-23-43'!$B:$OA,48,0) -> 46208 | AG5: =VLOOKUP(F5,Response!$A:$B,2,0) -> #N/A | AH5: CFR | AI5: =AF5 -> 46208 | AJ5: =VLOOKUP(B5,'Ces, Esc, RTS and Retail'!$A:$B,2,0) -> #N/A | AK5: =VLOOKUP(F5,'Ces, Esc, RTS and Retail'!$D:$F,3,0) -> #N/A | AL5: =VLOOKUP(B5,'Ces, Esc, RTS and Retail'!$H:$H,1,0) -> #N/A | AM5: =VLOOKUP(Q5,'Ces, Esc, RTS and Retail'!$J:$J,1,0) -> #N/A | AN5: =VLOOKUP(Q5,'[2]Trip Manager Report(Updated)_V2'!$I:$Z,18,0) -> #N/A | AO5: =VLOOKUP(E5,'Ces, Esc, RTS and Retail'!$L:$L,1,0) -> #N/A | AP5: =VLOOKUP(Q5,Response!$H:$M,5,0) -> #N/A
A6: Amazon | B6: 403-5995909-0108356 | C6: Sahana | D6: Sattva Anugraha Tower 16 302, Sattva Anugraha, Kamakshipalya | E6: 560079 | F6: 9980085231 | G6: 9980085231 | H6: WEWB7872HYSUPOGRMARS | I6: 78x72 inch | J6: furniture | K6: 1007002830 | L6: Engineered Wood Bed | M6: FG01 | N6: 1 | O6: ONLINE | P6: 26050590011277 | Q6: WFFI441318 | R6: BLR LOCAL | S6: Normal Order | T6: Shipped | U6: 2026-05-10 | V6: 2026-05-10 | W6: 2026-05-18 | X6: 2026-05-21 | Y6: 2026-05-21T08:06:10 | Z6: 2026-06-09T22:17:40 | AA6: Breached | AB6: 0 | AD6: =VLOOKUP(Q6,'[1]an1asv_22-06-2026_06-23-43'!$B:$OA,3,0) -> reachedathub | AE6: =VLOOKUP(Q6,'[1]an1asv_22-06-2026_06-23-43'!$B:$OA,147,0) -> Customer Request for Future Date Delivery | AF6: =VLOOKUP(Q6,'[1]an1asv_22-06-2026_06-23-43'!$B:$OA,48,0) -> 46200 | AG6: =VLOOKUP(F6,Response!$A:$B,2,0) -> #N/A | AH6: CFR | AI6: =AF6 -> 46200 | AJ6: =VLOOKUP(B6,'Ces, Esc, RTS and Retail'!$A:$B,2,0) -> #N/A | AK6: =VLOOKUP(F6,'Ces, Esc, RTS and Retail'!$D:$F,3,0) -> #N/A | AL6: =VLOOKUP(B6,'Ces, Esc, RTS and Retail'!$H:$H,1,0) -> #N/A | AM6: =VLOOKUP(Q6,'Ces, Esc, RTS and Retail'!$J:$J,1,0) -> #N/A | AN6: =VLOOKUP(Q6,'[2]Trip Manager Report(Updated)_V2'!$I:$Z,18,0) -> #N/A | AO6: =VLOOKUP(E6,'Ces, Esc, RTS and Retail'!$L:$L,1,0) -> #N/A | AP6: =VLOOKUP(Q6,Response!$H:$M,5,0) -> #N/A
A7: Wakefit_Retail | B7: ORDER202605DYn9qM | C7: Remjith TK | D7: Tower 3, Flat No 903, 9th Floor, Purva Atmosphere,Thanisandra. | E7: 560077 | F7: 9535740011 | H7: WEWB7860HYSNIXCW | I7: 78x60 inch | J7: furniture | K7: 1001039591 | L7: Engineered Wood Bed | M7: FG01 | N7: 1 | O7: ONLINE | P7: 26060590005593 | Q7: WFFI455027 | R7: BLR LOCAL | S7: Normal Order | T7: Docketed | U7: 2026-05-12 | V7: 2026-05-12 | W7: 2026-06-02 | X7: 2026-06-03 | Y7: 2026-06-11T21:36:27 | AA7: Breached | AB7: 0 | AD7: =VLOOKUP(Q7,'[1]an1asv_22-06-2026_06-23-43'!$B:$OA,3,0) -> reachedathub | AE7: =VLOOKUP(Q7,'[1]an1asv_22-06-2026_06-23-43'!$B:$OA,147,0) -> Customer Request for Future Date Delivery | AF7: =VLOOKUP(Q7,'[1]an1asv_22-06-2026_06-23-43'!$B:$OA,48,0) -> 46199 | AG7: =VLOOKUP(F7,Response!$A:$B,2,0) -> #N/A | AH7: CFR | AI7: =AF7 -> 46199 | AJ7: =VLOOKUP(B7,'Ces, Esc, RTS and Retail'!$A:$B,2,0) -> #N/A | AK7: =VLOOKUP(F7,'Ces, Esc, RTS and Retail'!$D:$F,3,0) -> #N/A | AL7: =VLOOKUP(B7,'Ces, Esc, RTS and Retail'!$H:$H,1,0) -> #N/A | AM7: =VLOOKUP(Q7,'Ces, Esc, RTS and Retail'!$J:$J,1,0) -> #N/A | AN7: =VLOOKUP(Q7,'[2]Trip Manager Report(Updated)_V2'!$I:$Z,18,0) -> #N/A | AO7: =VLOOKUP(E7,'Ces, Esc, RTS and Retail'!$L:$L,1,0) -> #N/A | AP7: =VLOOKUP(Q7,Response!$H:$M,5,0) -> #N/A
A8: Wakefit | B8: ORDER202605t2y4PB | C8: Avinash Chawla | D8: B-014, 1, Sansidh Galaxy, B Block, Rachenahalli | E8: 560077 | F8: 9823670557 | G8: 7276070557 | H8: WEWB7872HYSTESSERCW | I8: 78x72 inch | J8: furniture | K8: 1001033589 | L8: Engineered Wood Bed | M8: FG01 | N8: 1 | O8: ONLINE | P8: 26060590008303 | Q8: WFFI458051 | R8: BLR LOCAL | S8: Normal Order | T8: Docketed | U8: 2026-05-18 | V8: 2026-05-18 | W8: 2026-06-17 | X8: 2026-06-18 | Y8: 2026-06-17T12:06:09 | AA8: Breached | AB8: 0 | AD8: =VLOOKUP(Q8,'[1]an1asv_22-06-2026_06-23-43'!$B:$OA,3,0) -> reachedathub | AE8: =VLOOKUP(Q8,'[1]an1asv_22-06-2026_06-23-43'!$B:$OA,147,0) -> CNR/ No Date from Customer | AF8: =VLOOKUP(Q8,'[1]an1asv_22-06-2026_06-23-43'!$B:$OA,48,0) -> 46196 | AG8: =VLOOKUP(F8,Response!$A:$B,2,0) -> #N/A | AH8: CNR | AJ8: =VLOOKUP(B8,'Ces, Esc, RTS and Retail'!$A:$B,2,0) -> #N/A | AK8: =VLOOKUP(F8,'Ces, Esc, RTS and Retail'!$D:$F,3,0) -> #N/A | AL8: =VLOOKUP(B8,'Ces, Esc, RTS and Retail'!$H:$H,1,0) -> #N/A | AM8: =VLOOKUP(Q8,'Ces, Esc, RTS and Retail'!$J:$J,1,0) -> #N/A | AN8: =VLOOKUP(Q8,'[2]Trip Manager Report(Updated)_V2'!$I:$Z,18,0) -> #N/A | AO8: =VLOOKUP(E8,'Ces, Esc, RTS and Retail'!$L:$L,1,0) -> #N/A | AP8: =VLOOKUP(Q8,Response!$H:$M,5,0) -> #N/A
A9: Wakefit_Retail | B9: ORDER202605f7wbcG | C9: Paniraj thanthry | D9: #405, 4th floor, Sairam Gardenia, near RGA Tech Park & Decathlon mart, Hadosiddapura, Chikkakannalli, Kodathi JHC, Karnatak | E9: 560035 | F9: 8431567630 | G9: 8431567630 | H9: WEWB7860STESSERCW | I9: 78x60 inch | J9: furniture | K9: 1001033592 | L9: Engineered Wood Bed | M9: FG01 | N9: 1 | O9: ONLINE | P9: 26060590008782 | Q9: WFFI458444 | R9: BLR LOCAL | S9: Normal Order | T9: Shipped | U9: 2026-05-19 | V9: 2026-05-19 | W9: 2026-06-18 | X9: 2026-06-19 | Y9: 2026-06-17T23:21:10 | Z9: 2026-06-18T21:32:44 | AA9: Breached | AB9: 0 | AD9: =VLOOKUP(Q9,'[1]an1asv_22-06-2026_06-23-43'!$B:$OA,3,0) -> reachedathub | AE9: =VLOOKUP(Q9,'[1]an1asv_22-06-2026_06-23-43'!$B:$OA,147,0) -> Customer Request for Future Date Delivery | AF9: =VLOOKUP(Q9,'[1]an1asv_22-06-2026_06-23-43'!$B:$OA,48,0) -> 46196 | AG9: =VLOOKUP(F9,Response!$A:$B,2,0) -> #N/A | AH9: Planned | AJ9: =VLOOKUP(B9,'Ces, Esc, RTS and Retail'!$A:$B,2,0) -> #N/A | AK9: =VLOOKUP(F9,'Ces, Esc, RTS and Retail'!$D:$F,3,0) -> #N/A | AL9: =VLOOKUP(B9,'Ces, Esc, RTS and Retail'!$H:$H,1,0) -> #N/A | AM9: =VLOOKUP(Q9,'Ces, Esc, RTS and Retail'!$J:$J,1,0) -> #N/A | AN9: =VLOOKUP(Q9,'[2]Trip Manager Report(Updated)_V2'!$I:$Z,18,0) -> #N/A | AO9: =VLOOKUP(E9,'Ces, Esc, RTS and Retail'!$L:$L,1,0) -> #N/A | AP9: =VLOOKUP(Q9,Response!$H:$M,5,0) -> #N/A
A10: Wakefit | B10: ORDER202605M3lGeY | C10: Bhaskar Anand | D10: A1203, 12, Sanjeevini Aarna, A1203 sanjeevini Aarna dandupalya village hoskote highway | E10: 562114 | F10: 9535690956 | G10: 9535690956 | H10: WUWB7872SVAMANTHO | I10: 78x72 inch | J10: furniture | K10: 1007002695 | L10: Upholstered Beds | M10: FG01 | N10: 1 | O10: ONLINE | P10: 26050590013705 | Q10: WFFI444022 | R10: BLR LOCAL | S10: Normal Order | T10: Docketed | U10: 2026-05-06 | V10: 2026-05-20 | W10: 2026-06-19 | X10: 2026-06-19 | Y10: 2026-05-25T09:11:08 | AA10: Breached | AB10: 0 | AD10: =VLOOKUP(Q10,'[1]an1asv_22-06-2026_06-23-43'!$B:$OA,3,0) -> reachedathub | AE10: =VLOOKUP(Q10,'[1]an1asv_22-06-2026_06-23-43'!$B:$OA,147,0) -> Outside Service Location | AF10: =VLOOKUP(Q10,'[1]an1asv_22-06-2026_06-23-43'!$B:$OA,48,0) -> 46196 | AG10: =VLOOKUP(F10,Response!$A:$B,2,0) -> #N/A | AH10: Outside Service Location | AJ10: =VLOOKUP(B10,'Ces, Esc, RTS and Retail'!$A:$B,2,0) -> #N/A | AK10: =VLOOKUP(F10,'Ces, Esc, RTS and Retail'!$D:$F,3,0) -> #N/A | AL10: =VLOOKUP(B10,'Ces, Esc, RTS and Retail'!$H:$H,1,0) -> #N/A | AM10: =VLOOKUP(Q10,'Ces, Esc, RTS and Retail'!$J:$J,1,0) -> #N/A | AN10: =VLOOKUP(Q10,'[2]Trip Manager Report(Updated)_V2'!$I:$Z,18,0) -> #N/A | AO10: =VLOOKUP(E10,'Ces, Esc, RTS and Retail'!$L:$L,1,0) -> 562114 | AP10: =VLOOKUP(Q10,Response!$H:$M,5,0) -> #N/A
A11: Wakefit_Retail | B11: ORDER202605DGbKfC | C11: Hariharan | D11: #51 3rd floor 1st main 4th cross Swami vivekanda nagar | E11: 562114 | F11: 8526999803 | G11: 8526999803 | H11: WEWB7872NONUPOGRORIONR2 | I11: 78x72 inch | J11: furniture | K11: 1001019166 | L11: Engineered Wood Bed | M11: FG01 | N11: 1 | O11: ONLINE | P11: 26050590016916 | Q11: WFFI448123 | R11: BLR LOCAL | S11: Normal Order | T11: Shipped | U11: 2026-05-21 | V11: 2026-05-21 | W11: 2026-06-07 | X11: 2026-06-10 | Y11: 2026-05-30T20:11:32 | Z11: 2026-06-02T22:37:57 | AA11: Breached | AB11: 0 | AD11: =VLOOKUP(Q11,'[1]an1asv_22-06-2026_06-23-43'!$B:$OA,3,0) -> reachedathub | AE11: =VLOOKUP(Q11,'[1]an1asv_22-06-2026_06-23-43'!$B:$OA,147,0) -> Outside Service Location | AF11: =VLOOKUP(Q11,'[1]an1asv_22-06-2026_06-23-43'!$B:$OA,48,0) -> 46196 | AG11: =VLOOKUP(F11,Response!$A:$B,2,0) -> #N/A | AH11: Outside Service Location | AJ11: =VLOOKUP(B11,'Ces, Esc, RTS and Retail'!$A:$B,2,0) -> #N/A | AK11: =VLOOKUP(F11,'Ces, Esc, RTS and Retail'!$D:$F,3,0) -> #N/A | AL11: =VLOOKUP(B11,'Ces, Esc, RTS and Retail'!$H:$H,1,0) -> #N/A | AM11: =VLOOKUP(Q11,'Ces, Esc, RTS and Retail'!$J:$J,1,0) -> #N/A | AN11: =VLOOKUP(Q11,'[2]Trip Manager Report(Updated)_V2'!$I:$Z,18,0) -> #N/A | AO11: =VLOOKUP(E11,'Ces, Esc, RTS and Retail'!$L:$L,1,0) -> 562114 | AP11: =VLOOKUP(Q11,Response!$H:$M,5,0) -> #N/A
A12: Wakefit_Retail | B12: ORDER202605TXMROy | C12: Anshuman Mohanto | D12: D-102, ITC Garden Enclave, Jakkur Plantation, Jakkur, 560064, Bengaluru (L) : Jakkur Plantation BENGALURU, KARNATAKA - 560064 | E12: 560064 | F12: 9659979555 | H12: WDINESOMARIS6 | J12: furniture | K12: 1001039969 | L12: Dining Set | M12: FG01 | N12: 1 | O12: ONLINE | P12: 26060590009480 | Q12: WFFI459246 | R12: BLR LOCAL | S12: Replacement | T12: Shipped | U12: 2026-05-22 | V12: 2026-05-22 | W12: 2026-06-19 | X12: 2026-06-22 | Y12: 2026-06-19T11:07:45 | Z12: 2026-06-20T20:45:33 | AA12: Breached | AB12: 0 | AD12: =VLOOKUP(Q12,'[1]an1asv_22-06-2026_06-23-43'!$B:$OA,3,0) -> reachedathub | AE12: =VLOOKUP(Q12,'[1]an1asv_22-06-2026_06-23-43'!$B:$OA,147,0) -> INSUFFICIENT TIME | AF12: =VLOOKUP(Q12,'[1]an1asv_22-06-2026_06-23-43'!$B:$OA,48,0) -> 46195 | AG12: =VLOOKUP(F12,Response!$A:$B,2,0) -> #N/A | AH12: Planned | AJ12: =VLOOKUP(B12,'Ces, Esc, RTS and Retail'!$A:$B,2,0) -> #N/A | AK12: =VLOOKUP(F12,'Ces, Esc, RTS and Retail'!$D:$F,3,0) -> #N/A | AL12: =VLOOKUP(B12,'Ces, Esc, RTS and Retail'!$H:$H,1,0) -> #N/A | AM12: =VLOOKUP(Q12,'Ces, Esc, RTS and Retail'!$J:$J,1,0) -> #N/A | AN12: =VLOOKUP(Q12,'[2]Trip Manager Report(Updated)_V2'!$I:$Z,18,0) -> INSUFFICIENT TIME | AO12: =VLOOKUP(E12,'Ces, Esc, RTS and Retail'!$L:$L,1,0) -> #N/A | AP12: =VLOOKUP(Q12,Response!$H:$M,5,0) -> #N/A
A13: Wakefit_Retail | B13: ORDER202605JFeLOb | C13: Suresh Basimi | D13: S-1001, Ground Floor, BEL Layout, Bharath Nagar | E13: 560091 | F13: 7975673365 | G13: 7676268891 | H13: WEWB7860STESSERCW | I13: 78x60 inch | J13: furniture | K13: 1001033592 | L13: Engineered Wood Bed | M13: FG01 | N13: 1 | O13: ONLINE | P13: 26060590010666 | Q13: WFFI460892 | R13: BLR LOCAL | S13: Normal Order | T13: Docketed | U13: 2026-05-23 | V13: 2026-05-23 | W13: 2026-06-21 | X13: 2026-06-22 | Y13: 2026-06-22T09:36:14 | AA13: Breached | AB13: 0 | AD13: =VLOOKUP(Q13,'[1]an1asv_22-06-2026_06-23-43'!$B:$OA,3,0) -> reachedathub | AE13: =VLOOKUP(Q13,'[1]an1asv_22-06-2026_06-23-43'!$B:$OA,147,0) -> 0 | AF13: =VLOOKUP(Q13,'[1]an1asv_22-06-2026_06-23-43'!$B:$OA,48,0) -> 46195 | AG13: =VLOOKUP(F13,Response!$A:$B,2,0) -> #N/A | AH13: CNR | AJ13: =VLOOKUP(B13,'Ces, Esc, RTS and Retail'!$A:$B,2,0) -> #N/A | AK13: =VLOOKUP(F13,'Ces, Esc, RTS and Retail'!$D:$F,3,0) -> #N/A | AL13: =VLOOKUP(B13,'Ces, Esc, RTS and Retail'!$H:$H,1,0) -> #N/A | AM13: =VLOOKUP(Q13,'Ces, Esc, RTS and Retail'!$J:$J,1,0) -> #N/A | AN13: =VLOOKUP(Q13,'[2]Trip Manager Report(Updated)_V2'!$I:$Z,18,0) -> #N/A | AO13: =VLOOKUP(E13,'Ces, Esc, RTS and Retail'!$L:$L,1,0) -> #N/A | AP13: =VLOOKUP(Q13,Response!$H:$M,5,0) -> #N/A
A14: Wakefit | B14: ORDER202605gVn2hF | C14: Rishabh Gupta | D14: 1B 1102, 11, Suncity Gloria Apartments, Series 01-04, Sarjapur Dommasandra Rd, | E14: 560035 | F14: 9551997926 | G14: 9551997926 | H14: WDINEKOVAC1CGBK | J14: furniture | K14: 1001026055 | L14: Metal Dining Chair | M14: FG01 | N14: 1 | O14: ONLINE | P14: 26060590010253 | Q14: WFFWI223222 | R14: BLR LOCAL | S14: Normal Order | T14: Docketed | U14: 2026-05-23 | V14: 2026-05-23 | W14: 2026-06-21 | X14: 2026-06-22 | Y14: 2026-06-21T11:42:27 | AA14: Breached | AB14: 0 | AD14: =VLOOKUP(Q14,'[1]an1asv_22-06-2026_06-23-43'!$B:$OA,3,0) -> reachedathub | AE14: =VLOOKUP(Q14,'[1]an1asv_22-06-2026_06-23-43'!$B:$OA,147,0) -> 0 | AF14: =VLOOKUP(Q14,'[1]an1asv_22-06-2026_06-23-43'!$B:$OA,48,0) -> 46195 | AG14: =VLOOKUP(F14,Response!$A:$B,2,0) -> 0607 | AH14: CFR | AI14: 46209 | AJ14: =VLOOKUP(B14,'Ces, Esc, RTS and Retail'!$A:$B,2,0) -> #N/A | AK14: =VLOOKUP(F14,'Ces, Esc, RTS and Retail'!$D:$F,3,0) -> #N/A | AL14: =VLOOKUP(B14,'Ces, Esc, RTS and Retail'!$H:$H,1,0) -> #N/A | AM14: =VLOOKUP(Q14,'Ces, Esc, RTS and Retail'!$J:$J,1,0) -> #N/A | AN14: =VLOOKUP(Q14,'[2]Trip Manager Report(Updated)_V2'!$I:$Z,18,0) -> #N/A | AO14: =VLOOKUP(E14,'Ces, Esc, RTS and Retail'!$L:$L,1,0) -> #N/A | AP14: =VLOOKUP(Q14,Response!$H:$M,5,0) -> #N/A
A15: Wakefit | B15: ORDER202605gVn2hF | C15: Rishabh Gupta | D15: 1B 1102, 11, Suncity Gloria Apartments, Series 01-04, Sarjapur Dommasandra Rd, | E15: 560035 | F15: 9551997926 | G15: 9551997926 | H15: WDINEKOVAC1CGBK | J15: furniture | K15: 1001026055 | L15: Metal Dining Chair | M15: FG01 | N15: 1 | O15: ONLINE | P15: 26060590010256 | Q15: WFFWI223224 | R15: BLR LOCAL | S15: Normal Order | T15: Docketed | U15: 2026-05-23 | V15: 2026-05-23 | W15: 2026-06-21 | X15: 2026-06-22 | Y15: 2026-06-21T11:42:27 | AA15: Breached | AB15: 0 | AD15: =VLOOKUP(Q15,'[1]an1asv_22-06-2026_06-23-43'!$B:$OA,3,0) -> reachedathub | AE15: =VLOOKUP(Q15,'[1]an1asv_22-06-2026_06-23-43'!$B:$OA,147,0) -> 0 | AF15: =VLOOKUP(Q15,'[1]an1asv_22-06-2026_06-23-43'!$B:$OA,48,0) -> 46195 | AG15: =VLOOKUP(F15,Response!$A:$B,2,0) -> 0607 | AH15: CFR | AI15: 46209 | AJ15: =VLOOKUP(B15,'Ces, Esc, RTS and Retail'!$A:$B,2,0) -> #N/A | AK15: =VLOOKUP(F15,'Ces, Esc, RTS and Retail'!$D:$F,3,0) -> #N/A | AL15: =VLOOKUP(B15,'Ces, Esc, RTS and Retail'!$H:$H,1,0) -> #N/A | AM15: =VLOOKUP(Q15,'Ces, Esc, RTS and Retail'!$J:$J,1,0) -> #N/A | AN15: =VLOOKUP(Q15,'[2]Trip Manager Report(Updated)_V2'!$I:$Z,18,0) -> #N/A | AO15: =VLOOKUP(E15,'Ces, Esc, RTS and Retail'!$L:$L,1,0) -> #N/A | AP15: =VLOOKUP(Q15,Response!$H:$M,5,0) -> #N/A
A16: Wakefit | B16: ORDER202605gVn2hF | C16: Rishabh Gupta | D16: 1B 1102, 11, Suncity Gloria Apartments, Series 01-04, Sarjapur Dommasandra Rd, | E16: 560035 | F16: 9551997926 | G16: 9551997926 | H16: WDINEKOVAC1CGBK | J16: furniture | K16: 1001026055 | L16: Metal Dining Chair | M16: FG01 | N16: 1 | O16: ONLINE | P16: 26060590010260 | Q16: WFFWI223225 | R16: BLR LOCAL | S16: Normal Order | T16: Docketed | U16: 2026-05-23 | V16: 2026-05-23 | W16: 2026-06-21 | X16: 2026-06-22 | Y16: 2026-06-21T11:42:27 | AA16: Breached | AB16: 0 | AD16: =VLOOKUP(Q16,'[1]an1asv_22-06-2026_06-23-43'!$B:$OA,3,0) -> reachedathub | AE16: =VLOOKUP(Q16,'[1]an1asv_22-06-2026_06-23-43'!$B:$OA,147,0) -> 0 | AF16: =VLOOKUP(Q16,'[1]an1asv_22-06-2026_06-23-43'!$B:$OA,48,0) -> 46195 | AG16: =VLOOKUP(F16,Response!$A:$B,2,0) -> 0607 | AH16: CFR | AI16: 46209 | AJ16: =VLOOKUP(B16,'Ces, Esc, RTS and Retail'!$A:$B,2,0) -> #N/A | AK16: =VLOOKUP(F16,'Ces, Esc, RTS and Retail'!$D:$F,3,0) -> #N/A | AL16: =VLOOKUP(B16,'Ces, Esc, RTS and Retail'!$H:$H,1,0) -> #N/A | AM16: =VLOOKUP(Q16,'Ces, Esc, RTS and Retail'!$J:$J,1,0) -> #N/A | AN16: =VLOOKUP(Q16,'[2]Trip Manager Report(Updated)_V2'!$I:$Z,18,0) -> #N/A | AO16: =VLOOKUP(E16,'Ces, Esc, RTS and Retail'!$L:$L,1,0) -> #N/A | AP16: =VLOOKUP(Q16,Response!$H:$M,5,0) -> #N/A
A17: Wakefit | B17: ORDER202605gVn2hF | C17: Rishabh Gupta | D17: 1B 1102, 11, Suncity Gloria Apartments, Series 01-04, Sarjapur Dommasandra Rd, | E17: 560035 | F17: 9551997926 | G17: 9551997926 | H17: WDINEKOVAC1CGBK | J17: furniture | K17: 1001026055 | L17: Metal Dining Chair | M17: FG01 | N17: 1 | O17: ONLINE | P17: 26060590010264 | Q17: WFFWI223226 | R17: BLR LOCAL | S17: Normal Order | T17: Docketed | U17: 2026-05-23 | V17: 2026-05-23 | W17: 2026-06-21 | X17: 2026-06-22 | Y17: 2026-06-21T11:42:27 | AA17: Breached | AB17: 0 | AD17: =VLOOKUP(Q17,'[1]an1asv_22-06-2026_06-23-43'!$B:$OA,3,0) -> reachedathub | AE17: =VLOOKUP(Q17,'[1]an1asv_22-06-2026_06-23-43'!$B:$OA,147,0) -> 0 | AF17: =VLOOKUP(Q17,'[1]an1asv_22-06-2026_06-23-43'!$B:$OA,48,0) -> 46195 | AG17: =VLOOKUP(F17,Response!$A:$B,2,0) -> 0607 | AH17: CFR | AI17: 46209 | AJ17: =VLOOKUP(B17,'Ces, Esc, RTS and Retail'!$A:$B,2,0) -> #N/A | AK17: =VLOOKUP(F17,'Ces, Esc, RTS and Retail'!$D:$F,3,0) -> #N/A | AL17: =VLOOKUP(B17,'Ces, Esc, RTS and Retail'!$H:$H,1,0) -> #N/A | AM17: =VLOOKUP(Q17,'Ces, Esc, RTS and Retail'!$J:$J,1,0) -> #N/A | AN17: =VLOOKUP(Q17,'[2]Trip Manager Report(Updated)_V2'!$I:$Z,18,0) -> #N/A | AO17: =VLOOKUP(E17,'Ces, Esc, RTS and Retail'!$L:$L,1,0) -> #N/A | AP17: =VLOOKUP(Q17,Response!$H:$M,5,0) -> #N/A
A18: Wakefit | B18: ORDER202605gVn2hF | C18: Rishabh Gupta | D18: 1B 1102, 11, Suncity Gloria Apartments, Series 01-04, Sarjapur Dommasandra Rd, | E18: 560035 | F18: 9551997926 | G18: 9551997926 | H18: WDINEKOVAC1CGBK | J18: furniture | K18: 1001026055 | L18: Metal Dining Chair | M18: FG01 | N18: 1 | O18: ONLINE | P18: 26060590010266 | Q18: WFFWI223227 | R18: BLR LOCAL | S18: Normal Order | T18: Docketed | U18: 2026-05-23 | V18: 2026-05-23 | W18: 2026-06-21 | X18: 2026-06-22 | Y18: 2026-06-21T11:42:27 | AA18: Breached | AB18: 0 | AD18: =VLOOKUP(Q18,'[1]an1asv_22-06-2026_06-23-43'!$B:$OA,3,0) -> reachedathub | AE18: =VLOOKUP(Q18,'[1]an1asv_22-06-2026_06-23-43'!$B:$OA,147,0) -> 0 | AF18: =VLOOKUP(Q18,'[1]an1asv_22-06-2026_06-23-43'!$B:$OA,48,0) -> 46195 | AG18: =VLOOKUP(F18,Response!$A:$B,2,0) -> 0607 | AH18: CFR | AI18: 46209 | AJ18: =VLOOKUP(B18,'Ces, Esc, RTS and Retail'!$A:$B,2,0) -> #N/A | AK18: =VLOOKUP(F18,'Ces, Esc, RTS and Retail'!$D:$F,3,0) -> #N/A | AL18: =VLOOKUP(B18,'Ces, Esc, RTS and Retail'!$H:$H,1,0) -> #N/A | AM18: =VLOOKUP(Q18,'Ces, Esc, RTS and Retail'!$J:$J,1,0) -> #N/A | AN18: =VLOOKUP(Q18,'[2]Trip Manager Report(Updated)_V2'!$I:$Z,18,0) -> #N/A | AO18: =VLOOKUP(E18,'Ces, Esc, RTS and Retail'!$L:$L,1,0) -> #N/A | AP18: =VLOOKUP(Q18,Response!$H:$M,5,0) -> #N/A
A19: Wakefit | B19: ORDER202605gVn2hF | C19: Rishabh Gupta | D19: 1B 1102, 11, Suncity Gloria Apartments, Series 01-04, Sarjapur Dommasandra Rd, | E19: 560035 | F19: 9551997926 | G19: 9551997926 | H19: WDINEKOVAC1CGBK | J19: furniture | K19: 1001026055 | L19: Metal Dining Chair | M19: FG01 | N19: 1 | O19: ONLINE | P19: 26060590010272 | Q19: WFFWI223228 | R19: BLR LOCAL | S19: Normal Order | T19: Docketed | U19: 2026-05-23 | V19: 2026-05-23 | W19: 2026-06-21 | X19: 2026-06-22 | Y19: 2026-06-21T11:42:27 | AA19: Breached | AB19: 0 | AD19: =VLOOKUP(Q19,'[1]an1asv_22-06-2026_06-23-43'!$B:$OA,3,0) -> reachedathub | AE19: =VLOOKUP(Q19,'[1]an1asv_22-06-2026_06-23-43'!$B:$OA,147,0) -> 0 | AF19: =VLOOKUP(Q19,'[1]an1asv_22-06-2026_06-23-43'!$B:$OA,48,0) -> 46195 | AG19: =VLOOKUP(F19,Response!$A:$B,2,0) -> 0607 | AH19: CFR | AI19: 46209 | AJ19: =VLOOKUP(B19,'Ces, Esc, RTS and Retail'!$A:$B,2,0) -> #N/A | AK19: =VLOOKUP(F19,'Ces, Esc, RTS and Retail'!$D:$F,3,0) -> #N/A | AL19: =VLOOKUP(B19,'Ces, Esc, RTS and Retail'!$H:$H,1,0) -> #N/A | AM19: =VLOOKUP(Q19,'Ces, Esc, RTS and Retail'!$J:$J,1,0) -> #N/A | AN19: =VLOOKUP(Q19,'[2]Trip Manager Report(Updated)_V2'!$I:$Z,18,0) -> #N/A | AO19: =VLOOKUP(E19,'Ces, Esc, RTS and Retail'!$L:$L,1,0) -> #N/A | AP19: =VLOOKUP(Q19,Response!$H:$M,5,0) -> #N/A
A20: Amazon | B20: 406-1344094-7380325 | C20: Rituparna singh | D20: A 1304 ELV Kingsland Borewell road Whitefield,Opposite to Top in town superstore | E20: 560066 | F20: 7899760082 | H20: WBSBURNS4 | J20: furniture | K20: 1003010018 | L20: Bookshelf | M20: FG01 | N20: 1 | O20: ONLINE | P20: 26060590003737 | Q20: WFFI452866 | R20: BLR LOCAL | S20: Normal Order | T20: Shipped | U20: 2026-05-23 | V20: 2026-05-23 | W20: 2026-06-10 | X20: 2026-06-16 | Y20: 2026-06-07T15:36:00 | Z20: 2026-06-09T21:09:45 | AA20: Breached | AB20: 0 | AD20: =VLOOKUP(Q20,'[1]an1asv_22-06-2026_06-23-43'!$B:$OA,3,0) -> reachedathub | AE20: =VLOOKUP(Q20,'[1]an1asv_22-06-2026_06-23-43'!$B:$OA,147,0) -> Customer Request for Future Date Delivery | AF20: =VLOOKUP(Q20,'[1]an1asv_22-06-2026_06-23-43'!$B:$OA,48,0) -> 46200 | AG20: =VLOOKUP(F20,Response!$A:$B,2,0) -> #N/A | AH20: CFR | AI20: =AF20 -> 46200 | AJ20: =VLOOKUP(B20,'Ces, Esc, RTS and Retail'!$A:$B,2,0) -> #N/A | AK20: =VLOOKUP(F20,'Ces, Esc, RTS and Retail'!$D:$F,3,0) -> #N/A | AL20: =VLOOKUP(B20,'Ces, Esc, RTS and Retail'!$H:$H,1,0) -> #N/A | AM20: =VLOOKUP(Q20,'Ces, Esc, RTS and Retail'!$J:$J,1,0) -> #N/A | AN20: =VLOOKUP(Q20,'[2]Trip Manager Report(Updated)_V2'!$I:$Z,18,0) -> #N/A | AO20: =VLOOKUP(E20,'Ces, Esc, RTS and Retail'!$L:$L,1,0) -> #N/A | AP20: =VLOOKUP(Q20,Response!$H:$M,5,0) -> #N/A
A21: Wakefit | B21: ORDER202605ldgHkv | C21: Anvith Hegde | D21: No 16, 1, Cox Town, Home well towers sun | E21: 560005 | F21: 7676171571 | G21: 7676171571 | H21: WTVUHEIST | J21: furniture | K21: 1007000862 | L21: Tv Unit | M21: FG01 | N21: 1 | O21: COD | P21: 26050590016893 | Q21: WFFI448097 | R21: BLR LOCAL | S21: Normal Order | T21: Shipped | U21: 2026-05-24 | V21: 2026-05-24 | W21: 2026-06-07 | X21: 2026-06-08 | Y21: 2026-05-30T20:11:04 | Z21: 2026-06-13T20:23:27 | AA21: Breached | AB21: 0 | AD21: =VLOOKUP(Q21,'[1]an1asv_22-06-2026_06-23-43'!$B:$OA,3,0) -> reachedathub | AE21: =VLOOKUP(Q21,'[1]an1asv_22-06-2026_06-23-43'!$B:$OA,147,0) -> CNR/ No Date from Customer | AF21: =VLOOKUP(Q21,'[1]an1asv_22-06-2026_06-23-43'!$B:$OA,48,0) -> 46196 | AG21: =VLOOKUP(F21,Response!$A:$B,2,0) -> #N/A | AH21: CNR | AJ21: =VLOOKUP(B21,'Ces, Esc, RTS and Retail'!$A:$B,2,0) -> #N/A | AK21: =VLOOKUP(F21,'Ces, Esc, RTS and Retail'!$D:$F,3,0) -> #N/A | AL21: =VLOOKUP(B21,'Ces, Esc, RTS and Retail'!$H:$H,1,0) -> #N/A | AM21: =VLOOKUP(Q21,'Ces, Esc, RTS and Retail'!$J:$J,1,0) -> #N/A | AN21: =VLOOKUP(Q21,'[2]Trip Manager Report(Updated)_V2'!$I:$Z,18,0) -> #N/A | AO21: =VLOOKUP(E21,'Ces, Esc, RTS and Retail'!$L:$L,1,0) -> #N/A | AP21: =VLOOKUP(Q21,Response!$H:$M,5,0) -> #N/A
A22: Wakefit_Retail | B22: ORDER202603o3FbHd | C22: ABHISHEK SHARMA | D22: Comfort Aanandaranga, Flat 101, First Floor, No. 12, 1st cross road, Srinivas Colony, Sudhamnagar,Bengaluru | E22: 560027 | F22: 8147713806 | G22: 8147115142 | H22: WMDINESLMORS6AB | J22: furniture | K22: 1001026208 | L22: Metal Dining Table | M22: FG01 | N22: 1 | O22: ONLINE | P22: 26060590002271 | Q22: WFFI451420 | R22: BLR LOCAL | S22: Normal Order | T22: Shipped | U22: 2026-03-22 | V22: 2026-05-24 | W22: 2026-06-22 | X22: 2026-06-22 | Y22: 2026-06-05T07:04:49 | Z22: 2026-06-14T20:08:49 | AA22: Breached | AB22: 0 | AD22: =VLOOKUP(Q22,'[1]an1asv_22-06-2026_06-23-43'!$B:$OA,3,0) -> reachedathub | AE22: =VLOOKUP(Q22,'[1]an1asv_22-06-2026_06-23-43'!$B:$OA,147,0) -> Customer Request for Future Date Delivery | AF22: =VLOOKUP(Q22,'[1]an1asv_22-06-2026_06-23-43'!$B:$OA,48,0) -> 46205 | AG22: =VLOOKUP(F22,Response!$A:$B,2,0) -> #N/A | AH22: CFR | AI22: =AF22 -> 46205 | AJ22: =VLOOKUP(B22,'Ces, Esc, RTS and Retail'!$A:$B,2,0) -> #N/A | AK22: =VLOOKUP(F22,'Ces, Esc, RTS and Retail'!$D:$F,3,0) -> #N/A | AL22: =VLOOKUP(B22,'Ces, Esc, RTS and Retail'!$H:$H,1,0) -> #N/A | AM22: =VLOOKUP(Q22,'Ces, Esc, RTS and Retail'!$J:$J,1,0) -> #N/A | AN22: =VLOOKUP(Q22,'[2]Trip Manager Report(Updated)_V2'!$I:$Z,18,0) -> #N/A | AO22: =VLOOKUP(E22,'Ces, Esc, RTS and Retail'!$L:$L,1,0) -> #N/A | AP22: =VLOOKUP(Q22,Response!$H:$M,5,0) -> #N/A
A23: Wakefit_Retail | B23: ORDER202603o3FbHd | C23: ABHISHEK SHARMA | D23: Comfort Aanandaranga, Flat 101, First Floor, No. 12, 1st cross road, Srinivas Colony, Sudhamnagar,Bengaluru | E23: 560027 | F23: 8147713806 | G23: 8147115142 | H23: WMCFTPRANGRCOB | J23: furniture | K23: 1007103227 | L23: Metal Coffee Table | M23: FG01 | N23: 1 | O23: ONLINE | P23: 26060590001211 | Q23: WFFWI216269 | R23: BLR LOCAL | S23: Normal Order | T23: Shipped | U23: 2026-03-22 | V23: 2026-05-24 | W23: 2026-06-22 | X23: 2026-06-22 | Y23: 2026-06-02T22:04:00 | Z23: 2026-06-14T20:08:49 | AA23: Breached | AB23: 0 | AD23: =VLOOKUP(Q23,'[1]an1asv_22-06-2026_06-23-43'!$B:$OA,3,0) -> reachedathub | AE23: =VLOOKUP(Q23,'[1]an1asv_22-06-2026_06-23-43'!$B:$OA,147,0) -> Customer Request for Future Date Delivery | AF23: =VLOOKUP(Q23,'[1]an1asv_22-06-2026_06-23-43'!$B:$OA,48,0) -> 46205 | AG23: =VLOOKUP(F23,Response!$A:$B,2,0) -> #N/A | AH23: CFR | AI23: =AF23 -> 46205 | AJ23: =VLOOKUP(B23,'Ces, Esc, RTS and Retail'!$A:$B,2,0) -> #N/A | AK23: =VLOOKUP(F23,'Ces, Esc, RTS and Retail'!$D:$F,3,0) -> #N/A | AL23: =VLOOKUP(B23,'Ces, Esc, RTS and Retail'!$H:$H,1,0) -> #N/A | AM23: =VLOOKUP(Q23,'Ces, Esc, RTS and Retail'!$J:$J,1,0) -> #N/A | AN23: =VLOOKUP(Q23,'[2]Trip Manager Report(Updated)_V2'!$I:$Z,18,0) -> #N/A | AO23: =VLOOKUP(E23,'Ces, Esc, RTS and Retail'!$L:$L,1,0) -> #N/A | AP23: =VLOOKUP(Q23,Response!$H:$M,5,0) -> #N/A
A24: Wakefit_Retail | B24: ORDER202605AGEQsN | C24: Prakash Puvvada | D24: Flat No 118 1st floor PSR AUSTIN APARTMENT, Hosahalli Road, Sompura gate | E24: 562125 | F24: 8106964687 | H24: WEWB7860HYSTESSERCW | I24: 78x60 inch | J24: furniture | K24: 1001033590 | L24: Engineered Wood Bed | M24: FG01 | N24: 1 | O24: ONLINE | P24: 26060590009829 | Q24: WFFI459779 | R24: BLR LOCAL | S24: Normal Order | T24: Shipped | U24: 2026-05-24 | V24: 2026-05-24 | W24: 2026-06-21 | X24: 2026-06-22 | Y24: 2026-06-19T22:21:54 | Z24: 2026-06-20T22:09:12 | AA24: Breached | AB24: 0 | AD24: =VLOOKUP(Q24,'[1]an1asv_22-06-2026_06-23-43'!$B:$OA,3,0) -> reachedathub | AE24: =VLOOKUP(Q24,'[1]an1asv_22-06-2026_06-23-43'!$B:$OA,147,0) -> Planned | AF24: =VLOOKUP(Q24,'[1]an1asv_22-06-2026_06-23-43'!$B:$OA,48,0) -> 46195 | AG24: =VLOOKUP(F24,Response!$A:$B,2,0) -> #N/A | AH24: Planned | AJ24: =VLOOKUP(B24,'Ces, Esc, RTS and Retail'!$A:$B,2,0) -> #N/A | AK24: =VLOOKUP(F24,'Ces, Esc, RTS and Retail'!$D:$F,3,0) -> #N/A | AL24: =VLOOKUP(B24,'Ces, Esc, RTS and Retail'!$H:$H,1,0) -> #N/A | AM24: =VLOOKUP(Q24,'Ces, Esc, RTS and Retail'!$J:$J,1,0) -> #N/A | AN24: =VLOOKUP(Q24,'[2]Trip Manager Report(Updated)_V2'!$I:$Z,18,0) -> INSUFFICIENT TIME | AO24: =VLOOKUP(E24,'Ces, Esc, RTS and Retail'!$L:$L,1,0) -> #N/A | AP24: =VLOOKUP(Q24,Response!$H:$M,5,0) -> #N/A
A25: Wakefit_Retail | B25: ORDER202605Mmtvak | C25: chandan GS | D25: #35, 1 st floor 17 th cross muthyalanagar Near DC golden lotus Apartment Benaglauru 560054 | E25: 560054 | F25: 7353939151 | G25: 9739915331 | H25: WEWB7872HYSTESSERCW | I25: 78x72 inch | J25: furniture | K25: 1001033589 | L25: Engineered Wood Bed | M25: FG01 | N25: 1 | O25: ONLINE | P25: 26060590009793 | Q25: WFFI459752 | R25: BLR LOCAL | S25: Normal Order | T25: Shipped | U25: 2026-05-24 | V25: 2026-05-24 | W25: 2026-06-21 | X25: 2026-06-22 | Y25: 2026-06-19T22:21:14 | Z25: 2026-06-20T20:45:33 | AA25: Breached | AB25: 0 | AD25: =VLOOKUP(Q25,'[1]an1asv_22-06-2026_06-23-43'!$B:$OA,3,0) -> reachedathub | AE25: =VLOOKUP(Q25,'[1]an1asv_22-06-2026_06-23-43'!$B:$OA,147,0) -> CUSTOMER FUTURE REQUEST | AF25: =VLOOKUP(Q25,'[1]an1asv_22-06-2026_06-23-43'!$B:$OA,48,0) -> 46195 | AG25: =VLOOKUP(F25,Response!$A:$B,2,0) -> 1 | AH25: Planned | AJ25: =VLOOKUP(B25,'Ces, Esc, RTS and Retail'!$A:$B,2,0) -> #N/A | AK25: =VLOOKUP(F25,'Ces, Esc, RTS and Retail'!$D:$F,3,0) -> #N/A | AL25: =VLOOKUP(B25,'Ces, Esc, RTS and Retail'!$H:$H,1,0) -> #N/A | AM25: =VLOOKUP(Q25,'Ces, Esc, RTS and Retail'!$J:$J,1,0) -> #N/A | AN25: =VLOOKUP(Q25,'[2]Trip Manager Report(Updated)_V2'!$I:$Z,18,0) -> CUSTOMER FUTURE REQUEST | AO25: =VLOOKUP(E25,'Ces, Esc, RTS and Retail'!$L:$L,1,0) -> #N/A | AP25: =VLOOKUP(Q25,Response!$H:$M,5,0) -> #N/A
A26: Wakefit_Retail | B26: ORDER202605zaSW72 | C26: Sourabh JAIN | D26: B019, Ground Floor, Samhita Greenwoods, Thubarahalli, Bangalore, Karnataka | E26: 560066 | F26: 8553246986 | H26: WEWB7860HYSUPOGRTAURUSR4 | I26: 78x60 inch | J26: furniture | K26: 1007003128 | L26: Engineered Wood Bed | M26: FG01 | N26: 1 | O26: ONLINE | P26: 26050590015502 | Q26: WFFI446325 | R26: BLR LOCAL | S26: Normal Order | T26: Shipped | U26: 2026-05-24 | V26: 2026-05-24 | W26: 2026-06-06 | X26: 2026-06-07 | Y26: 2026-05-28T09:41:39 | Z26: 2026-06-06T21:44:57 | AA26: Breached | AB26: 0 | AD26: =VLOOKUP(Q26,'[1]an1asv_22-06-2026_06-23-43'!$B:$OA,3,0) -> reachedathub | AE26: =VLOOKUP(Q26,'[1]an1asv_22-06-2026_06-23-43'!$B:$OA,147,0) -> Customer Request for Future Date Delivery | AF26: =VLOOKUP(Q26,'[1]an1asv_22-06-2026_06-23-43'!$B:$OA,48,0) -> 46208 | AG26: =VLOOKUP(F26,Response!$A:$B,2,0) -> #N/A | AH26: CFR | AI26: =AF26 -> 46208 | AJ26: =VLOOKUP(B26,'Ces, Esc, RTS and Retail'!$A:$B,2,0) -> #N/A | AK26: =VLOOKUP(F26,'Ces, Esc, RTS and Retail'!$D:$F,3,0) -> #N/A | AL26: =VLOOKUP(B26,'Ces, Esc, RTS and Retail'!$H:$H,1,0) -> #N/A | AM26: =VLOOKUP(Q26,'Ces, Esc, RTS and Retail'!$J:$J,1,0) -> #N/A | AN26: =VLOOKUP(Q26,'[2]Trip Manager Report(Updated)_V2'!$I:$Z,18,0) -> #N/A | AO26: =VLOOKUP(E26,'Ces, Esc, RTS and Retail'!$L:$L,1,0) -> #N/A | AP26: =VLOOKUP(Q26,Response!$H:$M,5,0) -> #N/A
A27: Wakefit | B27: ORDER202605MPY3Dx | C27: Yogesh Mallik | D27: C305, 3, TVS Emerald Jardin, Manipal County Road | E27: 560068 | F27: 7676187519 | G27: 7676187519 | H27: WEWB7860HYSHALOSFW | I27: 78x60 inch | J27: furniture | K27: 1001033493 | L27: Engineered Wood Bed | M27: FG01 | N27: 1 | O27: ONLINE | P27: 26060590001218 | Q27: WFFI449914 | R27: BLR LOCAL | S27: Normal Order | T27: Docketed | U27: 2026-05-25 | V27: 2026-05-25 | W27: 2026-06-21 | X27: 2026-06-22 | Y27: 2026-06-02T22:04:10 | AA27: Breached | AB27: 0 | AD27: =VLOOKUP(Q27,'[1]an1asv_22-06-2026_06-23-43'!$B:$OA,3,0) -> reachedathub | AE27: =VLOOKUP(Q27,'[1]an1asv_22-06-2026_06-23-43'!$B:$OA,147,0) -> Customer Request for Future Date Delivery | AF27: =VLOOKUP(Q27,'[1]an1asv_22-06-2026_06-23-43'!$B:$OA,48,0) -> 46197 | AG27: =VLOOKUP(F27,Response!$A:$B,2,0) -> #N/A | AH27: CFR | AI27: =AF27 -> 46197 | AJ27: =VLOOKUP(B27,'Ces, Esc, RTS and Retail'!$A:$B,2,0) -> #N/A | AK27: =VLOOKUP(F27,'Ces, Esc, RTS and Retail'!$D:$F,3,0) -> 46197 | AL27: =VLOOKUP(B27,'Ces, Esc, RTS and Retail'!$H:$H,1,0) -> #N/A | AM27: =VLOOKUP(Q27,'Ces, Esc, RTS and Retail'!$J:$J,1,0) -> #N/A | AN27: =VLOOKUP(Q27,'[2]Trip Manager Report(Updated)_V2'!$I:$Z,18,0) -> #N/A | AO27: =VLOOKUP(E27,'Ces, Esc, RTS and Retail'!$L:$L,1,0) -> #N/A | AP27: =VLOOKUP(Q27,Response!$H:$M,5,0) -> #N/A
A28: Wakefit_Retail | B28: ORDER202605qUUGPK | C28: Raghavendra | D28: No 86 Channenahalli magadi main road pipeline road | E28: 562130 | F28: 9844564837 | G28: 9620123412 | H28: WWRB3S4D2MH2SH3TYRIANPPB | J28: furniture | K28: 1001029025 | L28: Wardrobes | M28: FG01 | N28: 1 | O28: ONLINE | P28: 26060590010658 | Q28: WFFI460885 | R28: BLR LOCAL | S28: Normal Order | T28: Docketed | U28: 2026-05-25 | V28: 2026-05-25 | W28: 2026-06-21 | X28: 2026-06-25 | Y28: 2026-06-22T09:36:02 | AA28: P1 | AB28: 0 | AD28: =VLOOKUP(Q28,'[1]an1asv_22-06-2026_06-23-43'!$B:$OA,3,0) -> reachedathub | AE28: =VLOOKUP(Q28,'[1]an1asv_22-06-2026_06-23-43'!$B:$OA,147,0) -> 0 | AF28: =VLOOKUP(Q28,'[1]an1asv_22-06-2026_06-23-43'!$B:$OA,48,0) -> 46195 | AG28: =VLOOKUP(F28,Response!$A:$B,2,0) -> #N/A | AH28: Outside Service Location | AJ28: =VLOOKUP(B28,'Ces, Esc, RTS and Retail'!$A:$B,2,0) -> #N/A | AK28: =VLOOKUP(F28,'Ces, Esc, RTS and Retail'!$D:$F,3,0) -> #N/A | AL28: =VLOOKUP(B28,'Ces, Esc, RTS and Retail'!$H:$H,1,0) -> #N/A | AM28: =VLOOKUP(Q28,'Ces, Esc, RTS and Retail'!$J:$J,1,0) -> #N/A | AN28: =VLOOKUP(Q28,'[2]Trip Manager Report(Updated)_V2'!$I:$Z,18,0) -> #N/A | AO28: =VLOOKUP(E28,'Ces, Esc, RTS and Retail'!$L:$L,1,0) -> 562130 | AP28: =VLOOKUP(Q28,Response!$H:$M,5,0) -> #N/A
A29: Wakefit_Retail | B29: ORDER202605mSiBNx | C29: Tony Pius | D29: No 77/38 1st main 11th cross Bharathi Layout SG Palya | E29: 560029 | F29: 9844142957 | H29: WEWB7860STESSERCW | I29: 78x60 inch | J29: furniture | K29: 1001033592 | L29: Engineered Wood Bed | M29: FG01 | N29: 1 | O29: ONLINE | P29: 26060590010669 | Q29: WFFI460896 | R29: BLR LOCAL | S29: Normal Order | T29: Docketed | U29: 2026-05-25 | V29: 2026-05-25 | W29: 2026-06-21 | X29: 2026-06-22 | Y29: 2026-06-22T09:36:22 | AA29: Breached | AB29: 0 | AD29: =VLOOKUP(Q29,'[1]an1asv_22-06-2026_06-23-43'!$B:$OA,3,0) -> reachedathub | AE29: =VLOOKUP(Q29,'[1]an1asv_22-06-2026_06-23-43'!$B:$OA,147,0) -> 0 | AF29: =VLOOKUP(Q29,'[1]an1asv_22-06-2026_06-23-43'!$B:$OA,48,0) -> 46195 | AG29: =VLOOKUP(F29,Response!$A:$B,2,0) -> #N/A | AH29: CNR | AJ29: =VLOOKUP(B29,'Ces, Esc, RTS and Retail'!$A:$B,2,0) -> #N/A | AK29: =VLOOKUP(F29,'Ces, Esc, RTS and Retail'!$D:$F,3,0) -> #N/A | AL29: =VLOOKUP(B29,'Ces, Esc, RTS and Retail'!$H:$H,1,0) -> #N/A | AM29: =VLOOKUP(Q29,'Ces, Esc, RTS and Retail'!$J:$J,1,0) -> #N/A | AN29: =VLOOKUP(Q29,'[2]Trip Manager Report(Updated)_V2'!$I:$Z,18,0) -> #N/A | AO29: =VLOOKUP(E29,'Ces, Esc, RTS and Retail'!$L:$L,1,0) -> #N/A | AP29: =VLOOKUP(Q29,Response!$H:$M,5,0) -> #N/A
A30: Amazon | B30: 406-2931917-2985941 | C30: Sushant Mishra | D30: Munnekolal, Marathali Jaipur roti point building, 3rd floor , flat number C9 | E30: 560037 | F30: 8240196250 | H30: WWRB2DMH1GINGHAMUTR2 | J30: furniture | K30: 1007129110 | L30: Wardrobes | M30: FG01 | N30: 1 | O30: ONLINE | P30: 26060590009240 | Q30: WFFI458997 | R30: BLR LOCAL | S30: Normal Order | T30: Shipped | U30: 2026-05-25 | V30: 2026-05-25 | W30: 2026-06-16 | X30: 2026-06-22 | Y30: 2026-06-18T17:35:59 | Z30: 2026-06-20T19:28:47 | AA30: Breached | AB30: 0 | AD30: =VLOOKUP(Q30,'[1]an1asv_22-06-2026_06-23-43'!$B:$OA,3,0) -> reachedathub | AE30: =VLOOKUP(Q30,'[1]an1asv_22-06-2026_06-23-43'!$B:$OA,147,0) -> Planned | AF30: =VLOOKUP(Q30,'[1]an1asv_22-06-2026_06-23-43'!$B:$OA,48,0) -> 46195 | AG30: =VLOOKUP(F30,Response!$A:$B,2,0) -> #N/A | AH30: CNR | AJ30: =VLOOKUP(B30,'Ces, Esc, RTS and Retail'!$A:$B,2,0) -> #N/A | AK30: =VLOOKUP(F30,'Ces, Esc, RTS and Retail'!$D:$F,3,0) -> #N/A | AL30: =VLOOKUP(B30,'Ces, Esc, RTS and Retail'!$H:$H,1,0) -> #N/A | AM30: =VLOOKUP(Q30,'Ces, Esc, RTS and Retail'!$J:$J,1,0) -> #N/A | AN30: =VLOOKUP(Q30,'[2]Trip Manager Report(Updated)_V2'!$I:$Z,18,0) -> CUSTOMER NOT REACHABLE | AO30: =VLOOKUP(E30,'Ces, Esc, RTS and Retail'!$L:$L,1,0) -> #N/A | AP30: =VLOOKUP(Q30,Response!$H:$M,5,0) -> #N/A
A31: Amazon | B31: 408-7252058-8797147 | C31: Surabhi Sheshadri | D31: 106, Salarpuria Cambridge residency Ulsoor | E31: 560008 | F31: 9819393551 | H31: WWRB3TWILLDBR2 | J31: furniture | K31: 1007124269 | L31: Wardrobes | M31: FG01 | N31: 1 | O31: ONLINE | P31: 26060590002389 | Q31: WFFI451529 | R31: BLR LOCAL | S31: Normal Order | T31: Docketed | U31: 2026-05-26 | V31: 2026-05-26 | W31: 2026-06-17 | X31: 2026-06-23 | Y31: 2026-06-05T12:55:58 | AA31: Breached | AB31: 0 | AD31: =VLOOKUP(Q31,'[1]an1asv_22-06-2026_06-23-43'!$B:$OA,3,0) -> reachedathub | AE31: =VLOOKUP(Q31,'[1]an1asv_22-06-2026_06-23-43'!$B:$OA,147,0) -> CNR/ No Date from Customer | AF31: =VLOOKUP(Q31,'[1]an1asv_22-06-2026_06-23-43'!$B:$OA,48,0) -> 46196 | AG31: =VLOOKUP(F31,Response!$A:$B,2,0) -> #N/A | AH31: CNR | AJ31: =VLOOKUP(B31,'Ces, Esc, RTS and Retail'!$A:$B,2,0) -> #N/A | AK31: =VLOOKUP(F31,'Ces, Esc, RTS and Retail'!$D:$F,3,0) -> #N/A | AL31: =VLOOKUP(B31,'Ces, Esc, RTS and Retail'!$H:$H,1,0) -> #N/A | AM31: =VLOOKUP(Q31,'Ces, Esc, RTS and Retail'!$J:$J,1,0) -> #N/A | AN31: =VLOOKUP(Q31,'[2]Trip Manager Report(Updated)_V2'!$I:$Z,18,0) -> #N/A | AO31: =VLOOKUP(E31,'Ces, Esc, RTS and Retail'!$L:$L,1,0) -> #N/A | AP31: =VLOOKUP(Q31,Response!$H:$M,5,0) -> 0
A32: Wakefit_Retail | B32: ORDER202603PbfafE | C32: NAWAL KISHORE LODHA | D32: VILLA NO 134 PRESTIGE SILVER OAK ECC ROAD WHITEFIELD | E32: 560066 | F32: 9972512512 | H32: WEWB7860HYSRUBBLE | I32: 78x60 inch | J32: furniture | K32: 1001021918 | L32: Engineered Wood Bed | M32: FG01 | N32: 1 | O32: ONLINE | P32: 26060590010217 | Q32: WFFI460440 | R32: BLR LOCAL | S32: Replacement | T32: Docketed | U32: 2026-05-26 | V32: 2026-05-26 | W32: 2026-06-21 | X32: 2026-06-22 | Y32: 2026-06-21T11:41:14 | AA32: Breached | AB32: 0 | AD32: =VLOOKUP(Q32,'[1]an1asv_22-06-2026_06-23-43'!$B:$OA,3,0) -> reachedathub | AE32: =VLOOKUP(Q32,'[1]an1asv_22-06-2026_06-23-43'!$B:$OA,147,0) -> 0 | AF32: =VLOOKUP(Q32,'[1]an1asv_22-06-2026_06-23-43'!$B:$OA,48,0) -> 46195 | AG32: =VLOOKUP(F32,Response!$A:$B,2,0) -> #N/A | AH32: CNR | AJ32: =VLOOKUP(B32,'Ces, Esc, RTS and Retail'!$A:$B,2,0) -> #N/A | AK32: =VLOOKUP(F32,'Ces, Esc, RTS and Retail'!$D:$F,3,0) -> #N/A | AL32: =VLOOKUP(B32,'Ces, Esc, RTS and Retail'!$H:$H,1,0) -> #N/A | AM32: =VLOOKUP(Q32,'Ces, Esc, RTS and Retail'!$J:$J,1,0) -> #N/A | AN32: =VLOOKUP(Q32,'[2]Trip Manager Report(Updated)_V2'!$I:$Z,18,0) -> #N/A | AO32: =VLOOKUP(E32,'Ces, Esc, RTS and Retail'!$L:$L,1,0) -> #N/A | AP32: =VLOOKUP(Q32,Response!$H:$M,5,0) -> #N/A
A33: Wakefit_Retail | B33: ORDER202605dyR4zG | C33: divya | D33: #68,Arihant Castle Apartment Flat no 301, 4th floor , shankarmutt main road bangalore - 560004 | E33: 560004 | F33: 9902362000 | H33: WCFTJAVA | J33: furniture | K33: 1003010011 | L33: Coffee Table | M33: FG01 | N33: 1 | O33: PREPAID-CASH | P33: 26060590010661 | Q33: WFFI460880 | R33: BLR LOCAL | S33: Normal Order | T33: Docketed | U33: 2026-05-26 | V33: 2026-05-26 | W33: 2026-06-21 | X33: 2026-06-22 | Y33: 2026-06-22T09:36:01 | AA33: Breached | AB33: 0 | AD33: =VLOOKUP(Q33,'[1]an1asv_22-06-2026_06-23-43'!$B:$OA,3,0) -> reachedathub | AE33: =VLOOKUP(Q33,'[1]an1asv_22-06-2026_06-23-43'!$B:$OA,147,0) -> 0 | AF33: =VLOOKUP(Q33,'[1]an1asv_22-06-2026_06-23-43'!$B:$OA,48,0) -> 46195 | AG33: =VLOOKUP(F33,Response!$A:$B,2,0) -> #N/A | AH33: CNR | AJ33: =VLOOKUP(B33,'Ces, Esc, RTS and Retail'!$A:$B,2,0) -> #N/A | AK33: =VLOOKUP(F33,'Ces, Esc, RTS and Retail'!$D:$F,3,0) -> #N/A | AL33: =VLOOKUP(B33,'Ces, Esc, RTS and Retail'!$H:$H,1,0) -> #N/A | AM33: =VLOOKUP(Q33,'Ces, Esc, RTS and Retail'!$J:$J,1,0) -> #N/A | AN33: =VLOOKUP(Q33,'[2]Trip Manager Report(Updated)_V2'!$I:$Z,18,0) -> #N/A | AO33: =VLOOKUP(E33,'Ces, Esc, RTS and Retail'!$L:$L,1,0) -> #N/A | AP33: =VLOOKUP(Q33,Response!$H:$M,5,0) -> #N/A
A34: Wakefit | B34: ORDER202605TdKrU4 | C34: David Anand | D34: 3, 44, Bethel house, 1st A Cross, BDS Layout, RK Hegde Nagar | E34: 560077 | F34: 9353561311 | G34: 9788925253 | H34: WWRB3TWILLCW | J34: furniture | K34: 1007100259 | L34: Wardrobes | M34: FG01 | N34: 1 | O34: ONLINE | P34: 26060590010263 | Q34: WFFI460481 | R34: BLR LOCAL | S34: Normal Order | T34: Docketed | U34: 2026-05-27 | V34: 2026-05-27 | W34: 2026-06-22 | X34: 2026-06-23 | Y34: 2026-06-21T11:42:23 | AA34: Breached | AB34: 0 | AD34: =VLOOKUP(Q34,'[1]an1asv_22-06-2026_06-23-43'!$B:$OA,3,0) -> reachedathub | AE34: =VLOOKUP(Q34,'[1]an1asv_22-06-2026_06-23-43'!$B:$OA,147,0) -> 0 | AF34: =VLOOKUP(Q34,'[1]an1asv_22-06-2026_06-23-43'!$B:$OA,48,0) -> 46195 | AG34: =VLOOKUP(F34,Response!$A:$B,2,0) -> #N/A | AH34: Planned | AJ34: =VLOOKUP(B34,'Ces, Esc, RTS and Retail'!$A:$B,2,0) -> #N/A | AK34: =VLOOKUP(F34,'Ces, Esc, RTS and Retail'!$D:$F,3,0) -> #N/A | AL34: =VLOOKUP(B34,'Ces, Esc, RTS and Retail'!$H:$H,1,0) -> #N/A | AM34: =VLOOKUP(Q34,'Ces, Esc, RTS and Retail'!$J:$J,1,0) -> #N/A | AN34: =VLOOKUP(Q34,'[2]Trip Manager Report(Updated)_V2'!$I:$Z,18,0) -> #N/A | AO34: =VLOOKUP(E34,'Ces, Esc, RTS and Retail'!$L:$L,1,0) -> #N/A | AP34: =VLOOKUP(Q34,Response!$H:$M,5,0) -> Yes
A35: Wakefit_Retail | B35: ORDER202605epfvW6 | C35: Paul Daniel | D35: 88/1, 2nd Floor, 7th Cross Rd, Athmananda Colony, RT Nagar, Bangalore - 560032 | E35: 560032 | F35: 8553736540 | G35: 8861042648 | H35: WSWB7860TIERHBTW | I35: 78x60 inch | J35: furniture | K35: 1007129571 | L35: Cot | M35: FG01 | N35: 1 | O35: ONLINE | P35: 26060590008892 | Q35: WFFI458515 | R35: BLR LOCAL | S35: Normal Order | T35: Shipped | U35: 2026-05-27 | V35: 2026-05-27 | W35: 2026-06-21 | X35: 2026-06-22 | Y35: 2026-06-18T09:06:10 | Z35: 2026-06-20T19:24:25 | AA35: Breached | AB35: 0 | AD35: =VLOOKUP(Q35,'[1]an1asv_22-06-2026_06-23-43'!$B:$OA,3,0) -> reachedathub | AE35: =VLOOKUP(Q35,'[1]an1asv_22-06-2026_06-23-43'!$B:$OA,147,0) -> Planned | AF35: =VLOOKUP(Q35,'[1]an1asv_22-06-2026_06-23-43'!$B:$OA,48,0) -> 46195 | AG35: =VLOOKUP(F35,Response!$A:$B,2,0) -> #N/A | AH35: CNR | AJ35: =VLOOKUP(B35,'Ces, Esc, RTS and Retail'!$A:$B,2,0) -> #N/A | AK35: =VLOOKUP(F35,'Ces, Esc, RTS and Retail'!$D:$F,3,0) -> #N/A | AL35: =VLOOKUP(B35,'Ces, Esc, RTS and Retail'!$H:$H,1,0) -> #N/A | AM35: =VLOOKUP(Q35,'Ces, Esc, RTS and Retail'!$J:$J,1,0) -> #N/A | AN35: =VLOOKUP(Q35,'[2]Trip Manager Report(Updated)_V2'!$I:$Z,18,0) -> CUSTOMER FUTURE REQUEST | AO35: =VLOOKUP(E35,'Ces, Esc, RTS and Retail'!$L:$L,1,0) -> #N/A | AP35: =VLOOKUP(Q35,Response!$H:$M,5,0) -> #N/A
A36: Wakefit | B36: ORDER202605IDlpYb | C36: Harish J | D36: No 235, VASISHTA, 9th Cross, Bapuji Layout, Vijayanagar, Bengaluru | E36: 560040 | F36: 9449262840 | G36: 9449262840 | H36: WWRB3TWILLDBR2 | J36: furniture | K36: 1007124269 | L36: Wardrobes | M36: FG01 | N36: 1 | O36: ONLINE | P36: 26060590002759 | Q36: WFFI451733 | R36: BLR LOCAL | S36: Normal Order | T36: Shipped | U36: 2026-05-27 | V36: 2026-05-27 | W36: 2026-06-24 | X36: 2026-06-25 | Y36: 2026-06-05T21:15:31 | Z36: 2026-06-21T21:07:41 | AA36: P1 | AB36: 0 | AD36: =VLOOKUP(Q36,'[1]an1asv_22-06-2026_06-23-43'!$B:$OA,3,0) -> reachedathub | AE36: =VLOOKUP(Q36,'[1]an1asv_22-06-2026_06-23-43'!$B:$OA,147,0) -> CNR/ No Date from Customer | AF36: =VLOOKUP(Q36,'[1]an1asv_22-06-2026_06-23-43'!$B:$OA,48,0) -> 46196 | AG36: =VLOOKUP(F36,Response!$A:$B,2,0) -> #N/A | AH36: Capcity Filled-Not Called | AJ36: =VLOOKUP(B36,'Ces, Esc, RTS and Retail'!$A:$B,2,0) -> #N/A | AK36: =VLOOKUP(F36,'Ces, Esc, RTS and Retail'!$D:$F,3,0) -> #N/A | AL36: =VLOOKUP(B36,'Ces, Esc, RTS and Retail'!$H:$H,1,0) -> #N/A | AM36: =VLOOKUP(Q36,'Ces, Esc, RTS and Retail'!$J:$J,1,0) -> #N/A | AN36: =VLOOKUP(Q36,'[2]Trip Manager Report(Updated)_V2'!$I:$Z,18,0) -> #N/A | AO36: =VLOOKUP(E36,'Ces, Esc, RTS and Retail'!$L:$L,1,0) -> #N/A | AP36: =VLOOKUP(Q36,Response!$H:$M,5,0) -> #N/A
A37: Wakefit | B37: ORDER202605XvXy8i | C37: Pooja | D37: Tower1-302, 3, Sattva Divinity, 9th cross, Pantharapalya, Nayandahalli, Bengaluru | E37: 560026 | F37: 9449262840 | G37: 8861848692 | H37: WWRB3TWILLCW | J37: furniture | K37: 1007100259 | L37: Wardrobes | M37: FG01 | N37: 1 | O37: ONLINE | P37: 26060590010259 | Q37: WFFI460479 | R37: BLR LOCAL | S37: Normal Order | T37: Docketed | U37: 2026-05-28 | V37: 2026-05-28 | W37: 2026-06-22 | X37: 2026-06-23 | Y37: 2026-06-21T11:42:14 | AA37: Breached | AB37: 0 | AD37: =VLOOKUP(Q37,'[1]an1asv_22-06-2026_06-23-43'!$B:$OA,3,0) -> reachedathub | AE37: =VLOOKUP(Q37,'[1]an1asv_22-06-2026_06-23-43'!$B:$OA,147,0) -> 0 | AF37: =VLOOKUP(Q37,'[1]an1asv_22-06-2026_06-23-43'!$B:$OA,48,0) -> 46195 | AG37: =VLOOKUP(F37,Response!$A:$B,2,0) -> #N/A | AH37: CNR | AJ37: =VLOOKUP(B37,'Ces, Esc, RTS and Retail'!$A:$B,2,0) -> #N/A | AK37: =VLOOKUP(F37,'Ces, Esc, RTS and Retail'!$D:$F,3,0) -> #N/A | AL37: =VLOOKUP(B37,'Ces, Esc, RTS and Retail'!$H:$H,1,0) -> #N/A | AM37: =VLOOKUP(Q37,'Ces, Esc, RTS and Retail'!$J:$J,1,0) -> #N/A | AN37: =VLOOKUP(Q37,'[2]Trip Manager Report(Updated)_V2'!$I:$Z,18,0) -> #N/A | AO37: =VLOOKUP(E37,'Ces, Esc, RTS and Retail'!$L:$L,1,0) -> #N/A | AP37: =VLOOKUP(Q37,Response!$H:$M,5,0) -> 0
A38: Wakefit | B38: ORDER2026053qD8Zl | C38: Yogesh Bhavsar | D38: A-405, 4, Mana Candela - 2, Kodathi, Sarjapur Road, Behind Wipro Sez. | E38: 560035 | F38: 9662160875 | G38: 9662160875 | H38: WEWB7872SASTRA | I38: 78x72 inch | J38: furniture | K38: 1007100292 | L38: Engineered Wood Bed | M38: FG01 | N38: 1 | O38: ONLINE | P38: 26060590010660 | Q38: WFFI460883 | R38: BLR LOCAL | S38: Normal Order | T38: Docketed | U38: 2026-05-28 | V38: 2026-05-28 | W38: 2026-06-21 | X38: 2026-06-22 | Y38: 2026-06-22T09:36:01 | AA38: Breached | AB38: 0 | AD38: =VLOOKUP(Q38,'[1]an1asv_22-06-2026_06-23-43'!$B:$OA,3,0) -> reachedathub | AE38: =VLOOKUP(Q38,'[1]an1asv_22-06-2026_06-23-43'!$B:$OA,147,0) -> 0 | AF38: =VLOOKUP(Q38,'[1]an1asv_22-06-2026_06-23-43'!$B:$OA,48,0) -> 46195 | AG38: =VLOOKUP(F38,Response!$A:$B,2,0) -> 1 | AH38: Planned | AJ38: =VLOOKUP(B38,'Ces, Esc, RTS and Retail'!$A:$B,2,0) -> #N/A | AK38: =VLOOKUP(F38,'Ces, Esc, RTS and Retail'!$D:$F,3,0) -> #N/A | AL38: =VLOOKUP(B38,'Ces, Esc, RTS and Retail'!$H:$H,1,0) -> #N/A | AM38: =VLOOKUP(Q38,'Ces, Esc, RTS and Retail'!$J:$J,1,0) -> #N/A | AN38: =VLOOKUP(Q38,'[2]Trip Manager Report(Updated)_V2'!$I:$Z,18,0) -> #N/A | AO38: =VLOOKUP(E38,'Ces, Esc, RTS and Retail'!$L:$L,1,0) -> #N/A | AP38: =VLOOKUP(Q38,Response!$H:$M,5,0) -> #N/A
A39: Wakefit_Retail | B39: ORDER202605prXreM | C39: Paniraj thanthry | D39: #405, 4th floor, Sairam Gardenia, near RGA Tech Park & Decathlon mart, Hadosiddapura, Chikkakannalli, Kodathi JHC, Karnatak | E39: 560035 | F39: 8431567630 | H39: WEWB7860HYSTESSERCW | I39: 78x60 inch | J39: furniture | K39: 1001033590 | L39: Engineered Wood Bed | M39: FG01 | N39: 1 | O39: ONLINE | P39: 26060590009799 | Q39: WFFI459754 | R39: BLR LOCAL | S39: Normal Order | T39: Docketed | U39: 2026-05-20 | V39: 2026-05-28 | W39: 2026-06-21 | X39: 2026-06-22 | Y39: 2026-06-19T22:21:15 | AA39: Breached | AB39: 0 | AD39: =VLOOKUP(Q39,'[1]an1asv_22-06-2026_06-23-43'!$B:$OA,3,0) -> reachedathub | AE39: =VLOOKUP(Q39,'[1]an1asv_22-06-2026_06-23-43'!$B:$OA,147,0) -> Customer Request for Future Date Delivery | AF39: =VLOOKUP(Q39,'[1]an1asv_22-06-2026_06-23-43'!$B:$OA,48,0) -> 46197 | AG39: =VLOOKUP(F39,Response!$A:$B,2,0) -> #N/A | AH39: CFR | AI39: =AF39 -> 46197 | AJ39: =VLOOKUP(B39,'Ces, Esc, RTS and Retail'!$A:$B,2,0) -> #N/A | AK39: =VLOOKUP(F39,'Ces, Esc, RTS and Retail'!$D:$F,3,0) -> #N/A | AL39: =VLOOKUP(B39,'Ces, Esc, RTS and Retail'!$H:$H,1,0) -> #N/A | AM39: =VLOOKUP(Q39,'Ces, Esc, RTS and Retail'!$J:$J,1,0) -> #N/A | AN39: =VLOOKUP(Q39,'[2]Trip Manager Report(Updated)_V2'!$I:$Z,18,0) -> #N/A | AO39: =VLOOKUP(E39,'Ces, Esc, RTS and Retail'!$L:$L,1,0) -> #N/A | AP39: =VLOOKUP(Q39,Response!$H:$M,5,0) -> #N/A
A40: Wakefit_Retail | B40: ORDER202605Z3H3cF | C40: Umar Lone | D40: Ajmera Lakeside Paradise, Flat No. D-205, D Block, 2nd Floor, Kempanahalli, Attur Layout, Yelahanka | E40: 560064 | F40: 9108520725 | G40: 950117183 | H40: WDINEARVWAC1NTBK | J40: furniture | K40: 1001026062 | L40: Metal Dining Chair | M40: FG01 | N40: 1 | O40: ONLINE | P40: 26060590010231 | Q40: WFFWI223215 | R40: BLR LOCAL | S40: Normal Order | T40: Docketed | U40: 2026-05-28 | V40: 2026-05-28 | W40: 2026-06-21 | X40: 2026-06-22 | Y40: 2026-06-21T11:41:40 | AA40: Breached | AB40: 0 | AD40: =VLOOKUP(Q40,'[1]an1asv_22-06-2026_06-23-43'!$B:$OA,3,0) -> reachedathub | AE40: =VLOOKUP(Q40,'[1]an1asv_22-06-2026_06-23-43'!$B:$OA,147,0) -> 0 | AF40: =VLOOKUP(Q40,'[1]an1asv_22-06-2026_06-23-43'!$B:$OA,48,0) -> 46195 | AG40: =VLOOKUP(F40,Response!$A:$B,2,0) -> 1 | AH40: Planned | AJ40: =VLOOKUP(B40,'Ces, Esc, RTS and Retail'!$A:$B,2,0) -> #N/A | AK40: =VLOOKUP(F40,'Ces, Esc, RTS and Retail'!$D:$F,3,0) -> #N/A | AL40: =VLOOKUP(B40,'Ces, Esc, RTS and Retail'!$H:$H,1,0) -> #N/A | AM40: =VLOOKUP(Q40,'Ces, Esc, RTS and Retail'!$J:$J,1,0) -> #N/A | AN40: =VLOOKUP(Q40,'[2]Trip Manager Report(Updated)_V2'!$I:$Z,18,0) -> #N/A | AO40: =VLOOKUP(E40,'Ces, Esc, RTS and Retail'!$L:$L,1,0) -> #N/A | AP40: =VLOOKUP(Q40,Response!$H:$M,5,0) -> #N/A
A41: Wakefit_Retail | B41: ORDER202605Z3H3cF | C41: Umar Lone | D41: Ajmera Lakeside Paradise, Flat No. D-205, D Block, 2nd Floor, Kempanahalli, Attur Layout, Yelahanka | E41: 560064 | F41: 9108520725 | G41: 950117183 | H41: WDINEARVWAC1NTBK | J41: furniture | K41: 1001026062 | L41: Metal Dining Chair | M41: FG01 | N41: 1 | O41: ONLINE | P41: 26060590010238 | Q41: WFFWI223216 | R41: BLR LOCAL | S41: Normal Order | T41: Docketed | U41: 2026-05-28 | V41: 2026-05-28 | W41: 2026-06-21 | X41: 2026-06-22 | Y41: 2026-06-21T11:41:40 | AA41: Breached | AB41: 0 | AD41: =VLOOKUP(Q41,'[1]an1asv_22-06-2026_06-23-43'!$B:$OA,3,0) -> reachedathub | AE41: =VLOOKUP(Q41,'[1]an1asv_22-06-2026_06-23-43'!$B:$OA,147,0) -> 0 | AF41: =VLOOKUP(Q41,'[1]an1asv_22-06-2026_06-23-43'!$B:$OA,48,0) -> 46195 | AG41: =VLOOKUP(F41,Response!$A:$B,2,0) -> 1 | AH41: Planned | AJ41: =VLOOKUP(B41,'Ces, Esc, RTS and Retail'!$A:$B,2,0) -> #N/A | AK41: =VLOOKUP(F41,'Ces, Esc, RTS and Retail'!$D:$F,3,0) -> #N/A | AL41: =VLOOKUP(B41,'Ces, Esc, RTS and Retail'!$H:$H,1,0) -> #N/A | AM41: =VLOOKUP(Q41,'Ces, Esc, RTS and Retail'!$J:$J,1,0) -> #N/A | AN41: =VLOOKUP(Q41,'[2]Trip Manager Report(Updated)_V2'!$I:$Z,18,0) -> #N/A | AO41: =VLOOKUP(E41,'Ces, Esc, RTS and Retail'!$L:$L,1,0) -> #N/A | AP41: =VLOOKUP(Q41,Response!$H:$M,5,0) -> #N/A
A42: Wakefit | B42: ORDER202605hrpLFf | C42: Utkarsh | D42: N035, 3, Assetz Marq - Phase 3, Kannamangala, Whitefield - Hoskote Rd. | E42: 560115 | F42: 8553178297 | G42: 8553178297 | H42: WEWB7860SCNTR | I42: 78x60 inch | J42: furniture | K42: 1001024520 | L42: Engineered Wood Bed | M42: FG01 | N42: 1 | O42: ONLINE | P42: 26060590010652 | Q42: WFFI460881 | R42: BLR LOCAL | S42: Normal Order | T42: Docketed | U42: 2026-05-28 | V42: 2026-05-28 | W42: 2026-06-21 | X42: 2026-06-23 | Y42: 2026-06-22T09:36:01 | AA42: Breached | AB42: 0 | AD42: =VLOOKUP(Q42,'[1]an1asv_22-06-2026_06-23-43'!$B:$OA,3,0) -> reachedathub | AE42: =VLOOKUP(Q42,'[1]an1asv_22-06-2026_06-23-43'!$B:$OA,147,0) -> 0 | AF42: =VLOOKUP(Q42,'[1]an1asv_22-06-2026_06-23-43'!$B:$OA,48,0) -> 46195 | AG42: =VLOOKUP(F42,Response!$A:$B,2,0) -> #N/A | AH42: Planned | AJ42: =VLOOKUP(B42,'Ces, Esc, RTS and Retail'!$A:$B,2,0) -> #N/A | AK42: =VLOOKUP(F42,'Ces, Esc, RTS and Retail'!$D:$F,3,0) -> #N/A | AL42: =VLOOKUP(B42,'Ces, Esc, RTS and Retail'!$H:$H,1,0) -> #N/A | AM42: =VLOOKUP(Q42,'Ces, Esc, RTS and Retail'!$J:$J,1,0) -> #N/A | AN42: =VLOOKUP(Q42,'[2]Trip Manager Report(Updated)_V2'!$I:$Z,18,0) -> #N/A | AO42: =VLOOKUP(E42,'Ces, Esc, RTS and Retail'!$L:$L,1,0) -> #N/A | AP42: =VLOOKUP(Q42,Response!$H:$M,5,0) -> Yes
A43: Wakefit | B43: ORDER202605rGs7FZ | C43: Deepthi G Gowda | D43: 167, 1, Channenahalli, Channenahalli Magadi Main Road | E43: 562130 | F43: 9019876343 | G43: 9019876343 | H43: WKSTSTACKL | J43: furniture | K43: 1007111446 | L43: Kids Study Table | M43: FG01 | N43: 1 | O43: ONLINE | P43: 26060590009846 | Q43: WFFI459797 | R43: BLR LOCAL | S43: Normal Order | T43: Docketed | U43: 2026-05-29 | V43: 2026-05-29 | W43: 2026-06-21 | X43: 2026-06-25 | Y43: 2026-06-19T22:22:15 | AA43: P1 | AB43: 0 | AD43: =VLOOKUP(Q43,'[1]an1asv_22-06-2026_06-23-43'!$B:$OA,3,0) -> reachedathub | AE43: =VLOOKUP(Q43,'[1]an1asv_22-06-2026_06-23-43'!$B:$OA,147,0) -> Outside Service Location | AF43: =VLOOKUP(Q43,'[1]an1asv_22-06-2026_06-23-43'!$B:$OA,48,0) -> 46196 | AG43: =VLOOKUP(F43,Response!$A:$B,2,0) -> #N/A | AH43: Outside Service Location | AJ43: =VLOOKUP(B43,'Ces, Esc, RTS and Retail'!$A:$B,2,0) -> #N/A | AK43: =VLOOKUP(F43,'Ces, Esc, RTS and Retail'!$D:$F,3,0) -> #N/A | AL43: =VLOOKUP(B43,'Ces, Esc, RTS and Retail'!$H:$H,1,0) -> #N/A | AM43: =VLOOKUP(Q43,'Ces, Esc, RTS and Retail'!$J:$J,1,0) -> #N/A | AN43: =VLOOKUP(Q43,'[2]Trip Manager Report(Updated)_V2'!$I:$Z,18,0) -> #N/A | AO43: =VLOOKUP(E43,'Ces, Esc, RTS and Retail'!$L:$L,1,0) -> 562130 | AP43: =VLOOKUP(Q43,Response!$H:$M,5,0) -> #N/A
A44: Wakefit | B44: ORDER202605QzQg6F | C44: Anshuman Sinha | D44: 2, Flat No 202, Block D, Keerthi Chalet Coconut Grove Layout, Horamavu | E44: 560043 | F44: 9844097333 | H44: WEWB7860SCNTR | I44: 78x60 inch | J44: furniture | K44: 1001024520 | L44: Engineered Wood Bed | M44: FG01 | N44: 1 | O44: ONLINE | P44: 26060590010657 | Q44: WFFI460888 | R44: BLR LOCAL | S44: Normal Order | T44: Docketed | U44: 2026-05-20 | V44: 2026-05-29 | W44: 2026-06-22 | X44: 2026-06-22 | Y44: 2026-06-22T09:36:10 | AA44: Breached | AB44: 0 | AD44: =VLOOKUP(Q44,'[1]an1asv_22-06-2026_06-23-43'!$B:$OA,3,0) -> reachedathub | AE44: =VLOOKUP(Q44,'[1]an1asv_22-06-2026_06-23-43'!$B:$OA,147,0) -> 0 | AF44: =VLOOKUP(Q44,'[1]an1asv_22-06-2026_06-23-43'!$B:$OA,48,0) -> 46195 | AG44: =VLOOKUP(F44,Response!$A:$B,2,0) -> #N/A | AH44: CNR | AJ44: =VLOOKUP(B44,'Ces, Esc, RTS and Retail'!$A:$B,2,0) -> #N/A | AK44: =VLOOKUP(F44,'Ces, Esc, RTS and Retail'!$D:$F,3,0) -> #N/A | AL44: =VLOOKUP(B44,'Ces, Esc, RTS and Retail'!$H:$H,1,0) -> #N/A | AM44: =VLOOKUP(Q44,'Ces, Esc, RTS and Retail'!$J:$J,1,0) -> #N/A | AN44: =VLOOKUP(Q44,'[2]Trip Manager Report(Updated)_V2'!$I:$Z,18,0) -> #N/A | AO44: =VLOOKUP(E44,'Ces, Esc, RTS and Retail'!$L:$L,1,0) -> #N/A | AP44: =VLOOKUP(Q44,Response!$H:$M,5,0) -> #N/A
A45: Wakefit_Retail | B45: ORDER202605nM80DS | C45: Hema L | D45: No-3, 2nd floor, Sapthagiri Nivasa, Karihobanahalli, Andharahalli Main Road | E45: 560091 | F45: 9108713224 | G45: 8453536682 | H45: WBSWILDE | J45: furniture | K45: 1003010026 | L45: Bookshelf | M45: FG01 | N45: 1 | O45: ONLINE | P45: 26060590010828 | Q45: WFFI461004 | R45: BLR LOCAL | S45: Normal Order | T45: Docketed | U45: 2026-05-29 | V45: 2026-05-29 | W45: 2026-06-22 | X45: 2026-06-23 | Y45: 2026-06-22T10:51:50 | AA45: Breached | AB45: 0 | AD45: =VLOOKUP(Q45,'[1]an1asv_22-06-2026_06-23-43'!$B:$OA,3,0) -> reachedathub | AE45: =VLOOKUP(Q45,'[1]an1asv_22-06-2026_06-23-43'!$B:$OA,147,0) -> 0 | AF45: =VLOOKUP(Q45,'[1]an1asv_22-06-2026_06-23-43'!$B:$OA,48,0) -> 46195 | AG45: =VLOOKUP(F45,Response!$A:$B,2,0) -> 1 | AH45: Planned | AJ45: =VLOOKUP(B45,'Ces, Esc, RTS and Retail'!$A:$B,2,0) -> #N/A | AK45: =VLOOKUP(F45,'Ces, Esc, RTS and Retail'!$D:$F,3,0) -> #N/A | AL45: =VLOOKUP(B45,'Ces, Esc, RTS and Retail'!$H:$H,1,0) -> #N/A | AM45: =VLOOKUP(Q45,'Ces, Esc, RTS and Retail'!$J:$J,1,0) -> #N/A | AN45: =VLOOKUP(Q45,'[2]Trip Manager Report(Updated)_V2'!$I:$Z,18,0) -> #N/A | AO45: =VLOOKUP(E45,'Ces, Esc, RTS and Retail'!$L:$L,1,0) -> #N/A | AP45: =VLOOKUP(Q45,Response!$H:$M,5,0) -> #N/A
A46: Flipkart | B46: OD337691787734982100 | C46: SHASHI KANT BHUSHAN | D46: S03 A Block PSR ASTER, V. Kallahalli Main Road, Volagerekallahalli | E46: 562125 | F46: 8828335796 | H46: WEWB7860HYSTAURUSR4 | I46: 78x60 inch | J46: furniture | K46: 1001019058 | L46: Engineered Wood Bed | M46: FG01 | N46: 1 | O46: ONLINE | P46: 26060590000913 | Q46: WFFI449863 | R46: BLR LOCAL | S46: Normal Order | T46: Docketed | U46: 2026-05-29 | V46: 2026-05-29 | W46: 2026-06-19 | X46: 2026-06-20 | Y46: 2026-06-02T15:36:59 | AA46: Breached | AB46: 0 | AD46: =VLOOKUP(Q46,'[1]an1asv_22-06-2026_06-23-43'!$B:$OA,3,0) -> reachedathub | AE46: =VLOOKUP(Q46,'[1]an1asv_22-06-2026_06-23-43'!$B:$OA,147,0) -> Customer Request for Future Date Delivery | AF46: =VLOOKUP(Q46,'[1]an1asv_22-06-2026_06-23-43'!$B:$OA,48,0) -> 46198 | AG46: =VLOOKUP(F46,Response!$A:$B,2,0) -> #N/A | AH46: CFR | AI46: =AF46 -> 46198 | AJ46: =VLOOKUP(B46,'Ces, Esc, RTS and Retail'!$A:$B,2,0) -> #N/A | AK46: =VLOOKUP(F46,'Ces, Esc, RTS and Retail'!$D:$F,3,0) -> #N/A | AL46: =VLOOKUP(B46,'Ces, Esc, RTS and Retail'!$H:$H,1,0) -> #N/A | AM46: =VLOOKUP(Q46,'Ces, Esc, RTS and Retail'!$J:$J,1,0) -> #N/A | AN46: =VLOOKUP(Q46,'[2]Trip Manager Report(Updated)_V2'!$I:$Z,18,0) -> #N/A | AO46: =VLOOKUP(E46,'Ces, Esc, RTS and Retail'!$L:$L,1,0) -> #N/A | AP46: =VLOOKUP(Q46,Response!$H:$M,5,0) -> #N/A
A47: Flipkart | B47: OD337691998549774100 | C47: Siyaram Singh | D47: Delhi Public School Bangalore North Delhi Public School Bangalore North, Srinivasa Nagar, Byappanahalli | E47: 562149 | F47: 9886515597 | H47: WWRB4DMH1GINGHAMFWR2 | J47: furniture | K47: 1007129100 | L47: Wardrobes | M47: FG01 | N47: 1 | O47: ONLINE | P47: 26060590008822 | Q47: WFFI458481 | R47: BLR LOCAL | S47: Normal Order | T47: Shipped | U47: 2026-05-29 | V47: 2026-05-29 | W47: 2026-06-19 | X47: 2026-06-20 | Y47: 2026-06-17T23:21:55 | Z47: 2026-06-20T20:15:33 | AA47: Breached | AB47: 0 | AD47: =VLOOKUP(Q47,'[1]an1asv_22-06-2026_06-23-43'!$B:$OA,3,0) -> reachedathub | AE47: =VLOOKUP(Q47,'[1]an1asv_22-06-2026_06-23-43'!$B:$OA,147,0) -> Planned | AF47: =VLOOKUP(Q47,'[1]an1asv_22-06-2026_06-23-43'!$B:$OA,48,0) -> 46195 | AG47: =VLOOKUP(F47,Response!$A:$B,2,0) -> #N/A | AH47: Outside Service Location | AJ47: =VLOOKUP(B47,'Ces, Esc, RTS and Retail'!$A:$B,2,0) -> #N/A | AK47: =VLOOKUP(F47,'Ces, Esc, RTS and Retail'!$D:$F,3,0) -> #N/A | AL47: =VLOOKUP(B47,'Ces, Esc, RTS and Retail'!$H:$H,1,0) -> #N/A | AM47: =VLOOKUP(Q47,'Ces, Esc, RTS and Retail'!$J:$J,1,0) -> #N/A | AN47: =VLOOKUP(Q47,'[2]Trip Manager Report(Updated)_V2'!$I:$Z,18,0) -> INSUFFICIENT TIME | AO47: =VLOOKUP(E47,'Ces, Esc, RTS and Retail'!$L:$L,1,0) -> 562149 | AP47: =VLOOKUP(Q47,Response!$H:$M,5,0) -> #N/A | AQ47: =VLOOKUP(B47,#REF!,9,0) -> #REF!
A48: Wakefit_Retail | B48: ORDER202605WiRSHB | C48: Sriya Raj | D48: 20/3 -2nd FLOOR VAYUR VIHAR LAYOUT VIHAR KODAGALAHATTI LAKE, HUNASAMARANAHALLI BENGALURU | E48: 562157 | F48: 9474227923 | G48: 9663499752 | H48: WDRUAZHA | J48: furniture | K48: 1007003037 | L48: Engineered Wood Dressing Table | M48: FG01 | N48: 1 | O48: ONLINE | P48: 26060590000469 | Q48: WFFI449360 | R48: BLR LOCAL | S48: Normal Order | T48: Docketed | U48: 2026-05-30 | V48: 2026-05-30 | W48: 2026-06-01 | X48: 2026-06-04 | Y48: 2026-06-01T18:42:08 | AA48: Breached | AB48: 0 | AD48: =VLOOKUP(Q48,'[1]an1asv_22-06-2026_06-23-43'!$B:$OA,3,0) -> reachedathub | AE48: =VLOOKUP(Q48,'[1]an1asv_22-06-2026_06-23-43'!$B:$OA,147,0) -> Outside Service Location | AF48: =VLOOKUP(Q48,'[1]an1asv_22-06-2026_06-23-43'!$B:$OA,48,0) -> 46196 | AG48: =VLOOKUP(F48,Response!$A:$B,2,0) -> #N/A | AH48: Outside Service Location | AJ48: =VLOOKUP(B48,'Ces, Esc, RTS and Retail'!$A:$B,2,0) -> #N/A | AK48: =VLOOKUP(F48,'Ces, Esc, RTS and Retail'!$D:$F,3,0) -> #N/A | AL48: =VLOOKUP(B48,'Ces, Esc, RTS and Retail'!$H:$H,1,0) -> #N/A | AM48: =VLOOKUP(Q48,'Ces, Esc, RTS and Retail'!$J:$J,1,0) -> #N/A | AN48: =VLOOKUP(Q48,'[2]Trip Manager Report(Updated)_V2'!$I:$Z,18,0) -> #N/A | AO48: =VLOOKUP(E48,'Ces, Esc, RTS and Retail'!$L:$L,1,0) -> 562157 | AP48: =VLOOKUP(Q48,Response!$H:$M,5,0) -> #N/A | AQ48: =VLOOKUP(B48,#REF!,9,0) -> #REF!
A49: Wakefit_Retail | B49: ORDER202605yT1mym | C49: SANJEEV AGAWRAL | D49: BRIGADE GATEWAY L,BLOCK 1301,26/1,DR RAJKUMAR ROAD MALLESHWARAM WEST,13TH FLOOR,BANGLORE,560055 | E49: 560055 | F49: 9964282111 | H49: WEWB7860HYSTESSERCW | I49: 78x60 inch | J49: furniture | K49: 1001033590 | L49: Engineered Wood Bed | M49: FG01 | N49: 1 | O49: PREPAID-CASH | P49: 26060590009816 | Q49: WFFI459769 | R49: BLR LOCAL | S49: Normal Order | T49: Docketed | U49: 2026-05-30 | V49: 2026-05-30 | W49: 2026-06-21 | X49: 2026-06-22 | Y49: 2026-06-19T22:21:35 | AA49: Breached | AB49: 0 | AD49: =VLOOKUP(Q49,'[1]an1asv_22-06-2026_06-23-43'!$B:$OA,3,0) -> reachedathub | AE49: =VLOOKUP(Q49,'[1]an1asv_22-06-2026_06-23-43'!$B:$OA,147,0) -> CNR/ No Date from Customer | AF49: =VLOOKUP(Q49,'[1]an1asv_22-06-2026_06-23-43'!$B:$OA,48,0) -> 46196 | AG49: =VLOOKUP(F49,Response!$A:$B,2,0) -> #N/A | AH49: CNR | AJ49: =VLOOKUP(B49,'Ces, Esc, RTS and Retail'!$A:$B,2,0) -> #N/A | AK49: =VLOOKUP(F49,'Ces, Esc, RTS and Retail'!$D:$F,3,0) -> #N/A | AL49: =VLOOKUP(B49,'Ces, Esc, RTS and Retail'!$H:$H,1,0) -> #N/A | AM49: =VLOOKUP(Q49,'Ces, Esc, RTS and Retail'!$J:$J,1,0) -> #N/A | AN49: =VLOOKUP(Q49,'[2]Trip Manager Report(Updated)_V2'!$I:$Z,18,0) -> #N/A | AO49: =VLOOKUP(E49,'Ces, Esc, RTS and Retail'!$L:$L,1,0) -> #N/A | AP49: =VLOOKUP(Q49,Response!$H:$M,5,0) -> #N/A
A50: Flipkart | B50: OD337699474550076100 | C50: Rajesh Saha | D50: Room no 116, Sri Lakshmi Venkateshwara Arcade, 4th Cross Thirumala Bakery Road, Chanasandra, ITBL, Kadugudi 3G Homes Crimson Layout, 4th cross, new extension, Channasandra ,Kadugodi | E50: 560067 | F50: 9435441894 | H50: WBSPROSE | J50: furniture | K50: 1003010025 | L50: Bookshelf | M50: FG01 | N50: 1 | O50: ONLINE | P50: 26060590010860 | Q50: WFFI461030 | R50: BLR LOCAL | S50: Normal Order | T50: Docketed | U50: 2026-05-30 | V50: 2026-05-30 | W50: 2026-06-11 | X50: 2026-06-12 | Y50: 2026-06-22T10:52:23 | AA50: Breached | AB50: 0 | AD50: =VLOOKUP(Q50,'[1]an1asv_22-06-2026_06-23-43'!$B:$OA,3,0) -> reachedathub | AE50: =VLOOKUP(Q50,'[1]an1asv_22-06-2026_06-23-43'!$B:$OA,147,0) -> 0 | AF50: =VLOOKUP(Q50,'[1]an1asv_22-06-2026_06-23-43'!$B:$OA,48,0) -> 46195 | AG50: =VLOOKUP(F50,Response!$A:$B,2,0) -> 1 | AH50: Planned | AJ50: =VLOOKUP(B50,'Ces, Esc, RTS and Retail'!$A:$B,2,0) -> #N/A | AK50: =VLOOKUP(F50,'Ces, Esc, RTS and Retail'!$D:$F,3,0) -> #N/A | AL50: =VLOOKUP(B50,'Ces, Esc, RTS and Retail'!$H:$H,1,0) -> #N/A | AM50: =VLOOKUP(Q50,'Ces, Esc, RTS and Retail'!$J:$J,1,0) -> #N/A | AN50: =VLOOKUP(Q50,'[2]Trip Manager Report(Updated)_V2'!$I:$Z,18,0) -> #N/A | AO50: =VLOOKUP(E50,'Ces, Esc, RTS and Retail'!$L:$L,1,0) -> #N/A | AP50: =VLOOKUP(Q50,Response!$H:$M,5,0) -> #N/A
A51: Wakefit | B51: ORDER202605xeJwSe | C51: Vandana Dhayalan | D51: 1592, 2, Atharva, 17th A Main, 5th Block, HBR layout | E51: 560043 | F51: 9886901963 | G51: 9886901963 | H51: WBSWILDE | J51: furniture | K51: 1003010026 | L51: Bookshelf | M51: FG01 | N51: 1 | O51: ONLINE | P51: 26060590010852 | Q51: WFFI461025 | R51: BLR LOCAL | S51: Normal Order | T51: Docketed | U51: 2026-05-30 | V51: 2026-05-30 | W51: 2026-06-22 | X51: 2026-06-23 | Y51: 2026-06-22T10:52:15 | AA51: Breached | AB51: 0 | AD51: =VLOOKUP(Q51,'[1]an1asv_22-06-2026_06-23-43'!$B:$OA,3,0) -> reachedathub | AE51: =VLOOKUP(Q51,'[1]an1asv_22-06-2026_06-23-43'!$B:$OA,147,0) -> 0 | AF51: =VLOOKUP(Q51,'[1]an1asv_22-06-2026_06-23-43'!$B:$OA,48,0) -> 46195 | AG51: =VLOOKUP(F51,Response!$A:$B,2,0) -> 1 | AH51: Planned | AJ51: =VLOOKUP(B51,'Ces, Esc, RTS and Retail'!$A:$B,2,0) -> #N/A | AK51: =VLOOKUP(F51,'Ces, Esc, RTS and Retail'!$D:$F,3,0) -> #N/A | AL51: =VLOOKUP(B51,'Ces, Esc, RTS and Retail'!$H:$H,1,0) -> #N/A | AM51: =VLOOKUP(Q51,'Ces, Esc, RTS and Retail'!$J:$J,1,0) -> #N/A | AN51: =VLOOKUP(Q51,'[2]Trip Manager Report(Updated)_V2'!$I:$Z,18,0) -> #N/A | AO51: =VLOOKUP(E51,'Ces, Esc, RTS and Retail'!$L:$L,1,0) -> #N/A | AP51: =VLOOKUP(Q51,Response!$H:$M,5,0) -> #N/A
A52: Wakefit_Retail | B52: ORDER2026055NlLkq | C52: SRI MAHALAKSHMI ENTERPRISE | D52: NO 980 saikutir 2nd railway parallel road 1st A main kengeri satellite town | E52: 560060 | F52: 9901780150 | H52: WBSBARNES | J52: furniture | K52: 1003010016 | L52: Bookshelf | M52: FG01 | N52: 1 | O52: ONLINE | P52: 26060590010886 | Q52: WFFI461058 | R52: BLR LOCAL | S52: Normal Order | T52: Docketed | U52: 2026-05-30 | V52: 2026-05-30 | W52: 2026-06-22 | X52: 2026-06-23 | Y52: 2026-06-22T10:52:57 | AA52: Breached | AB52: 0 | AD52: =VLOOKUP(Q52,'[1]an1asv_22-06-2026_06-23-43'!$B:$OA,3,0) -> reachedathub | AE52: =VLOOKUP(Q52,'[1]an1asv_22-06-2026_06-23-43'!$B:$OA,147,0) -> 0 | AF52: =VLOOKUP(Q52,'[1]an1asv_22-06-2026_06-23-43'!$B:$OA,48,0) -> 46195 | AG52: =VLOOKUP(F52,Response!$A:$B,2,0) -> #N/A | AH52: CNR | AJ52: =VLOOKUP(B52,'Ces, Esc, RTS and Retail'!$A:$B,2,0) -> #N/A | AK52: =VLOOKUP(F52,'Ces, Esc, RTS and Retail'!$D:$F,3,0) -> #N/A | AL52: =VLOOKUP(B52,'Ces, Esc, RTS and Retail'!$H:$H,1,0) -> #N/A | AM52: =VLOOKUP(Q52,'Ces, Esc, RTS and Retail'!$J:$J,1,0) -> #N/A | AN52: =VLOOKUP(Q52,'[2]Trip Manager Report(Updated)_V2'!$I:$Z,18,0) -> #N/A | AO52: =VLOOKUP(E52,'Ces, Esc, RTS and Retail'!$L:$L,1,0) -> #N/A | AP52: =VLOOKUP(Q52,Response!$H:$M,5,0) -> #N/A
A53: Wakefit | B53: ORDER202605KYj0KU | C53: putturaj shanbhog | D53: K-1508, 15, Brigade Eldorado, K-1508 Brigade Eldarado Apartment 15th Floor Near shell Office Aerospace Park Bagaluru | E53: 562149 | F53: 9019090140 | G53: 9019090140 | H53: WUWB7872SFVSTVELURA | I53: 78x72 inch | J53: furniture | K53: 1007103542 | L53: Upholstered Beds | M53: FG01 | N53: 1 | O53: ONLINE | P53: 26060590010262 | Q53: WFFI460478 | R53: BLR LOCAL | S53: Normal Order | T53: Docketed | U53: 2026-05-30 | V53: 2026-05-30 | W53: 2026-06-22 | X53: 2026-06-24 | Y53: 2026-06-21T11:42:15 | AA53: P0 | AB53: 0 | AD53: =VLOOKUP(Q53,'[1]an1asv_22-06-2026_06-23-43'!$B:$OA,3,0) -> reachedathub | AE53: =VLOOKUP(Q53,'[1]an1asv_22-06-2026_06-23-43'!$B:$OA,147,0) -> 0 | AF53: =VLOOKUP(Q53,'[1]an1asv_22-06-2026_06-23-43'!$B:$OA,48,0) -> 46195 | AG53: =VLOOKUP(F53,Response!$A:$B,2,0) -> #N/A | AH53: Outside Service Location | AJ53: =VLOOKUP(B53,'Ces, Esc, RTS and Retail'!$A:$B,2,0) -> #N/A | AK53: =VLOOKUP(F53,'Ces, Esc, RTS and Retail'!$D:$F,3,0) -> #N/A | AL53: =VLOOKUP(B53,'Ces, Esc, RTS and Retail'!$H:$H,1,0) -> #N/A | AM53: =VLOOKUP(Q53,'Ces, Esc, RTS and Retail'!$J:$J,1,0) -> #N/A | AN53: =VLOOKUP(Q53,'[2]Trip Manager Report(Updated)_V2'!$I:$Z,18,0) -> #N/A | AO53: =VLOOKUP(E53,'Ces, Esc, RTS and Retail'!$L:$L,1,0) -> 562149 | AP53: =VLOOKUP(Q53,Response!$H:$M,5,0) -> #N/A | AQ53: =VLOOKUP(B53,#REF!,9,0) -> #REF!
A54: Wakefit | B54: ORDER202605wwNfYi | C54: Anas Merchant | D54: Floor-5, 23/1 Genesis grande , Benson Town | E54: 560046 | F54: 7760626583 | G54: 9606517245 | H54: WWRB4S4D2MH2SH1TYRIANPPL | J54: furniture | K54: 1001028186 | L54: Wardrobes | M54: FG01 | N54: 1 | O54: ONLINE | P54: 26060590010268 | Q54: WFFI460483 | R54: BLR LOCAL | S54: Normal Order | T54: Docketed | U54: 2026-05-31 | V54: 2026-05-31 | W54: 2026-06-22 | X54: 2026-06-23 | Y54: 2026-06-21T11:42:24 | AA54: Breached | AB54: 0 | AD54: =VLOOKUP(Q54,'[1]an1asv_22-06-2026_06-23-43'!$B:$OA,3,0) -> reachedathub | AE54: =VLOOKUP(Q54,'[1]an1asv_22-06-2026_06-23-43'!$B:$OA,147,0) -> 0 | AF54: =VLOOKUP(Q54,'[1]an1asv_22-06-2026_06-23-43'!$B:$OA,48,0) -> 46195 | AG54: =VLOOKUP(F54,Response!$A:$B,2,0) -> #N/A | AH54: CNR | AJ54: =VLOOKUP(B54,'Ces, Esc, RTS and Retail'!$A:$B,2,0) -> #N/A | AK54: =VLOOKUP(F54,'Ces, Esc, RTS and Retail'!$D:$F,3,0) -> #N/A | AL54: =VLOOKUP(B54,'Ces, Esc, RTS and Retail'!$H:$H,1,0) -> #N/A | AM54: =VLOOKUP(Q54,'Ces, Esc, RTS and Retail'!$J:$J,1,0) -> #N/A | AN54: =VLOOKUP(Q54,'[2]Trip Manager Report(Updated)_V2'!$I:$Z,18,0) -> #N/A | AO54: =VLOOKUP(E54,'Ces, Esc, RTS and Retail'!$L:$L,1,0) -> #N/A | AP54: =VLOOKUP(Q54,Response!$H:$M,5,0) -> 0
A55: Wakefit | B55: ORDER202605ZT3dT5 | C55: CHAKRAPANI GOTUR | D55: NO-349,RAMA KURUPA,TEACHER"S COLONY,10TH CROSS,NAGARBHAVI | E55: 560072 | F55: 7382633198 | G55: 8143726501 | H55: WEWB7830SNORMA | I55: 78x30 inch | J55: furniture | K55: 1001021936 | L55: Engineered Wood Bed | M55: FG01 | N55: 1 | O55: ONLINE | P55: 26060590010371 | Q55: WFFI460693 | R55: BLR LOCAL | S55: Normal Order | T55: Docketed | U55: 2026-05-31 | V55: 2026-05-31 | W55: 2026-06-22 | X55: 2026-06-23 | Y55: 2026-06-21T13:36:49 | AA55: Breached | AB55: 0 | AD55: =VLOOKUP(Q55,'[1]an1asv_22-06-2026_06-23-43'!$B:$OA,3,0) -> reachedathub | AE55: =VLOOKUP(Q55,'[1]an1asv_22-06-2026_06-23-43'!$B:$OA,147,0) -> 0 | AF55: =VLOOKUP(Q55,'[1]an1asv_22-06-2026_06-23-43'!$B:$OA,48,0) -> 46195 | AG55: =VLOOKUP(F55,Response!$A:$B,2,0) -> #N/A | AH55: Planned | AJ55: =VLOOKUP(B55,'Ces, Esc, RTS and Retail'!$A:$B,2,0) -> #N/A | AK55: =VLOOKUP(F55,'Ces, Esc, RTS and Retail'!$D:$F,3,0) -> #N/A | AL55: =VLOOKUP(B55,'Ces, Esc, RTS and Retail'!$H:$H,1,0) -> #N/A | AM55: =VLOOKUP(Q55,'Ces, Esc, RTS and Retail'!$J:$J,1,0) -> #N/A | AN55: =VLOOKUP(Q55,'[2]Trip Manager Report(Updated)_V2'!$I:$Z,18,0) -> #N/A | AO55: =VLOOKUP(E55,'Ces, Esc, RTS and Retail'!$L:$L,1,0) -> #N/A | AP55: =VLOOKUP(Q55,Response!$H:$M,5,0) -> Yes
A56: Wakefit_Retail | B56: ORDER202605oFXL2J | C56: Shrinivasan Gopalakrishnan | D56: No.13/3, Vishal Residency, 2nd cross, MLA Layout, Lottegollahalli, | E56: 560094 | F56: 9986997719 | G56: 9686578845 | H56: WBDSTTINKER | J56: furniture | K56: 1007001569 | L56: Bedside Table | M56: FG01 | N56: 1 | O56: ONLINE | P56: 26060590010845 | Q56: WFFI461017 | R56: BLR LOCAL | S56: Normal Order | T56: Docketed | U56: 2026-05-31 | V56: 2026-05-31 | W56: 2026-06-22 | X56: 2026-06-23 | Y56: 2026-06-22T10:52:05 | AA56: Breached | AB56: 0 | AD56: =VLOOKUP(Q56,'[1]an1asv_22-06-2026_06-23-43'!$B:$OA,3,0) -> reachedathub | AE56: =VLOOKUP(Q56,'[1]an1asv_22-06-2026_06-23-43'!$B:$OA,147,0) -> 0 | AF56: =VLOOKUP(Q56,'[1]an1asv_22-06-2026_06-23-43'!$B:$OA,48,0) -> 46195 | AG56: =VLOOKUP(F56,Response!$A:$B,2,0) -> 1 | AH56: Planned | AJ56: =VLOOKUP(B56,'Ces, Esc, RTS and Retail'!$A:$B,2,0) -> #N/A | AK56: =VLOOKUP(F56,'Ces, Esc, RTS and Retail'!$D:$F,3,0) -> #N/A | AL56: =VLOOKUP(B56,'Ces, Esc, RTS and Retail'!$H:$H,1,0) -> #N/A | AM56: =VLOOKUP(Q56,'Ces, Esc, RTS and Retail'!$J:$J,1,0) -> #N/A | AN56: =VLOOKUP(Q56,'[2]Trip Manager Report(Updated)_V2'!$I:$Z,18,0) -> #N/A | AO56: =VLOOKUP(E56,'Ces, Esc, RTS and Retail'!$L:$L,1,0) -> #N/A | AP56: =VLOOKUP(Q56,Response!$H:$M,5,0) -> #N/A
A57: Wakefit_Retail | B57: ORDER202605I41bMQ | C57: Jitendra Kumar | D57: Flat no 104, Malibu Paloma, Borewell road, Whitefield | E57: 560066 | F57: 9900052560 | G57: 9900052560 | H57: WWSFINIUTFW | J57: furniture | K57: 1001018087 | L57: Wallshelf | M57: FG01 | N57: 1 | O57: ONLINE | P57: 26060590010887 | Q57: WFFI461056 | R57: BLR LOCAL | S57: Normal Order | T57: Docketed | U57: 2026-05-31 | V57: 2026-05-31 | W57: 2026-06-22 | X57: 2026-06-23 | Y57: 2026-06-22T10:52:56 | AA57: Breached | AB57: 0 | AD57: =VLOOKUP(Q57,'[1]an1asv_22-06-2026_06-23-43'!$B:$OA,3,0) -> reachedathub | AE57: =VLOOKUP(Q57,'[1]an1asv_22-06-2026_06-23-43'!$B:$OA,147,0) -> 0 | AF57: =VLOOKUP(Q57,'[1]an1asv_22-06-2026_06-23-43'!$B:$OA,48,0) -> 46195 | AG57: =VLOOKUP(F57,Response!$A:$B,2,0) -> 2606 | AH57: CFR | AI57: 46199 | AJ57: =VLOOKUP(B57,'Ces, Esc, RTS and Retail'!$A:$B,2,0) -> #N/A | AK57: =VLOOKUP(F57,'Ces, Esc, RTS and Retail'!$D:$F,3,0) -> #N/A | AL57: =VLOOKUP(B57,'Ces, Esc, RTS and Retail'!$H:$H,1,0) -> #N/A | AM57: =VLOOKUP(Q57,'Ces, Esc, RTS and Retail'!$J:$J,1,0) -> #N/A | AN57: =VLOOKUP(Q57,'[2]Trip Manager Report(Updated)_V2'!$I:$Z,18,0) -> #N/A | AO57: =VLOOKUP(E57,'Ces, Esc, RTS and Retail'!$L:$L,1,0) -> #N/A | AP57: =VLOOKUP(Q57,Response!$H:$M,5,0) -> #N/A
A58: Wakefit_Retail | B58: ORDER202605OsKOWi | C58: R S NANDAKUMAR | D58: D 1108 11th floor GOPALAN FLORENZA SRINIVASAPURA MAIN ROAD BSK 6TH STAGE 11TH BLOCK | E58: 560060 | F58: 9980344701 | H58: WBDSTASTRA | J58: furniture | K58: 1001017866 | L58: Bedside Table | M58: FG01 | N58: 1 | O58: ONLINE | P58: 26060590010912 | Q58: WFFI461083 | R58: BLR LOCAL | S58: Normal Order | T58: Docketed | U58: 2026-05-31 | V58: 2026-05-31 | W58: 2026-06-22 | X58: 2026-06-23 | Y58: 2026-06-22T10:53:25 | AA58: Breached | AB58: 0 | AD58: =VLOOKUP(Q58,'[1]an1asv_22-06-2026_06-23-43'!$B:$OA,3,0) -> reachedathub | AE58: =VLOOKUP(Q58,'[1]an1asv_22-06-2026_06-23-43'!$B:$OA,147,0) -> 0 | AF58: =VLOOKUP(Q58,'[1]an1asv_22-06-2026_06-23-43'!$B:$OA,48,0) -> 46195 | AG58: =VLOOKUP(F58,Response!$A:$B,2,0) -> #N/A | AH58: CNR | AJ58: =VLOOKUP(B58,'Ces, Esc, RTS and Retail'!$A:$B,2,0) -> #N/A | AK58: =VLOOKUP(F58,'Ces, Esc, RTS and Retail'!$D:$F,3,0) -> #N/A | AL58: =VLOOKUP(B58,'Ces, Esc, RTS and Retail'!$H:$H,1,0) -> #N/A | AM58: =VLOOKUP(Q58,'Ces, Esc, RTS and Retail'!$J:$J,1,0) -> #N/A | AN58: =VLOOKUP(Q58,'[2]Trip Manager Report(Updated)_V2'!$I:$Z,18,0) -> #N/A | AO58: =VLOOKUP(E58,'Ces, Esc, RTS and Retail'!$L:$L,1,0) -> #N/A | AP58: =VLOOKUP(Q58,Response!$H:$M,5,0) -> #N/A
A59: Wakefit_Retail | B59: ORDER2026055Beg4w | C59: Ramakant Timsina | D59: B903 ,Block B, 9th Floor Jeevans Octave Apartment | E59: 560067 | F59: 7397492119 | G59: 7002113138 | H59: WBSPROSE | J59: furniture | K59: 1003010025 | L59: Bookshelf | M59: FG01 | N59: 1 | O59: ONLINE | P59: 26060590010902 | Q59: WFFI461074 | R59: BLR LOCAL | S59: Normal Order | T59: Docketed | U59: 2026-05-31 | V59: 2026-05-31 | W59: 2026-06-22 | X59: 2026-06-23 | Y59: 2026-06-22T10:53:13 | AA59: Breached | AB59: 0 | AD59: =VLOOKUP(Q59,'[1]an1asv_22-06-2026_06-23-43'!$B:$OA,3,0) -> reachedathub | AE59: =VLOOKUP(Q59,'[1]an1asv_22-06-2026_06-23-43'!$B:$OA,147,0) -> 0 | AF59: =VLOOKUP(Q59,'[1]an1asv_22-06-2026_06-23-43'!$B:$OA,48,0) -> 46195 | AG59: =VLOOKUP(F59,Response!$A:$B,2,0) -> 1 | AH59: Planned | AJ59: =VLOOKUP(B59,'Ces, Esc, RTS and Retail'!$A:$B,2,0) -> #N/A | AK59: =VLOOKUP(F59,'Ces, Esc, RTS and Retail'!$D:$F,3,0) -> #N/A | AL59: =VLOOKUP(B59,'Ces, Esc, RTS and Retail'!$H:$H,1,0) -> #N/A | AM59: =VLOOKUP(Q59,'Ces, Esc, RTS and Retail'!$J:$J,1,0) -> #N/A | AN59: =VLOOKUP(Q59,'[2]Trip Manager Report(Updated)_V2'!$I:$Z,18,0) -> #N/A | AO59: =VLOOKUP(E59,'Ces, Esc, RTS and Retail'!$L:$L,1,0) -> #N/A | AP59: =VLOOKUP(Q59,Response!$H:$M,5,0) -> #N/A
A60: Wakefit_Retail | B60: ORDER202605THb78c | C60: Sachin Ramola | D60: B 206, 3RD Floor, , Js harmony,, 3rd main road M Vishveshvaraiah Nagar Hoysala Nagar, Ramamurthy Nagar, | E60: 560016 | F60: 9711611351 | H60: WBDSTELARAS | J60: furniture | K60: 1003010014 | L60: Bedside Table | M60: FG01 | N60: 1 | O60: ONLINE | P60: 26060590010813 | Q60: WFFI460991 | R60: BLR LOCAL | S60: Normal Order | T60: Docketed | U60: 2026-05-31 | V60: 2026-05-31 | W60: 2026-06-22 | X60: 2026-06-23 | Y60: 2026-06-22T10:51:30 | AA60: Breached | AB60: 0 | AD60: =VLOOKUP(Q60,'[1]an1asv_22-06-2026_06-23-43'!$B:$OA,3,0) -> reachedathub | AE60: =VLOOKUP(Q60,'[1]an1asv_22-06-2026_06-23-43'!$B:$OA,147,0) -> 0 | AF60: =VLOOKUP(Q60,'[1]an1asv_22-06-2026_06-23-43'!$B:$OA,48,0) -> 46195 | AG60: =VLOOKUP(F60,Response!$A:$B,2,0) -> #N/A | AH60: CNR | AJ60: =VLOOKUP(B60,'Ces, Esc, RTS and Retail'!$A:$B,2,0) -> #N/A | AK60: =VLOOKUP(F60,'Ces, Esc, RTS and Retail'!$D:$F,3,0) -> #N/A | AL60: =VLOOKUP(B60,'Ces, Esc, RTS and Retail'!$H:$H,1,0) -> #N/A | AM60: =VLOOKUP(Q60,'Ces, Esc, RTS and Retail'!$J:$J,1,0) -> #N/A | AN60: =VLOOKUP(Q60,'[2]Trip Manager Report(Updated)_V2'!$I:$Z,18,0) -> #N/A | AO60: =VLOOKUP(E60,'Ces, Esc, RTS and Retail'!$L:$L,1,0) -> #N/A | AP60: =VLOOKUP(Q60,Response!$H:$M,5,0) -> #N/A
A61: Wakefit_Retail | B61: ORDER202606CyZPkV | C61: Bharathkumar N | D61: VEGA 604, SJR VERITY, HOSA ROAD, KASAVANAHALLI | E61: 560035 | F61: 9940649906 | H61: WEWB7872HYSUPOPLMARS | I61: 78x72 inch | J61: furniture | K61: 1007002500 | L61: Engineered Wood Bed | M61: FG01 | N61: 1 | O61: ONLINE | P61: 26060590010821 | Q61: WFFI460993 | R61: BLR LOCAL | S61: Normal Order | T61: Docketed | U61: 2026-06-06 | V61: 2026-06-06 | W61: 2026-06-22 | X61: 2026-06-23 | Y61: 2026-06-22T10:51:32 | AA61: Breached | AB61: 0 | AD61: =VLOOKUP(Q61,'[1]an1asv_22-06-2026_06-23-43'!$B:$OA,3,0) -> reachedathub | AE61: =VLOOKUP(Q61,'[1]an1asv_22-06-2026_06-23-43'!$B:$OA,147,0) -> 0 | AF61: =VLOOKUP(Q61,'[1]an1asv_22-06-2026_06-23-43'!$B:$OA,48,0) -> 46195 | AG61: =VLOOKUP(F61,Response!$A:$B,2,0) -> #N/A | AH61: CNR | AJ61: =VLOOKUP(B61,'Ces, Esc, RTS and Retail'!$A:$B,2,0) -> #N/A | AK61: =VLOOKUP(F61,'Ces, Esc, RTS and Retail'!$D:$F,3,0) -> #N/A | AL61: =VLOOKUP(B61,'Ces, Esc, RTS and Retail'!$H:$H,1,0) -> #N/A | AM61: =VLOOKUP(Q61,'Ces, Esc, RTS and Retail'!$J:$J,1,0) -> #N/A | AN61: =VLOOKUP(Q61,'[2]Trip Manager Report(Updated)_V2'!$I:$Z,18,0) -> #N/A | AO61: =VLOOKUP(E61,'Ces, Esc, RTS and Retail'!$L:$L,1,0) -> #N/A | AP61: =VLOOKUP(Q61,Response!$H:$M,5,0) -> #N/A
A62: Wakefit_Retail | B62: ORDER202606Qzk0Vl | C62: thomas varghese | D62: 38, 2, Jbs celesta, Mullur ,carmelaram | E62: 560035 | F62: 8113052420 | G62: 8113052420 | H62: WEWB7872SVENUS | I62: 78x72 inch | J62: furniture | K62: 1007002458 | L62: Engineered Wood Bed | M62: FG01 | N62: 1 | O62: ONLINE | P62: 26060590010843 | Q62: WFFI461015 | R62: BLR LOCAL | S62: Normal Order | T62: Docketed | U62: 2026-06-09 | V62: 2026-06-09 | W62: 2026-06-23 | X62: 2026-06-24 | Y62: 2026-06-22T10:52:03 | AA62: P0 | AB62: 0 | AD62: =VLOOKUP(Q62,'[1]an1asv_22-06-2026_06-23-43'!$B:$OA,3,0) -> reachedathub | AE62: =VLOOKUP(Q62,'[1]an1asv_22-06-2026_06-23-43'!$B:$OA,147,0) -> 0 | AF62: =VLOOKUP(Q62,'[1]an1asv_22-06-2026_06-23-43'!$B:$OA,48,0) -> 46195 | AG62: =VLOOKUP(F62,Response!$A:$B,2,0) -> #N/A | AH62: CNR | AJ62: =VLOOKUP(B62,'Ces, Esc, RTS and Retail'!$A:$B,2,0) -> #N/A | AK62: =VLOOKUP(F62,'Ces, Esc, RTS and Retail'!$D:$F,3,0) -> #N/A | AL62: =VLOOKUP(B62,'Ces, Esc, RTS and Retail'!$H:$H,1,0) -> #N/A | AM62: =VLOOKUP(Q62,'Ces, Esc, RTS and Retail'!$J:$J,1,0) -> #N/A | AN62: =VLOOKUP(Q62,'[2]Trip Manager Report(Updated)_V2'!$I:$Z,18,0) -> #N/A | AO62: =VLOOKUP(E62,'Ces, Esc, RTS and Retail'!$L:$L,1,0) -> #N/A | AP62: =VLOOKUP(Q62,Response!$H:$M,5,0) -> #N/A
A63: Wakefit_Retail | B63: ORDER202605nH70cW | C63: Soumya Singh | D63: E-601 , Godrej Park Retreat, Camelaram, Hadosiddapura, Chikkakannalli, Kodathi JHC, Bangalore, Karnataka | E63: 560035 | F63: 8317306416 | G63: 8317306416 | H63: WEWB7860SUPOPLTAURUSR2 | I63: 78x60 inch | J63: furniture | K63: 1007003118 | L63: Engineered Wood Bed | M63: FG01 | N63: 1 | O63: ONLINE | P63: 26060590010825 | Q63: WFFI460998 | R63: BLR LOCAL | S63: Normal Order | T63: Docketed | U63: 2026-05-31 | V63: 2026-05-31 | W63: 2026-06-22 | X63: 2026-06-23 | Y63: 2026-06-22T10:51:43 | AA63: Breached | AB63: 0 | AD63: =VLOOKUP(Q63,'[1]an1asv_22-06-2026_06-23-43'!$B:$OA,3,0) -> reachedathub | AE63: =VLOOKUP(Q63,'[1]an1asv_22-06-2026_06-23-43'!$B:$OA,147,0) -> 0 | AF63: =VLOOKUP(Q63,'[1]an1asv_22-06-2026_06-23-43'!$B:$OA,48,0) -> 46195 | AG63: =VLOOKUP(F63,Response!$A:$B,2,0) -> 1 | AH63: Planned | AJ63: =VLOOKUP(B63,'Ces, Esc, RTS and Retail'!$A:$B,2,0) -> #N/A | AK63: =VLOOKUP(F63,'Ces, Esc, RTS and Retail'!$D:$F,3,0) -> #N/A | AL63: =VLOOKUP(B63,'Ces, Esc, RTS and Retail'!$H:$H,1,0) -> #N/A | AM63: =VLOOKUP(Q63,'Ces, Esc, RTS and Retail'!$J:$J,1,0) -> #N/A | AN63: =VLOOKUP(Q63,'[2]Trip Manager Report(Updated)_V2'!$I:$Z,18,0) -> #N/A | AO63: =VLOOKUP(E63,'Ces, Esc, RTS and Retail'!$L:$L,1,0) -> #N/A | AP63: =VLOOKUP(Q63,Response!$H:$M,5,0) -> #N/A
A64: Amazon | B64: 404-3686386-6730741 | C64: Nitin Pai | D64: No 25, 1st floor, Dee Enclave, 2nd cross, kodigehalli main road | E64: 560092 | F64: 8861625771 | H64: WWRB4DMH1ORGANZAPCWR2 | J64: furniture | K64: 1007129089 | L64: Wardrobes | M64: FG01 | N64: 1 | O64: ONLINE | P64: 26060590010838 | Q64: WFFI461009 | R64: BLR LOCAL | S64: Normal Order | T64: Docketed | U64: 2026-06-01 | V64: 2026-06-01 | W64: 2026-06-14 | X64: 2026-06-20 | Y64: 2026-06-22T10:51:56 | AA64: Breached | AB64: 0 | AD64: =VLOOKUP(Q64,'[1]an1asv_22-06-2026_06-23-43'!$B:$OA,3,0) -> reachedathub | AE64: =VLOOKUP(Q64,'[1]an1asv_22-06-2026_06-23-43'!$B:$OA,147,0) -> 0 | AF64: =VLOOKUP(Q64,'[1]an1asv_22-06-2026_06-23-43'!$B:$OA,48,0) -> 46195 | AG64: =VLOOKUP(F64,Response!$A:$B,2,0) -> 1 | AH64: Planned | AJ64: =VLOOKUP(B64,'Ces, Esc, RTS and Retail'!$A:$B,2,0) -> #N/A | AK64: =VLOOKUP(F64,'Ces, Esc, RTS and Retail'!$D:$F,3,0) -> #N/A | AL64: =VLOOKUP(B64,'Ces, Esc, RTS and Retail'!$H:$H,1,0) -> #N/A | AM64: =VLOOKUP(Q64,'Ces, Esc, RTS and Retail'!$J:$J,1,0) -> #N/A | AN64: =VLOOKUP(Q64,'[2]Trip Manager Report(Updated)_V2'!$I:$Z,18,0) -> #N/A | AO64: =VLOOKUP(E64,'Ces, Esc, RTS and Retail'!$L:$L,1,0) -> #N/A | AP64: =VLOOKUP(Q64,Response!$H:$M,5,0) -> #N/A
A65: Wakefit | B65: ORDER202606EVP2mU | C65: kavitha mohan | D65: 20, 2nd G main road, Muthyalanagar | E65: 560054 | F65: 7022257504 | G65: 7022257504 | H65: WSTSAGER1 | J65: furniture | K65: 1007100321 | L65: Study Table | M65: FG01 | N65: 1 | O65: ONLINE | P65: 26060590010267 | Q65: WFFI460482 | R65: BLR LOCAL | S65: Normal Order | T65: Docketed | U65: 2026-06-01 | V65: 2026-06-01 | W65: 2026-06-22 | X65: 2026-06-23 | Y65: 2026-06-21T11:42:22 | AA65: Breached | AB65: 0 | AD65: =VLOOKUP(Q65,'[1]an1asv_22-06-2026_06-23-43'!$B:$OA,3,0) -> reachedathub | AE65: =VLOOKUP(Q65,'[1]an1asv_22-06-2026_06-23-43'!$B:$OA,147,0) -> 0 | AF65: =VLOOKUP(Q65,'[1]an1asv_22-06-2026_06-23-43'!$B:$OA,48,0) -> 46195 | AG65: =VLOOKUP(F65,Response!$A:$B,2,0) -> #N/A | AH65: CNR | AJ65: =VLOOKUP(B65,'Ces, Esc, RTS and Retail'!$A:$B,2,0) -> #N/A | AK65: =VLOOKUP(F65,'Ces, Esc, RTS and Retail'!$D:$F,3,0) -> #N/A | AL65: =VLOOKUP(B65,'Ces, Esc, RTS and Retail'!$H:$H,1,0) -> #N/A | AM65: =VLOOKUP(Q65,'Ces, Esc, RTS and Retail'!$J:$J,1,0) -> #N/A | AN65: =VLOOKUP(Q65,'[2]Trip Manager Report(Updated)_V2'!$I:$Z,18,0) -> #N/A | AO65: =VLOOKUP(E65,'Ces, Esc, RTS and Retail'!$L:$L,1,0) -> #N/A | AP65: =VLOOKUP(Q65,Response!$H:$M,5,0) -> 0
A66: Wakefit_Retail | B66: ORDER202606SyJHQe | C66: Navyasree Yarlagadda | D66: 1402, 14th floor Tower 33, L&T Raintree Boulevard, Indra Nagar, Sahakar Nagar, Byatarayanapura, Bengaluru | E66: 560092 | F66: 8867788977 | G66: 7386115415 | H66: WMCFTKAFFEOSTR1 | J66: furniture | K66: 1001024424 | L66: Metal Coffee Table | M66: FG01 | N66: 1 | O66: PREPAID-CASH | P66: 26060590010273 | Q66: WFFI460485 | R66: BLR LOCAL | S66: Normal Order | T66: Docketed | U66: 2026-06-01 | V66: 2026-06-01 | W66: 2026-06-22 | X66: 2026-06-23 | Y66: 2026-06-21T11:42:30 | AA66: Breached | AB66: 0 | AD66: =VLOOKUP(Q66,'[1]an1asv_22-06-2026_06-23-43'!$B:$OA,3,0) -> reachedathub | AE66: =VLOOKUP(Q66,'[1]an1asv_22-06-2026_06-23-43'!$B:$OA,147,0) -> 0 | AF66: =VLOOKUP(Q66,'[1]an1asv_22-06-2026_06-23-43'!$B:$OA,48,0) -> 46195 | AG66: =VLOOKUP(F66,Response!$A:$B,2,0) -> 1 | AH66: Planned | AJ66: =VLOOKUP(B66,'Ces, Esc, RTS and Retail'!$A:$B,2,0) -> #N/A | AK66: =VLOOKUP(F66,'Ces, Esc, RTS and Retail'!$D:$F,3,0) -> #N/A | AL66: =VLOOKUP(B66,'Ces, Esc, RTS and Retail'!$H:$H,1,0) -> #N/A | AM66: =VLOOKUP(Q66,'Ces, Esc, RTS and Retail'!$J:$J,1,0) -> #N/A | AN66: =VLOOKUP(Q66,'[2]Trip Manager Report(Updated)_V2'!$I:$Z,18,0) -> #N/A | AO66: =VLOOKUP(E66,'Ces, Esc, RTS and Retail'!$L:$L,1,0) -> #N/A | AP66: =VLOOKUP(Q66,Response!$H:$M,5,0) -> 0
A67: Wakefit | B67: ORDER202606bh8Ut2 | C67: Avinash Kumar | D67: B1403, 14, Godrej Park Retreat, Godrej Park Retreat, Tower B, 1403, Carmelaram, Hadosiddapura, Chikkakannalli, Kodathi JHC | E67: 560035 | F67: 9866277566 | G67: 8240303495 | H67: WSTSHEAPG | J67: furniture | K67: 1007004622 | L67: Study Table | M67: FG01 | N67: 1 | O67: ONLINE | P67: 26060590010380 | Q67: WFFI460698 | R67: BLR LOCAL | S67: Normal Order | T67: Docketed | U67: 2026-06-19 | V67: 2026-06-19 | W67: 2026-06-21 | X67: 2026-06-22 | Y67: 2026-06-21T13:37:00 | AA67: Breached | AB67: 0 | AD67: =VLOOKUP(Q67,'[1]an1asv_22-06-2026_06-23-43'!$B:$OA,3,0) -> reachedathub | AE67: =VLOOKUP(Q67,'[1]an1asv_22-06-2026_06-23-43'!$B:$OA,147,0) -> 0 | AF67: =VLOOKUP(Q67,'[1]an1asv_22-06-2026_06-23-43'!$B:$OA,48,0) -> 46195 | AG67: =VLOOKUP(F67,Response!$A:$B,2,0) -> #N/A | AH67: CNR | AJ67: =VLOOKUP(B67,'Ces, Esc, RTS and Retail'!$A:$B,2,0) -> #N/A | AK67: =VLOOKUP(F67,'Ces, Esc, RTS and Retail'!$D:$F,3,0) -> #N/A | AL67: =VLOOKUP(B67,'Ces, Esc, RTS and Retail'!$H:$H,1,0) -> #N/A | AM67: =VLOOKUP(Q67,'Ces, Esc, RTS and Retail'!$J:$J,1,0) -> #N/A | AN67: =VLOOKUP(Q67,'[2]Trip Manager Report(Updated)_V2'!$I:$Z,18,0) -> #N/A | AO67: =VLOOKUP(E67,'Ces, Esc, RTS and Retail'!$L:$L,1,0) -> #N/A | AP67: =VLOOKUP(Q67,Response!$H:$M,5,0) -> #N/A
A68: Wakefit | B68: ORDER202606uDguoZ | C68: Nandish | D68: 1104, 11, Sattva Ashraya. Tower-02, Lakshmisagara, Bidadi | E68: 562109 | F68: 9902656162 | G68: 6364704342 | H68: WEWB7560STAURUSR2 | I68: 75x60 inch | J68: furniture | K68: 1001024999 | L68: Engineered Wood Bed | M68: FG01 | N68: 1 | O68: ONLINE | P68: 26060590010915 | Q68: WFFI461085 | R68: BLR LOCAL | S68: Normal Order | T68: Docketed | U68: 2026-06-01 | V68: 2026-06-01 | W68: 2026-06-22 | X68: 2026-06-26 | Y68: 2026-06-22T10:53:30 | AA68: P1 | AB68: 0 | AD68: =VLOOKUP(Q68,'[1]an1asv_22-06-2026_06-23-43'!$B:$OA,3,0) -> reachedathub | AE68: =VLOOKUP(Q68,'[1]an1asv_22-06-2026_06-23-43'!$B:$OA,147,0) -> 0 | AF68: =VLOOKUP(Q68,'[1]an1asv_22-06-2026_06-23-43'!$B:$OA,48,0) -> 46195 | AG68: =VLOOKUP(F68,Response!$A:$B,2,0) -> #N/A | AH68: Outside Service Location | AJ68: =VLOOKUP(B68,'Ces, Esc, RTS and Retail'!$A:$B,2,0) -> #N/A | AK68: =VLOOKUP(F68,'Ces, Esc, RTS and Retail'!$D:$F,3,0) -> #N/A | AL68: =VLOOKUP(B68,'Ces, Esc, RTS and Retail'!$H:$H,1,0) -> #N/A | AM68: =VLOOKUP(Q68,'Ces, Esc, RTS and Retail'!$J:$J,1,0) -> #N/A | AN68: =VLOOKUP(Q68,'[2]Trip Manager Report(Updated)_V2'!$I:$Z,18,0) -> #N/A | AO68: =VLOOKUP(E68,'Ces, Esc, RTS and Retail'!$L:$L,1,0) -> 562109 | AP68: =VLOOKUP(Q68,Response!$H:$M,5,0) -> #N/A
A69: Wakefit_Retail | B69: ORDER2026065OocVf | C69: Rahul Gangadharan | D69: House no# D1-1004, Goldenpalms apartment, K narayanapura | E69: 560077 | F69: 9886425450 | H69: WEWB7860SUPOGRMARS | I69: 78x60 inch | J69: furniture | K69: 1007002827 | L69: Engineered Wood Bed | M69: FG01 | N69: 1 | O69: ONLINE | P69: 26060590002749 | Q69: WFFI451719 | R69: BLR LOCAL | S69: Normal Order | T69: Shipped | U69: 2026-06-01 | V69: 2026-06-01 | W69: 2026-06-21 | X69: 2026-06-22 | Y69: 2026-06-05T21:15:05 | Z69: 2026-06-21T21:18:51 | AA69: Breached | AB69: 0 | AD69: =VLOOKUP(Q69,'[1]an1asv_22-06-2026_06-23-43'!$B:$OA,3,0) -> reachedathub | AE69: =VLOOKUP(Q69,'[1]an1asv_22-06-2026_06-23-43'!$B:$OA,147,0) -> Planned | AF69: =VLOOKUP(Q69,'[1]an1asv_22-06-2026_06-23-43'!$B:$OA,48,0) -> 46195 | AG69: =VLOOKUP(F69,Response!$A:$B,2,0) -> #N/A | AH69: Not planned | AJ69: =VLOOKUP(B69,'Ces, Esc, RTS and Retail'!$A:$B,2,0) -> #N/A | AK69: =VLOOKUP(F69,'Ces, Esc, RTS and Retail'!$D:$F,3,0) -> #N/A | AL69: =VLOOKUP(B69,'Ces, Esc, RTS and Retail'!$H:$H,1,0) -> #N/A | AM69: =VLOOKUP(Q69,'Ces, Esc, RTS and Retail'!$J:$J,1,0) -> #N/A | AN69: =VLOOKUP(Q69,'[2]Trip Manager Report(Updated)_V2'!$I:$Z,18,0) -> #N/A | AO69: =VLOOKUP(E69,'Ces, Esc, RTS and Retail'!$L:$L,1,0) -> #N/A | AP69: =VLOOKUP(Q69,Response!$H:$M,5,0) -> #N/A
A70: Wakefit_Retail | B70: ORDER2026065OocVf | C70: Rahul Gangadharan | D70: House no# D1-1004, Goldenpalms apartment, K narayanapura | E70: 560077 | F70: 9886425450 | H70: WEWB7872STESSERCW | I70: 78x72 inch | J70: furniture | K70: 1001033591 | L70: Engineered Wood Bed | M70: FG01 | N70: 1 | O70: ONLINE | P70: 26060590010665 | Q70: WFFI460891 | R70: BLR LOCAL | S70: Normal Order | T70: Docketed | U70: 2026-06-01 | V70: 2026-06-01 | W70: 2026-06-21 | X70: 2026-06-22 | Y70: 2026-06-22T09:36:13 | AA70: Breached | AB70: 0 | AD70: =VLOOKUP(Q70,'[1]an1asv_22-06-2026_06-23-43'!$B:$OA,3,0) -> reachedathub | AE70: =VLOOKUP(Q70,'[1]an1asv_22-06-2026_06-23-43'!$B:$OA,147,0) -> 0 | AF70: =VLOOKUP(Q70,'[1]an1asv_22-06-2026_06-23-43'!$B:$OA,48,0) -> 46195 | AG70: =VLOOKUP(F70,Response!$A:$B,2,0) -> #N/A | AH70: CNR | AJ70: =VLOOKUP(B70,'Ces, Esc, RTS and Retail'!$A:$B,2,0) -> #N/A | AK70: =VLOOKUP(F70,'Ces, Esc, RTS and Retail'!$D:$F,3,0) -> #N/A | AL70: =VLOOKUP(B70,'Ces, Esc, RTS and Retail'!$H:$H,1,0) -> #N/A | AM70: =VLOOKUP(Q70,'Ces, Esc, RTS and Retail'!$J:$J,1,0) -> #N/A | AN70: =VLOOKUP(Q70,'[2]Trip Manager Report(Updated)_V2'!$I:$Z,18,0) -> #N/A | AO70: =VLOOKUP(E70,'Ces, Esc, RTS and Retail'!$L:$L,1,0) -> #N/A | AP70: =VLOOKUP(Q70,Response!$H:$M,5,0) -> #N/A
A71: Wakefit_Retail | B71: ORDER202606ydEmMy | C71: Pavan Hareesh Guruvelli | D71: D.No: G 08, Block A First Floor, Mahaveer Cygnet, Kogilu, Yelahanka Old Town, Bengaluru, Karnataka | E71: 560064 | F71: 7893871088 | G71: 9640371436 | H71: WEWB7860SCNTR | I71: 78x60 inch | J71: furniture | K71: 1001024520 | L71: Engineered Wood Bed | M71: FG01 | N71: 1 | O71: ONLINE | P71: 26060590010667 | Q71: WFFI460893 | R71: BLR LOCAL | S71: Normal Order | T71: Docketed | U71: 2026-06-01 | V71: 2026-06-01 | W71: 2026-06-21 | X71: 2026-06-22 | Y71: 2026-06-22T09:36:19 | AA71: Breached | AB71: 0 | AD71: =VLOOKUP(Q71,'[1]an1asv_22-06-2026_06-23-43'!$B:$OA,3,0) -> reachedathub | AE71: =VLOOKUP(Q71,'[1]an1asv_22-06-2026_06-23-43'!$B:$OA,147,0) -> 0 | AF71: =VLOOKUP(Q71,'[1]an1asv_22-06-2026_06-23-43'!$B:$OA,48,0) -> 46195 | AG71: =VLOOKUP(F71,Response!$A:$B,2,0) -> #N/A | AH71: CNR | AJ71: =VLOOKUP(B71,'Ces, Esc, RTS and Retail'!$A:$B,2,0) -> #N/A | AK71: =VLOOKUP(F71,'Ces, Esc, RTS and Retail'!$D:$F,3,0) -> #N/A | AL71: =VLOOKUP(B71,'Ces, Esc, RTS and Retail'!$H:$H,1,0) -> #N/A | AM71: =VLOOKUP(Q71,'Ces, Esc, RTS and Retail'!$J:$J,1,0) -> #N/A | AN71: =VLOOKUP(Q71,'[2]Trip Manager Report(Updated)_V2'!$I:$Z,18,0) -> #N/A | AO71: =VLOOKUP(E71,'Ces, Esc, RTS and Retail'!$L:$L,1,0) -> #N/A | AP71: =VLOOKUP(Q71,Response!$H:$M,5,0) -> #N/A
A72: Wakefit | B72: ORDER202606eH98gA | C72: Prajwal Kumar | D72: House no 17, 5th B main road, HRBR layout, 2nd block, Kalyan Nagar | E72: 560043 | F72: 7358075989 | H72: WEWB7560STAURUSR2 | I72: 75x60 inch | J72: furniture | K72: 1001024999 | L72: Engineered Wood Bed | M72: FG01 | N72: 1 | O72: ONLINE | P72: 26060590010854 | Q72: WFFI461028 | R72: BLR LOCAL | S72: Normal Order | T72: Docketed | U72: 2026-06-01 | V72: 2026-06-01 | W72: 2026-06-22 | X72: 2026-06-23 | Y72: 2026-06-22T10:52:20 | AA72: Breached | AB72: 0 | AD72: =VLOOKUP(Q72,'[1]an1asv_22-06-2026_06-23-43'!$B:$OA,3,0) -> reachedathub | AE72: =VLOOKUP(Q72,'[1]an1asv_22-06-2026_06-23-43'!$B:$OA,147,0) -> 0 | AF72: =VLOOKUP(Q72,'[1]an1asv_22-06-2026_06-23-43'!$B:$OA,48,0) -> 46195 | AG72: =VLOOKUP(F72,Response!$A:$B,2,0) -> 1 | AH72: Planned | AJ72: =VLOOKUP(B72,'Ces, Esc, RTS and Retail'!$A:$B,2,0) -> #N/A | AK72: =VLOOKUP(F72,'Ces, Esc, RTS and Retail'!$D:$F,3,0) -> #N/A | AL72: =VLOOKUP(B72,'Ces, Esc, RTS and Retail'!$H:$H,1,0) -> #N/A | AM72: =VLOOKUP(Q72,'Ces, Esc, RTS and Retail'!$J:$J,1,0) -> #N/A | AN72: =VLOOKUP(Q72,'[2]Trip Manager Report(Updated)_V2'!$I:$Z,18,0) -> #N/A | AO72: =VLOOKUP(E72,'Ces, Esc, RTS and Retail'!$L:$L,1,0) -> #N/A | AP72: =VLOOKUP(Q72,Response!$H:$M,5,0) -> #N/A
A73: Wakefit_Retail | B73: ORDER202606KQyK1H | C73: Gaurav Mehta | D73: 1410, VRR Fortuna, Sarjapur Road | E73: 560035 | F73: 8765161244 | G73: 7999934960 | H73: WEWB7860SUPOGRMARS | I73: 78x60 inch | J73: furniture | K73: 1007002827 | L73: Engineered Wood Bed | M73: FG01 | N73: 1 | O73: ONLINE | P73: 26060590010819 | Q73: WFFI460989 | R73: BLR LOCAL | S73: Normal Order | T73: Docketed | U73: 2026-06-20 | V73: 2026-06-20 | W73: 2026-06-23 | X73: 2026-06-24 | Y73: 2026-06-22T10:51:31 | AA73: P0 | AB73: 0 | AD73: =VLOOKUP(Q73,'[1]an1asv_22-06-2026_06-23-43'!$B:$OA,3,0) -> reachedathub | AE73: =VLOOKUP(Q73,'[1]an1asv_22-06-2026_06-23-43'!$B:$OA,147,0) -> 0 | AF73: =VLOOKUP(Q73,'[1]an1asv_22-06-2026_06-23-43'!$B:$OA,48,0) -> 46195 | AG73: =VLOOKUP(F73,Response!$A:$B,2,0) -> #N/A | AH73: CNR | AJ73: =VLOOKUP(B73,'Ces, Esc, RTS and Retail'!$A:$B,2,0) -> #N/A | AK73: =VLOOKUP(F73,'Ces, Esc, RTS and Retail'!$D:$F,3,0) -> #N/A | AL73: =VLOOKUP(B73,'Ces, Esc, RTS and Retail'!$H:$H,1,0) -> #N/A | AM73: =VLOOKUP(Q73,'Ces, Esc, RTS and Retail'!$J:$J,1,0) -> #N/A | AN73: =VLOOKUP(Q73,'[2]Trip Manager Report(Updated)_V2'!$I:$Z,18,0) -> #N/A | AO73: =VLOOKUP(E73,'Ces, Esc, RTS and Retail'!$L:$L,1,0) -> #N/A | AP73: =VLOOKUP(Q73,Response!$H:$M,5,0) -> #N/A
A74: Wakefit | B74: ORDER202606s4wVlm | C74: Akshika | D74: F2, 1, Crystal view apartments, 62 St John’s road | E74: 560042 | F74: 9535734663 | G74: 9535734663 | H74: WEWB7860NONUPOGRTAURUSR2 | I74: 78x60 inch | J74: furniture | K74: 1007003126 | L74: Engineered Wood Bed | M74: FG01 | N74: 1 | O74: ONLINE | P74: 26060590010883 | Q74: WFFI461055 | R74: BLR LOCAL | S74: Normal Order | T74: Docketed | U74: 2026-06-01 | V74: 2026-06-01 | W74: 2026-06-22 | X74: 2026-06-23 | Y74: 2026-06-22T10:52:53 | AA74: Breached | AB74: 0 | AD74: =VLOOKUP(Q74,'[1]an1asv_22-06-2026_06-23-43'!$B:$OA,3,0) -> reachedathub | AE74: =VLOOKUP(Q74,'[1]an1asv_22-06-2026_06-23-43'!$B:$OA,147,0) -> 0 | AF74: =VLOOKUP(Q74,'[1]an1asv_22-06-2026_06-23-43'!$B:$OA,48,0) -> 46195 | AG74: =VLOOKUP(F74,Response!$A:$B,2,0) -> #N/A | AH74: CNR | AJ74: =VLOOKUP(B74,'Ces, Esc, RTS and Retail'!$A:$B,2,0) -> #N/A | AK74: =VLOOKUP(F74,'Ces, Esc, RTS and Retail'!$D:$F,3,0) -> #N/A | AL74: =VLOOKUP(B74,'Ces, Esc, RTS and Retail'!$H:$H,1,0) -> #N/A | AM74: =VLOOKUP(Q74,'Ces, Esc, RTS and Retail'!$J:$J,1,0) -> #N/A | AN74: =VLOOKUP(Q74,'[2]Trip Manager Report(Updated)_V2'!$I:$Z,18,0) -> #N/A | AO74: =VLOOKUP(E74,'Ces, Esc, RTS and Retail'!$L:$L,1,0) -> #N/A | AP74: =VLOOKUP(Q74,Response!$H:$M,5,0) -> #N/A
A75: Wakefit_Retail | B75: ORDER202606vuY0Xn | C75: Akash mallikarjun Jonnagirimath | D75: RBI STAFF QUARTERS VIJAYNAGAR RPC LAYOUT | E75: 560104 | F75: 9901426828 | G75: 8904512741 | H75: WSWB7860TIERHBSW | I75: 78x60 inch | J75: furniture | K75: 1007120115 | L75: Cot | M75: FG01 | N75: 1 | O75: ONLINE | P75: 26060590010248 | Q75: WFFI460469 | R75: BLR LOCAL | S75: Normal Order | T75: Shipped | U75: 2026-06-01 | V75: 2026-06-01 | W75: 2026-06-22 | X75: 2026-06-23 | Y75: 2026-06-21T11:41:52 | Z75: 2026-06-21T21:07:41 | AA75: Breached | AB75: 0 | AD75: =VLOOKUP(Q75,'[1]an1asv_22-06-2026_06-23-43'!$B:$OA,3,0) -> reachedathub | AE75: =VLOOKUP(Q75,'[1]an1asv_22-06-2026_06-23-43'!$B:$OA,147,0) -> 0 | AF75: =VLOOKUP(Q75,'[1]an1asv_22-06-2026_06-23-43'!$B:$OA,48,0) -> 46195 | AG75: =VLOOKUP(F75,Response!$A:$B,2,0) -> #N/A | AH75: Planned | AJ75: =VLOOKUP(B75,'Ces, Esc, RTS and Retail'!$A:$B,2,0) -> 46183 | AK75: =VLOOKUP(F75,'Ces, Esc, RTS and Retail'!$D:$F,3,0) -> #N/A | AL75: =VLOOKUP(B75,'Ces, Esc, RTS and Retail'!$H:$H,1,0) -> #N/A | AM75: =VLOOKUP(Q75,'Ces, Esc, RTS and Retail'!$J:$J,1,0) -> #N/A | AN75: =VLOOKUP(Q75,'[2]Trip Manager Report(Updated)_V2'!$I:$Z,18,0) -> #N/A | AO75: =VLOOKUP(E75,'Ces, Esc, RTS and Retail'!$L:$L,1,0) -> #N/A | AP75: =VLOOKUP(Q75,Response!$H:$M,5,0) -> Yes
A76: Wakefit | B76: ORDER202606Rj5V1x | C76: Savera | D76: 310, 3, S2 Violet, Banjara Layout, Horamavu, Bangalore | E76: 560043 | F76: 7406065470 | G76: 7406065470 | H76: WSTMOPPINFW | J76: furniture | K76: 1007120464 | L76: Study Table | M76: FG01 | N76: 1 | O76: ONLINE | P76: 26060590010226 | Q76: WFFI460449 | R76: BLR LOCAL | S76: Normal Order | T76: Shipped | U76: 2026-06-01 | V76: 2026-06-01 | W76: 2026-06-21 | X76: 2026-06-22 | Y76: 2026-06-21T11:41:24 | Z76: 2026-06-21T21:18:51 | AA76: Breached | AB76: 0 | AD76: =VLOOKUP(Q76,'[1]an1asv_22-06-2026_06-23-43'!$B:$OA,3,0) -> reachedathub | AE76: =VLOOKUP(Q76,'[1]an1asv_22-06-2026_06-23-43'!$B:$OA,147,0) -> 0 | AF76: =VLOOKUP(Q76,'[1]an1asv_22-06-2026_06-23-43'!$B:$OA,48,0) -> 46195 | AG76: =VLOOKUP(F76,Response!$A:$B,2,0) -> 1 | AH76: Not planned | AJ76: =VLOOKUP(B76,'Ces, Esc, RTS and Retail'!$A:$B,2,0) -> #N/A | AK76: =VLOOKUP(F76,'Ces, Esc, RTS and Retail'!$D:$F,3,0) -> #N/A | AL76: =VLOOKUP(B76,'Ces, Esc, RTS and Retail'!$H:$H,1,0) -> #N/A | AM76: =VLOOKUP(Q76,'Ces, Esc, RTS and Retail'!$J:$J,1,0) -> #N/A | AN76: =VLOOKUP(Q76,'[2]Trip Manager Report(Updated)_V2'!$I:$Z,18,0) -> #N/A | AO76: =VLOOKUP(E76,'Ces, Esc, RTS and Retail'!$L:$L,1,0) -> #N/A | AP76: =VLOOKUP(Q76,Response!$H:$M,5,0) -> #N/A
A77: Wakefit_Retail | B77: ORDER2026066Cm5b9 | C77: Keerthana M | D77: 3/1A3 Ganga nilaya 1st floor 3rd cross harsha layout | E77: 560060 | F77: 9986682349 | G77: 9449182182 | H77: WEWB7872HYSTESSERCW | I77: 78x72 inch | J77: furniture | K77: 1001033589 | L77: Engineered Wood Bed | M77: FG01 | N77: 1 | O77: ONLINE | P77: 26060590009844 | Q77: WFFI459799 | R77: BLR LOCAL | S77: Normal Order | T77: Shipped | U77: 2026-06-01 | V77: 2026-06-01 | W77: 2026-06-21 | X77: 2026-06-22 | Y77: 2026-06-19T22:22:16 | Z77: 2026-06-20T22:02:52 | AA77: Breached | AB77: 0 | AD77: =VLOOKUP(Q77,'[1]an1asv_22-06-2026_06-23-43'!$B:$OA,3,0) -> reachedathub | AE77: =VLOOKUP(Q77,'[1]an1asv_22-06-2026_06-23-43'!$B:$OA,147,0) -> Planned | AF77: =VLOOKUP(Q77,'[1]an1asv_22-06-2026_06-23-43'!$B:$OA,48,0) -> 46195 | AG77: =VLOOKUP(F77,Response!$A:$B,2,0) -> #N/A | AH77: Planned | AJ77: =VLOOKUP(B77,'Ces, Esc, RTS and Retail'!$A:$B,2,0) -> #N/A | AK77: =VLOOKUP(F77,'Ces, Esc, RTS and Retail'!$D:$F,3,0) -> #N/A | AL77: =VLOOKUP(B77,'Ces, Esc, RTS and Retail'!$H:$H,1,0) -> #N/A | AM77: =VLOOKUP(Q77,'Ces, Esc, RTS and Retail'!$J:$J,1,0) -> #N/A | AN77: =VLOOKUP(Q77,'[2]Trip Manager Report(Updated)_V2'!$I:$Z,18,0) -> INSUFFICIENT TIME | AO77: =VLOOKUP(E77,'Ces, Esc, RTS and Retail'!$L:$L,1,0) -> #N/A | AP77: =VLOOKUP(Q77,Response!$H:$M,5,0) -> #N/A
A78: Wakefit | B78: ORDER202606VQnBhJ | C78: Kartheeka | D78: E - 1130, 11, Serene, Brigade Cornerstone Utopia | E78: 560087 | F78: 7569596164 | G78: 7569596164 | H78: WEWB7860STAURUSR2 | I78: 78x60 inch | J78: furniture | K78: 1003000472 | L78: Engineered Wood Bed | M78: FG01 | N78: 1 | O78: ONLINE | P78: 26060590010858 | Q78: WFFI461032 | R78: BLR LOCAL | S78: Normal Order | T78: Docketed | U78: 2026-06-01 | V78: 2026-06-01 | W78: 2026-06-22 | X78: 2026-06-23 | Y78: 2026-06-22T10:52:23 | AA78: Breached | AB78: 0 | AD78: =VLOOKUP(Q78,'[1]an1asv_22-06-2026_06-23-43'!$B:$OA,3,0) -> reachedathub | AE78: =VLOOKUP(Q78,'[1]an1asv_22-06-2026_06-23-43'!$B:$OA,147,0) -> 0 | AF78: =VLOOKUP(Q78,'[1]an1asv_22-06-2026_06-23-43'!$B:$OA,48,0) -> 46195 | AG78: =VLOOKUP(F78,Response!$A:$B,2,0) -> 0107 | AH78: CFR | AI78: 46204 | AJ78: =VLOOKUP(B78,'Ces, Esc, RTS and Retail'!$A:$B,2,0) -> #N/A | AK78: =VLOOKUP(F78,'Ces, Esc, RTS and Retail'!$D:$F,3,0) -> #N/A | AL78: =VLOOKUP(B78,'Ces, Esc, RTS and Retail'!$H:$H,1,0) -> #N/A | AM78: =VLOOKUP(Q78,'Ces, Esc, RTS and Retail'!$J:$J,1,0) -> #N/A | AN78: =VLOOKUP(Q78,'[2]Trip Manager Report(Updated)_V2'!$I:$Z,18,0) -> #N/A | AO78: =VLOOKUP(E78,'Ces, Esc, RTS and Retail'!$L:$L,1,0) -> #N/A | AP78: =VLOOKUP(Q78,Response!$H:$M,5,0) -> #N/A
A79: Wakefit | B79: ORDER202606MGr3fw | C79: Vani Pathuri | D79: F2112, 21, Brigade EL Dorado, F 2112 ,21st floor,Feldspar block, Aerospace park, Huvinayakanahalli | E79: 562149 | F79: 8977348488 | G79: 9490966299 | H79: WSTNOTIQ160CW | J79: furniture | K79: 1007126157 | L79: Height Adjustable Study Table | M79: FG01 | N79: 1 | O79: ONLINE | P79: 26060590002774 | Q79: WFFI451740 | R79: BLR LOCAL | S79: Normal Order | T79: Docketed | U79: 2026-06-01 | V79: 2026-06-01 | W79: 2026-06-22 | X79: 2026-06-24 | Y79: 2026-06-05T21:15:43 | AA79: P0 | AB79: 0 | AD79: =VLOOKUP(Q79,'[1]an1asv_22-06-2026_06-23-43'!$B:$OA,3,0) -> reachedathub | AE79: =VLOOKUP(Q79,'[1]an1asv_22-06-2026_06-23-43'!$B:$OA,147,0) -> Outside Service Location | AF79: =VLOOKUP(Q79,'[1]an1asv_22-06-2026_06-23-43'!$B:$OA,48,0) -> 46196 | AG79: =VLOOKUP(F79,Response!$A:$B,2,0) -> #N/A | AH79: Outside Service Location | AJ79: =VLOOKUP(B79,'Ces, Esc, RTS and Retail'!$A:$B,2,0) -> #N/A | AK79: =VLOOKUP(F79,'Ces, Esc, RTS and Retail'!$D:$F,3,0) -> #N/A | AL79: =VLOOKUP(B79,'Ces, Esc, RTS and Retail'!$H:$H,1,0) -> #N/A | AM79: =VLOOKUP(Q79,'Ces, Esc, RTS and Retail'!$J:$J,1,0) -> #N/A | AN79: =VLOOKUP(Q79,'[2]Trip Manager Report(Updated)_V2'!$I:$Z,18,0) -> #N/A | AO79: =VLOOKUP(E79,'Ces, Esc, RTS and Retail'!$L:$L,1,0) -> 562149 | AP79: =VLOOKUP(Q79,Response!$H:$M,5,0) -> #N/A | AQ79: =VLOOKUP(B79,#REF!,9,0) -> #REF!
A80: Flipkart | B80: OD437719514664279100 | C80: Shreyansh Shrivastava | D80: 1st floor, SLN Nilaya Apparment, mear SLN water supply Hennur Bande, Kalyan Nagar, Near St. Paul High School | E80: 560043 | F80: 9691671862 | H80: WEWB7860STAURUSR2 | I80: 78x60 inch | J80: furniture | K80: 1003000472 | L80: Engineered Wood Bed | M80: FG01 | N80: 1 | O80: ONLINE | P80: 26060590010905 | Q80: WFFI461076 | R80: BLR LOCAL | S80: Normal Order | T80: Docketed | U80: 2026-06-02 | V80: 2026-06-02 | W80: 2026-06-12 | X80: 2026-06-13 | Y80: 2026-06-22T10:53:16 | AA80: Breached | AB80: 0 | AD80: =VLOOKUP(Q80,'[1]an1asv_22-06-2026_06-23-43'!$B:$OA,3,0) -> reachedathub | AE80: =VLOOKUP(Q80,'[1]an1asv_22-06-2026_06-23-43'!$B:$OA,147,0) -> 0 | AF80: =VLOOKUP(Q80,'[1]an1asv_22-06-2026_06-23-43'!$B:$OA,48,0) -> 46195 | AG80: =VLOOKUP(F80,Response!$A:$B,2,0) -> #N/A | AH80: CNR | AJ80: =VLOOKUP(B80,'Ces, Esc, RTS and Retail'!$A:$B,2,0) -> #N/A | AK80: =VLOOKUP(F80,'Ces, Esc, RTS and Retail'!$D:$F,3,0) -> #N/A | AL80: =VLOOKUP(B80,'Ces, Esc, RTS and Retail'!$H:$H,1,0) -> #N/A | AM80: =VLOOKUP(Q80,'Ces, Esc, RTS and Retail'!$J:$J,1,0) -> #N/A | AN80: =VLOOKUP(Q80,'[2]Trip Manager Report(Updated)_V2'!$I:$Z,18,0) -> #N/A | AO80: =VLOOKUP(E80,'Ces, Esc, RTS and Retail'!$L:$L,1,0) -> #N/A | AP80: =VLOOKUP(Q80,Response!$H:$M,5,0) -> #N/A
A81: Wakefit_Retail | B81: ORDER202605E8TGII | C81: Shrinivasan Gopalakrishnan | D81: No.13/3, Vishal Residency, 2nd cross, MLA Layout, Lottegollahalli, | E81: 560094 | F81: 9986997719 | G81: 9686578845 | H81: WEWB7860STAURUSR2 | I81: 78x60 inch | J81: furniture | K81: 1003000472 | L81: Engineered Wood Bed | M81: FG01 | N81: 1 | O81: ONLINE | P81: 26060590010817 | Q81: WFFI460988 | R81: BLR LOCAL | S81: Normal Order | T81: Docketed | U81: 2026-05-31 | V81: 2026-06-02 | W81: 2026-06-23 | X81: 2026-06-23 | Y81: 2026-06-22T10:51:31 | AA81: Breached | AB81: 0 | AD81: =VLOOKUP(Q81,'[1]an1asv_22-06-2026_06-23-43'!$B:$OA,3,0) -> reachedathub | AE81: =VLOOKUP(Q81,'[1]an1asv_22-06-2026_06-23-43'!$B:$OA,147,0) -> 0 | AF81: =VLOOKUP(Q81,'[1]an1asv_22-06-2026_06-23-43'!$B:$OA,48,0) -> 46195 | AG81: =VLOOKUP(F81,Response!$A:$B,2,0) -> 1 | AH81: Planned | AJ81: =VLOOKUP(B81,'Ces, Esc, RTS and Retail'!$A:$B,2,0) -> #N/A | AK81: =VLOOKUP(F81,'Ces, Esc, RTS and Retail'!$D:$F,3,0) -> #N/A | AL81: =VLOOKUP(B81,'Ces, Esc, RTS and Retail'!$H:$H,1,0) -> #N/A | AM81: =VLOOKUP(Q81,'Ces, Esc, RTS and Retail'!$J:$J,1,0) -> #N/A | AN81: =VLOOKUP(Q81,'[2]Trip Manager Report(Updated)_V2'!$I:$Z,18,0) -> #N/A | AO81: =VLOOKUP(E81,'Ces, Esc, RTS and Retail'!$L:$L,1,0) -> #N/A | AP81: =VLOOKUP(Q81,Response!$H:$M,5,0) -> #N/A
A82: Amazon | B82: 403-3709383-9072335 | C82: Santhosh Ranganathan | D82: Sanviros Global Pvt Ltd #18, 2nd floor, 1st A main road, Ganganagar Extn | E82: 560032 | F82: 6366101983 | H82: WTVUCOSBY | J82: furniture | K82: 1007000863 | L82: Tv Unit | M82: FG01 | N82: 1 | O82: ONLINE | P82: 26060590010907 | Q82: WFFI461078 | R82: BLR LOCAL | S82: Normal Order | T82: Docketed | U82: 2026-06-02 | V82: 2026-06-02 | W82: 2026-06-23 | X82: 2026-07-01 | Y82: 2026-06-22T10:53:19 | AA82: P1 | AB82: 0 | AD82: =VLOOKUP(Q82,'[1]an1asv_22-06-2026_06-23-43'!$B:$OA,3,0) -> reachedathub | AE82: =VLOOKUP(Q82,'[1]an1asv_22-06-2026_06-23-43'!$B:$OA,147,0) -> 0 | AF82: =VLOOKUP(Q82,'[1]an1asv_22-06-2026_06-23-43'!$B:$OA,48,0) -> 46195 | AG82: =VLOOKUP(F82,Response!$A:$B,2,0) -> #N/A | AH82: Capcity Filled-Not Called | AJ82: =VLOOKUP(B82,'Ces, Esc, RTS and Retail'!$A:$B,2,0) -> #N/A | AK82: =VLOOKUP(F82,'Ces, Esc, RTS and Retail'!$D:$F,3,0) -> #N/A | AL82: =VLOOKUP(B82,'Ces, Esc, RTS and Retail'!$H:$H,1,0) -> #N/A | AM82: =VLOOKUP(Q82,'Ces, Esc, RTS and Retail'!$J:$J,1,0) -> #N/A | AN82: =VLOOKUP(Q82,'[2]Trip Manager Report(Updated)_V2'!$I:$Z,18,0) -> #N/A | AO82: =VLOOKUP(E82,'Ces, Esc, RTS and Retail'!$L:$L,1,0) -> #N/A | AP82: =VLOOKUP(Q82,Response!$H:$M,5,0) -> #N/A
A83: Wakefit_Retail | B83: ORDER202606Ykg4cP | C83: Hemashree Gowda | D83: No 32 1st floor 6th e main 2nd stage west of chord road Mahalakshmi pura Bangalore 86 | E83: 560086 | F83: 9900117963 | H83: WSTSAGER1 | J83: furniture | K83: 1007100321 | L83: Study Table | M83: FG01 | N83: 1 | O83: COD | P83: 26060590010275 | Q83: WFFI460488 | R83: BLR LOCAL | S83: Normal Order | T83: Docketed | U83: 2026-06-02 | V83: 2026-06-02 | W83: 2026-06-22 | X83: 2026-06-23 | Y83: 2026-06-21T11:42:33 | AA83: Breached | AB83: 0 | AD83: =VLOOKUP(Q83,'[1]an1asv_22-06-2026_06-23-43'!$B:$OA,3,0) -> reachedathub | AE83: =VLOOKUP(Q83,'[1]an1asv_22-06-2026_06-23-43'!$B:$OA,147,0) -> 0 | AF83: =VLOOKUP(Q83,'[1]an1asv_22-06-2026_06-23-43'!$B:$OA,48,0) -> 46195 | AG83: =VLOOKUP(F83,Response!$A:$B,2,0) -> #N/A | AH83: Planned | AJ83: =VLOOKUP(B83,'Ces, Esc, RTS and Retail'!$A:$B,2,0) -> #N/A | AK83: =VLOOKUP(F83,'Ces, Esc, RTS and Retail'!$D:$F,3,0) -> #N/A | AL83: =VLOOKUP(B83,'Ces, Esc, RTS and Retail'!$H:$H,1,0) -> #N/A | AM83: =VLOOKUP(Q83,'Ces, Esc, RTS and Retail'!$J:$J,1,0) -> #N/A | AN83: =VLOOKUP(Q83,'[2]Trip Manager Report(Updated)_V2'!$I:$Z,18,0) -> #N/A | AO83: =VLOOKUP(E83,'Ces, Esc, RTS and Retail'!$L:$L,1,0) -> #N/A | AP83: =VLOOKUP(Q83,Response!$H:$M,5,0) -> Yes
A84: Wakefit | B84: ORDER202606a739Le | C84: Sandeep L | D84: 134, Eshavasyam, 9th cross Duo marvel layout, Ananthapura Road, Yelahanka | E84: 560064 | F84: 9964383593 | G84: 9964383593 | H84: WEWB7230SALT | I84: 72x30 inch | J84: furniture | K84: 1001019160 | L84: Engineered Wood Bed | M84: FG01 | N84: 1 | O84: ONLINE | P84: 26060590010890 | Q84: WFFI461062 | R84: BLR LOCAL | S84: Normal Order | T84: Docketed | U84: 2026-06-02 | V84: 2026-06-02 | W84: 2026-06-22 | X84: 2026-06-23 | Y84: 2026-06-22T10:53:00 | AA84: Breached | AB84: 0 | AD84: =VLOOKUP(Q84,'[1]an1asv_22-06-2026_06-23-43'!$B:$OA,3,0) -> reachedathub | AE84: =VLOOKUP(Q84,'[1]an1asv_22-06-2026_06-23-43'!$B:$OA,147,0) -> 0 | AF84: =VLOOKUP(Q84,'[1]an1asv_22-06-2026_06-23-43'!$B:$OA,48,0) -> 46195 | AG84: =VLOOKUP(F84,Response!$A:$B,2,0) -> #N/A | AH84: CNR | AJ84: =VLOOKUP(B84,'Ces, Esc, RTS and Retail'!$A:$B,2,0) -> #N/A | AK84: =VLOOKUP(F84,'Ces, Esc, RTS and Retail'!$D:$F,3,0) -> #N/A | AL84: =VLOOKUP(B84,'Ces, Esc, RTS and Retail'!$H:$H,1,0) -> #N/A | AM84: =VLOOKUP(Q84,'Ces, Esc, RTS and Retail'!$J:$J,1,0) -> #N/A | AN84: =VLOOKUP(Q84,'[2]Trip Manager Report(Updated)_V2'!$I:$Z,18,0) -> #N/A | AO84: =VLOOKUP(E84,'Ces, Esc, RTS and Retail'!$L:$L,1,0) -> #N/A | AP84: =VLOOKUP(Q84,Response!$H:$M,5,0) -> #N/A
A85: Wakefit | B85: ORDER202606L9XknK | C85: Sandra | D85: B 008, Amigo Amparo, Sy no 75/17, chokanahali village main road, | E85: 560064 | F85: 9790653023 | G85: 9606012089 | H85: WBDSTTINKER | J85: furniture | K85: 1007001569 | L85: Bedside Table | M85: FG01 | N85: 1 | O85: ONLINE | P85: 26060590010815 | Q85: WFFI460985 | R85: BLR LOCAL | S85: Normal Order | T85: Docketed | U85: 2026-06-02 | V85: 2026-06-02 | W85: 2026-06-22 | X85: 2026-06-23 | Y85: 2026-06-22T10:51:29 | AA85: Breached | AB85: 0 | AD85: =VLOOKUP(Q85,'[1]an1asv_22-06-2026_06-23-43'!$B:$OA,3,0) -> reachedathub | AE85: =VLOOKUP(Q85,'[1]an1asv_22-06-2026_06-23-43'!$B:$OA,147,0) -> 0 | AF85: =VLOOKUP(Q85,'[1]an1asv_22-06-2026_06-23-43'!$B:$OA,48,0) -> 46195 | AG85: =VLOOKUP(F85,Response!$A:$B,2,0) -> 1 | AH85: Planned | AJ85: =VLOOKUP(B85,'Ces, Esc, RTS and Retail'!$A:$B,2,0) -> #N/A | AK85: =VLOOKUP(F85,'Ces, Esc, RTS and Retail'!$D:$F,3,0) -> #N/A | AL85: =VLOOKUP(B85,'Ces, Esc, RTS and Retail'!$H:$H,1,0) -> #N/A | AM85: =VLOOKUP(Q85,'Ces, Esc, RTS and Retail'!$J:$J,1,0) -> #N/A | AN85: =VLOOKUP(Q85,'[2]Trip Manager Report(Updated)_V2'!$I:$Z,18,0) -> #N/A | AO85: =VLOOKUP(E85,'Ces, Esc, RTS and Retail'!$L:$L,1,0) -> #N/A | AP85: =VLOOKUP(Q85,Response!$H:$M,5,0) -> #N/A
A86: Wakefit | B86: ORDER202606S9Z6mB | C86: Sushma Gs | D86: #12,rudramsha,2nd main gowdara colony,rmv 2nd stage,nagashettyhally,bangalore | E86: 560094 | F86: 8792492341 | H86: WWRB2TWILLNOR1 | J86: furniture | K86: 1007003996 | L86: Wardrobes | M86: FG01 | N86: 1 | O86: ONLINE | P86: 26060590010274 | Q86: WFFI460487 | R86: BLR LOCAL | S86: Normal Order | T86: Docketed | U86: 2026-06-02 | V86: 2026-06-02 | W86: 2026-06-22 | X86: 2026-06-23 | Y86: 2026-06-21T11:42:33 | AA86: Breached | AB86: 0 | AD86: =VLOOKUP(Q86,'[1]an1asv_22-06-2026_06-23-43'!$B:$OA,3,0) -> reachedathub | AE86: =VLOOKUP(Q86,'[1]an1asv_22-06-2026_06-23-43'!$B:$OA,147,0) -> 0 | AF86: =VLOOKUP(Q86,'[1]an1asv_22-06-2026_06-23-43'!$B:$OA,48,0) -> 46195 | AG86: =VLOOKUP(F86,Response!$A:$B,2,0) -> 1 | AH86: Planned | AJ86: =VLOOKUP(B86,'Ces, Esc, RTS and Retail'!$A:$B,2,0) -> #N/A | AK86: =VLOOKUP(F86,'Ces, Esc, RTS and Retail'!$D:$F,3,0) -> #N/A | AL86: =VLOOKUP(B86,'Ces, Esc, RTS and Retail'!$H:$H,1,0) -> #N/A | AM86: =VLOOKUP(Q86,'Ces, Esc, RTS and Retail'!$J:$J,1,0) -> #N/A | AN86: =VLOOKUP(Q86,'[2]Trip Manager Report(Updated)_V2'!$I:$Z,18,0) -> #N/A | AO86: =VLOOKUP(E86,'Ces, Esc, RTS and Retail'!$L:$L,1,0) -> #N/A | AP86: =VLOOKUP(Q86,Response!$H:$M,5,0) -> 0
A87: Wakefit | B87: ORDER202606IBrXoh | C87: Navya | D87: Y-6, 3, Yugan’s residence, 10th D main, Nisarga Layout, Ananthpura, Yelahanka | E87: 560064 | F87: 8951462489 | G87: 8951462489 | H87: WEWB7860NONCNTR | I87: 78x60 inch | J87: furniture | K87: 1001024342 | L87: Engineered Wood Bed | M87: FG01 | N87: 1 | O87: ONLINE | P87: 26060590010668 | Q87: WFFI460895 | R87: BLR LOCAL | S87: Normal Order | T87: Docketed | U87: 2026-06-02 | V87: 2026-06-02 | W87: 2026-06-21 | X87: 2026-06-22 | Y87: 2026-06-22T09:36:22 | AA87: Breached | AB87: 0 | AD87: =VLOOKUP(Q87,'[1]an1asv_22-06-2026_06-23-43'!$B:$OA,3,0) -> reachedathub | AE87: =VLOOKUP(Q87,'[1]an1asv_22-06-2026_06-23-43'!$B:$OA,147,0) -> 0 | AF87: =VLOOKUP(Q87,'[1]an1asv_22-06-2026_06-23-43'!$B:$OA,48,0) -> 46195 | AG87: =VLOOKUP(F87,Response!$A:$B,2,0) -> 1 | AH87: Planned | AJ87: =VLOOKUP(B87,'Ces, Esc, RTS and Retail'!$A:$B,2,0) -> #N/A | AK87: =VLOOKUP(F87,'Ces, Esc, RTS and Retail'!$D:$F,3,0) -> #N/A | AL87: =VLOOKUP(B87,'Ces, Esc, RTS and Retail'!$H:$H,1,0) -> #N/A | AM87: =VLOOKUP(Q87,'Ces, Esc, RTS and Retail'!$J:$J,1,0) -> #N/A | AN87: =VLOOKUP(Q87,'[2]Trip Manager Report(Updated)_V2'!$I:$Z,18,0) -> #N/A | AO87: =VLOOKUP(E87,'Ces, Esc, RTS and Retail'!$L:$L,1,0) -> #N/A | AP87: =VLOOKUP(Q87,Response!$H:$M,5,0) -> #N/A
A88: Amazon | B88: 403-7701125-5793938 | C88: Chaithanya | D88: Block A, 604 Century Breeze apartments, Hindus Cemetery Road, Nehru Nagar | E88: 560064 | F88: 9538817007 | H88: WWRB2DTWILLDBR2 | J88: furniture | K88: 1007124268 | L88: Wardrobes | M88: FG01 | N88: 1 | O88: ONLINE | P88: 26060590010701 | Q88: WFFI460926 | R88: BLR LOCAL | S88: Normal Order | T88: Docketed | U88: 2026-06-02 | V88: 2026-06-02 | W88: 2026-06-21 | X88: 2026-06-27 | Y88: 2026-06-22T09:37:21 | AA88: P1 | AB88: 0 | AD88: =VLOOKUP(Q88,'[1]an1asv_22-06-2026_06-23-43'!$B:$OA,3,0) -> reachedathub | AE88: =VLOOKUP(Q88,'[1]an1asv_22-06-2026_06-23-43'!$B:$OA,147,0) -> 0 | AF88: =VLOOKUP(Q88,'[1]an1asv_22-06-2026_06-23-43'!$B:$OA,48,0) -> 46195 | AG88: =VLOOKUP(F88,Response!$A:$B,2,0) -> #N/A | AH88: Capcity Filled-Not Called | AJ88: =VLOOKUP(B88,'Ces, Esc, RTS and Retail'!$A:$B,2,0) -> #N/A | AK88: =VLOOKUP(F88,'Ces, Esc, RTS and Retail'!$D:$F,3,0) -> #N/A | AL88: =VLOOKUP(B88,'Ces, Esc, RTS and Retail'!$H:$H,1,0) -> #N/A | AM88: =VLOOKUP(Q88,'Ces, Esc, RTS and Retail'!$J:$J,1,0) -> #N/A | AN88: =VLOOKUP(Q88,'[2]Trip Manager Report(Updated)_V2'!$I:$Z,18,0) -> #N/A | AO88: =VLOOKUP(E88,'Ces, Esc, RTS and Retail'!$L:$L,1,0) -> #N/A | AP88: =VLOOKUP(Q88,Response!$H:$M,5,0) -> #N/A
A89: Amazon | B89: 408-1684737-9372350 | C89: Sarwath Galaria | D89: D1501, Salarpuria Sattva Gold Summit, Hennur Bagalur Road Kothanur,Decathalon | E89: 560077 | F89: 9945154330 | H89: WWRB2TWILLFWR2 | J89: furniture | K89: 1007129090 | L89: Wardrobes | M89: FG01 | N89: 1 | O89: ONLINE | P89: 26060590010675 | Q89: WFFI460900 | R89: BLR LOCAL | S89: Normal Order | T89: Docketed | U89: 2026-06-02 | V89: 2026-06-02 | W89: 2026-06-14 | X89: 2026-06-20 | Y89: 2026-06-22T09:36:48 | AA89: Breached | AB89: 0 | AD89: =VLOOKUP(Q89,'[1]an1asv_22-06-2026_06-23-43'!$B:$OA,3,0) -> reachedathub | AE89: =VLOOKUP(Q89,'[1]an1asv_22-06-2026_06-23-43'!$B:$OA,147,0) -> 0 | AF89: =VLOOKUP(Q89,'[1]an1asv_22-06-2026_06-23-43'!$B:$OA,48,0) -> 46195 | AG89: =VLOOKUP(F89,Response!$A:$B,2,0) -> 2506 | AH89: CFR | AI89: 46198 | AJ89: =VLOOKUP(B89,'Ces, Esc, RTS and Retail'!$A:$B,2,0) -> #N/A | AK89: =VLOOKUP(F89,'Ces, Esc, RTS and Retail'!$D:$F,3,0) -> #N/A | AL89: =VLOOKUP(B89,'Ces, Esc, RTS and Retail'!$H:$H,1,0) -> #N/A | AM89: =VLOOKUP(Q89,'Ces, Esc, RTS and Retail'!$J:$J,1,0) -> #N/A | AN89: =VLOOKUP(Q89,'[2]Trip Manager Report(Updated)_V2'!$I:$Z,18,0) -> #N/A | AO89: =VLOOKUP(E89,'Ces, Esc, RTS and Retail'!$L:$L,1,0) -> #N/A | AP89: =VLOOKUP(Q89,Response!$H:$M,5,0) -> #N/A
A90: Wakefit | B90: ORDER202606bMDgrj | C90: Itikana Manna | D90: 22, sai adith nilaya, vinayaka layout,ramamurthy nagar | E90: 560016 | F90: 6297832717 | G90: 6297832717 | H90: WEWB7872HYSALGOL | I90: 78x72 inch | J90: furniture | K90: 1007003113 | L90: Engineered Wood Bed | M90: FG01 | N90: 1 | O90: ONLINE | P90: 26060590010853 | Q90: WFFI461026 | R90: BLR LOCAL | S90: Normal Order | T90: Docketed | U90: 2026-06-02 | V90: 2026-06-02 | W90: 2026-06-22 | X90: 2026-06-23 | Y90: 2026-06-22T10:52:17 | AA90: Breached | AB90: 0 | AD90: =VLOOKUP(Q90,'[1]an1asv_22-06-2026_06-23-43'!$B:$OA,3,0) -> reachedathub | AE90: =VLOOKUP(Q90,'[1]an1asv_22-06-2026_06-23-43'!$B:$OA,147,0) -> 0 | AF90: =VLOOKUP(Q90,'[1]an1asv_22-06-2026_06-23-43'!$B:$OA,48,0) -> 46195 | AG90: =VLOOKUP(F90,Response!$A:$B,2,0) -> 1 | AH90: Planned | AJ90: =VLOOKUP(B90,'Ces, Esc, RTS and Retail'!$A:$B,2,0) -> #N/A | AK90: =VLOOKUP(F90,'Ces, Esc, RTS and Retail'!$D:$F,3,0) -> #N/A | AL90: =VLOOKUP(B90,'Ces, Esc, RTS and Retail'!$H:$H,1,0) -> #N/A | AM90: =VLOOKUP(Q90,'Ces, Esc, RTS and Retail'!$J:$J,1,0) -> #N/A | AN90: =VLOOKUP(Q90,'[2]Trip Manager Report(Updated)_V2'!$I:$Z,18,0) -> #N/A | AO90: =VLOOKUP(E90,'Ces, Esc, RTS and Retail'!$L:$L,1,0) -> #N/A | AP90: =VLOOKUP(Q90,Response!$H:$M,5,0) -> #N/A
A91: Amazon | B91: 406-2485693-9085108 | C91: Allan L Warjri | D91: H-502, KOLTE PATIL RAAGA APARTMENTS KANNUR, BELLAHALLI VILLAGE | E91: 562149 | F91: 9436119306 | H91: WEWB7236NONTAURUSR2 | I91: 72x36 inch | J91: furniture | K91: 1007100455 | L91: Engineered Wood Bed | M91: FG01 | N91: 1 | O91: ONLINE | P91: 26060590010869 | Q91: WFFI461045 | R91: BLR LOCAL | S91: Normal Order | T91: Docketed | U91: 2026-06-02 | V91: 2026-06-02 | W91: 2026-06-16 | X91: 2026-06-24 | Y91: 2026-06-22T10:52:41 | AA91: P0 | AB91: 0 | AD91: =VLOOKUP(Q91,'[1]an1asv_22-06-2026_06-23-43'!$B:$OA,3,0) -> reachedathub | AE91: =VLOOKUP(Q91,'[1]an1asv_22-06-2026_06-23-43'!$B:$OA,147,0) -> 0 | AF91: =VLOOKUP(Q91,'[1]an1asv_22-06-2026_06-23-43'!$B:$OA,48,0) -> 46195 | AG91: =VLOOKUP(F91,Response!$A:$B,2,0) -> #N/A | AH91: Outside Service Location | AJ91: =VLOOKUP(B91,'Ces, Esc, RTS and Retail'!$A:$B,2,0) -> #N/A | AK91: =VLOOKUP(F91,'Ces, Esc, RTS and Retail'!$D:$F,3,0) -> #N/A | AL91: =VLOOKUP(B91,'Ces, Esc, RTS and Retail'!$H:$H,1,0) -> #N/A | AM91: =VLOOKUP(Q91,'Ces, Esc, RTS and Retail'!$J:$J,1,0) -> #N/A | AN91: =VLOOKUP(Q91,'[2]Trip Manager Report(Updated)_V2'!$I:$Z,18,0) -> #N/A | AO91: =VLOOKUP(E91,'Ces, Esc, RTS and Retail'!$L:$L,1,0) -> 562149 | AP91: =VLOOKUP(Q91,Response!$H:$M,5,0) -> #N/A | AQ91: =VLOOKUP(B91,#REF!,9,0) -> #REF!
A92: Amazon | B92: 406-2485693-9085108 | C92: Allan L Warjri | D92: H-502, KOLTE PATIL RAAGA APARTMENTS KANNUR, BELLAHALLI VILLAGE | E92: 562149 | F92: 9436119306 | H92: WEWB7236NONTAURUSR2 | I92: 72x36 inch | J92: furniture | K92: 1007100455 | L92: Engineered Wood Bed | M92: FG01 | N92: 1 | O92: ONLINE | P92: 26060590010874 | Q92: WFFI461051 | R92: BLR LOCAL | S92: Normal Order | T92: Docketed | U92: 2026-06-02 | V92: 2026-06-02 | W92: 2026-06-16 | X92: 2026-06-24 | Y92: 2026-06-22T10:52:48 | AA92: P0 | AB92: 0 | AD92: =VLOOKUP(Q92,'[1]an1asv_22-06-2026_06-23-43'!$B:$OA,3,0) -> reachedathub | AE92: =VLOOKUP(Q92,'[1]an1asv_22-06-2026_06-23-43'!$B:$OA,147,0) -> 0 | AF92: =VLOOKUP(Q92,'[1]an1asv_22-06-2026_06-23-43'!$B:$OA,48,0) -> 46195 | AG92: =VLOOKUP(F92,Response!$A:$B,2,0) -> #N/A | AH92: Outside Service Location | AJ92: =VLOOKUP(B92,'Ces, Esc, RTS and Retail'!$A:$B,2,0) -> #N/A | AK92: =VLOOKUP(F92,'Ces, Esc, RTS and Retail'!$D:$F,3,0) -> #N/A | AL92: =VLOOKUP(B92,'Ces, Esc, RTS and Retail'!$H:$H,1,0) -> #N/A | AM92: =VLOOKUP(Q92,'Ces, Esc, RTS and Retail'!$J:$J,1,0) -> #N/A | AN92: =VLOOKUP(Q92,'[2]Trip Manager Report(Updated)_V2'!$I:$Z,18,0) -> #N/A | AO92: =VLOOKUP(E92,'Ces, Esc, RTS and Retail'!$L:$L,1,0) -> 562149 | AP92: =VLOOKUP(Q92,Response!$H:$M,5,0) -> #N/A | AQ92: =VLOOKUP(B92,#REF!,9,0) -> #REF!
A93: Wakefit | B93: ORDER202606PT4e4u | C93: Raja Singh | D93: No. 71, 4, 5th Cross Ramaiah Layout, 1st Main Road Hegganahalli | E93: 560058 | F93: 8095668682 | G93: 8095668682 | H93: WEWB7860SUPOPLTAURUSR2 | I93: 78x60 inch | J93: furniture | K93: 1007003118 | L93: Engineered Wood Bed | M93: FG01 | N93: 1 | O93: ONLINE | P93: 26060590010862 | Q93: WFFI461034 | R93: BLR LOCAL | S93: Normal Order | T93: Docketed | U93: 2026-06-02 | V93: 2026-06-02 | W93: 2026-06-22 | X93: 2026-06-23 | Y93: 2026-06-22T10:52:26 | AA93: Breached | AB93: 0 | AD93: =VLOOKUP(Q93,'[1]an1asv_22-06-2026_06-23-43'!$B:$OA,3,0) -> reachedathub | AE93: =VLOOKUP(Q93,'[1]an1asv_22-06-2026_06-23-43'!$B:$OA,147,0) -> 0 | AF93: =VLOOKUP(Q93,'[1]an1asv_22-06-2026_06-23-43'!$B:$OA,48,0) -> 46195 | AG93: =VLOOKUP(F93,Response!$A:$B,2,0) -> 1 | AH93: Planned | AJ93: =VLOOKUP(B93,'Ces, Esc, RTS and Retail'!$A:$B,2,0) -> #N/A | AK93: =VLOOKUP(F93,'Ces, Esc, RTS and Retail'!$D:$F,3,0) -> #N/A | AL93: =VLOOKUP(B93,'Ces, Esc, RTS and Retail'!$H:$H,1,0) -> #N/A | AM93: =VLOOKUP(Q93,'Ces, Esc, RTS and Retail'!$J:$J,1,0) -> #N/A | AN93: =VLOOKUP(Q93,'[2]Trip Manager Report(Updated)_V2'!$I:$Z,18,0) -> #N/A | AO93: =VLOOKUP(E93,'Ces, Esc, RTS and Retail'!$L:$L,1,0) -> #N/A | AP93: =VLOOKUP(Q93,Response!$H:$M,5,0) -> #N/A
A94: Flipkart | B94: OD437727129804463100 | C94: Muppala Priya | D94: #504, Neelima Nilayam 61 Thubarahalli, ELV Brindavan Layout Road, Whitefield | E94: 560066 | F94: 9148845655 | H94: WEWB7860STAURUSR2 | I94: 78x60 inch | J94: furniture | K94: 1003000472 | L94: Engineered Wood Bed | M94: FG01 | N94: 1 | O94: ONLINE | P94: 26060590010144 | Q94: WFFI460308 | R94: BLR LOCAL | S94: Normal Order | T94: Docketed | U94: 2026-06-02 | V94: 2026-06-02 | W94: 2026-06-13 | X94: 2026-06-14 | Y94: 2026-06-20T19:32:43 | AA94: Breached | AB94: 0 | AD94: =VLOOKUP(Q94,'[1]an1asv_22-06-2026_06-23-43'!$B:$OA,3,0) -> reachedathub | AE94: =VLOOKUP(Q94,'[1]an1asv_22-06-2026_06-23-43'!$B:$OA,147,0) -> CNR/ No Date from Customer | AF94: =VLOOKUP(Q94,'[1]an1asv_22-06-2026_06-23-43'!$B:$OA,48,0) -> 46196 | AG94: =VLOOKUP(F94,Response!$A:$B,2,0) -> #N/A | AH94: CNR | AJ94: =VLOOKUP(B94,'Ces, Esc, RTS and Retail'!$A:$B,2,0) -> #N/A | AK94: =VLOOKUP(F94,'Ces, Esc, RTS and Retail'!$D:$F,3,0) -> #N/A | AL94: =VLOOKUP(B94,'Ces, Esc, RTS and Retail'!$H:$H,1,0) -> #N/A | AM94: =VLOOKUP(Q94,'Ces, Esc, RTS and Retail'!$J:$J,1,0) -> #N/A | AN94: =VLOOKUP(Q94,'[2]Trip Manager Report(Updated)_V2'!$I:$Z,18,0) -> #N/A | AO94: =VLOOKUP(E94,'Ces, Esc, RTS and Retail'!$L:$L,1,0) -> #N/A | AP94: =VLOOKUP(Q94,Response!$H:$M,5,0) -> #N/A
A95: Flipkart | B95: OD337727288634919100 | C95: Nishanth K | D95: 101 Zion castle Swarnadhama Layout, 1st Main Road, Sathya Layout, B Narayanapura, Mahadevapura | E95: 560016 | F95: 8867559323 | H95: WBDSTTINKER | J95: furniture | K95: 1007001569 | L95: Bedside Table | M95: FG01 | N95: 1 | O95: ONLINE | P95: 26060590010870 | Q95: WFFI461038 | R95: BLR LOCAL | S95: Normal Order | T95: Docketed | U95: 2026-06-02 | V95: 2026-06-02 | W95: 2026-06-15 | X95: 2026-06-16 | Y95: 2026-06-22T10:52:34 | AA95: Breached | AB95: 0 | AD95: =VLOOKUP(Q95,'[1]an1asv_22-06-2026_06-23-43'!$B:$OA,3,0) -> reachedathub | AE95: =VLOOKUP(Q95,'[1]an1asv_22-06-2026_06-23-43'!$B:$OA,147,0) -> 0 | AF95: =VLOOKUP(Q95,'[1]an1asv_22-06-2026_06-23-43'!$B:$OA,48,0) -> 46195 | AG95: =VLOOKUP(F95,Response!$A:$B,2,0) -> #N/A | AH95: CNR | AJ95: =VLOOKUP(B95,'Ces, Esc, RTS and Retail'!$A:$B,2,0) -> #N/A | AK95: =VLOOKUP(F95,'Ces, Esc, RTS and Retail'!$D:$F,3,0) -> #N/A | AL95: =VLOOKUP(B95,'Ces, Esc, RTS and Retail'!$H:$H,1,0) -> #N/A | AM95: =VLOOKUP(Q95,'Ces, Esc, RTS and Retail'!$J:$J,1,0) -> #N/A | AN95: =VLOOKUP(Q95,'[2]Trip Manager Report(Updated)_V2'!$I:$Z,18,0) -> #N/A | AO95: =VLOOKUP(E95,'Ces, Esc, RTS and Retail'!$L:$L,1,0) -> #N/A | AP95: =VLOOKUP(Q95,Response!$H:$M,5,0) -> #N/A
A96: Amazon | B96: 405-0324615-2508355 | C96: NAVEEN GAONKAR | D96: Flat no D005 MIMS Residency Thanisandra Main Road Sampigehalli | E96: 560064 | F96: 8618268619 | H96: WEWB7860HYSTAURUSR4 | I96: 78x60 inch | J96: furniture | K96: 1001019058 | L96: Engineered Wood Bed | M96: FG01 | N96: 1 | O96: ONLINE | P96: 26060590003561 | Q96: WFFI452442 | R96: BLR LOCAL | S96: Normal Order | T96: Docketed | U96: 2026-06-02 | V96: 2026-06-02 | W96: 2026-06-23 | X96: 2026-06-29 | Y96: 2026-06-07T09:41:33 | AA96: P1 | AB96: 0 | AD96: =VLOOKUP(Q96,'[1]an1asv_22-06-2026_06-23-43'!$B:$OA,3,0) -> reachedathub | AE96: =VLOOKUP(Q96,'[1]an1asv_22-06-2026_06-23-43'!$B:$OA,147,0) -> CNR/ No Date from Customer | AF96: =VLOOKUP(Q96,'[1]an1asv_22-06-2026_06-23-43'!$B:$OA,48,0) -> 46196 | AG96: =VLOOKUP(F96,Response!$A:$B,2,0) -> #N/A | AH96: Capcity Filled-Not Called | AJ96: =VLOOKUP(B96,'Ces, Esc, RTS and Retail'!$A:$B,2,0) -> #N/A | AK96: =VLOOKUP(F96,'Ces, Esc, RTS and Retail'!$D:$F,3,0) -> #N/A | AL96: =VLOOKUP(B96,'Ces, Esc, RTS and Retail'!$H:$H,1,0) -> #N/A | AM96: =VLOOKUP(Q96,'Ces, Esc, RTS and Retail'!$J:$J,1,0) -> #N/A | AN96: =VLOOKUP(Q96,'[2]Trip Manager Report(Updated)_V2'!$I:$Z,18,0) -> #N/A | AO96: =VLOOKUP(E96,'Ces, Esc, RTS and Retail'!$L:$L,1,0) -> #N/A | AP96: =VLOOKUP(Q96,Response!$H:$M,5,0) -> #N/A
A97: Wakefit | B97: ORDER202606sRGQ4q | C97: harish M | D97: 2, 104 Mayur Signature Apartment,Chikkatirupati road , Channasandra, Whitefield | E97: 560067 | F97: 9036545467 | G97: 8904155368 | H97: WCFTJAVA | J97: furniture | K97: 1003010011 | L97: Coffee Table | M97: FG01 | N97: 1 | O97: ONLINE | P97: 26060590010903 | Q97: WFFI461075 | R97: BLR LOCAL | S97: Normal Order | T97: Docketed | U97: 2026-06-02 | V97: 2026-06-02 | W97: 2026-06-22 | X97: 2026-06-23 | Y97: 2026-06-22T10:53:13 | AA97: Breached | AB97: 0 | AD97: =VLOOKUP(Q97,'[1]an1asv_22-06-2026_06-23-43'!$B:$OA,3,0) -> reachedathub | AE97: =VLOOKUP(Q97,'[1]an1asv_22-06-2026_06-23-43'!$B:$OA,147,0) -> 0 | AF97: =VLOOKUP(Q97,'[1]an1asv_22-06-2026_06-23-43'!$B:$OA,48,0) -> 46195 | AG97: =VLOOKUP(F97,Response!$A:$B,2,0) -> #N/A | AH97: CNR | AJ97: =VLOOKUP(B97,'Ces, Esc, RTS and Retail'!$A:$B,2,0) -> #N/A | AK97: =VLOOKUP(F97,'Ces, Esc, RTS and Retail'!$D:$F,3,0) -> #N/A | AL97: =VLOOKUP(B97,'Ces, Esc, RTS and Retail'!$H:$H,1,0) -> #N/A | AM97: =VLOOKUP(Q97,'Ces, Esc, RTS and Retail'!$J:$J,1,0) -> #N/A | AN97: =VLOOKUP(Q97,'[2]Trip Manager Report(Updated)_V2'!$I:$Z,18,0) -> #N/A | AO97: =VLOOKUP(E97,'Ces, Esc, RTS and Retail'!$L:$L,1,0) -> #N/A | AP97: =VLOOKUP(Q97,Response!$H:$M,5,0) -> #N/A
A98: Wakefit | B98: ORDER202606rtbtOx | C98: Neha M | D98: 80, 2, Standalone House, 8th E Cross, 14th G Main Road, Weavers layout, Attiguppe | E98: 560040 | F98: 9818549455 | G98: 9818549455 | H98: WEWB7860STAURUSR2 | I98: 78x60 inch | J98: furniture | K98: 1003000472 | L98: Engineered Wood Bed | M98: FG01 | N98: 1 | O98: ONLINE | P98: 26060590010840 | Q98: WFFI461016 | R98: BLR LOCAL | S98: Normal Order | T98: Docketed | U98: 2026-06-03 | V98: 2026-06-03 | W98: 2026-06-22 | X98: 2026-06-23 | Y98: 2026-06-22T10:52:05 | AA98: Breached | AB98: 0 | AD98: =VLOOKUP(Q98,'[1]an1asv_22-06-2026_06-23-43'!$B:$OA,3,0) -> reachedathub | AE98: =VLOOKUP(Q98,'[1]an1asv_22-06-2026_06-23-43'!$B:$OA,147,0) -> 0 | AF98: =VLOOKUP(Q98,'[1]an1asv_22-06-2026_06-23-43'!$B:$OA,48,0) -> 46195 | AG98: =VLOOKUP(F98,Response!$A:$B,2,0) -> #N/A | AH98: CNR | AJ98: =VLOOKUP(B98,'Ces, Esc, RTS and Retail'!$A:$B,2,0) -> #N/A | AK98: =VLOOKUP(F98,'Ces, Esc, RTS and Retail'!$D:$F,3,0) -> #N/A | AL98: =VLOOKUP(B98,'Ces, Esc, RTS and Retail'!$H:$H,1,0) -> #N/A | AM98: =VLOOKUP(Q98,'Ces, Esc, RTS and Retail'!$J:$J,1,0) -> #N/A | AN98: =VLOOKUP(Q98,'[2]Trip Manager Report(Updated)_V2'!$I:$Z,18,0) -> #N/A | AO98: =VLOOKUP(E98,'Ces, Esc, RTS and Retail'!$L:$L,1,0) -> #N/A | AP98: =VLOOKUP(Q98,Response!$H:$M,5,0) -> #N/A
A99: Wakefit | B99: ORDER202606epbOFY | C99: Vainateya J | D99: 107, 1, Benaka Homes Libero Apt, Seenappa Layout, New BEL Road | E99: 560094 | F99: 8600252427 | G99: 8600252427 | H99: WSTFULLER | J99: furniture | K99: 1007000790 | L99: Study Table | M99: FG01 | N99: 1 | O99: ONLINE | P99: 26060590010235 | Q99: WFFI460458 | R99: BLR LOCAL | S99: Normal Order | T99: Docketed | U99: 2026-06-03 | V99: 2026-06-03 | W99: 2026-06-22 | X99: 2026-06-23 | Y99: 2026-06-21T11:41:38 | AA99: Breached | AB99: 0 | AD99: =VLOOKUP(Q99,'[1]an1asv_22-06-2026_06-23-43'!$B:$OA,3,0) -> reachedathub | AE99: =VLOOKUP(Q99,'[1]an1asv_22-06-2026_06-23-43'!$B:$OA,147,0) -> 0 | AF99: =VLOOKUP(Q99,'[1]an1asv_22-06-2026_06-23-43'!$B:$OA,48,0) -> 46195 | AG99: =VLOOKUP(F99,Response!$A:$B,2,0) -> #N/A | AH99: Planned | AJ99: =VLOOKUP(B99,'Ces, Esc, RTS and Retail'!$A:$B,2,0) -> #N/A | AK99: =VLOOKUP(F99,'Ces, Esc, RTS and Retail'!$D:$F,3,0) -> #N/A | AL99: =VLOOKUP(B99,'Ces, Esc, RTS and Retail'!$H:$H,1,0) -> #N/A | AM99: =VLOOKUP(Q99,'Ces, Esc, RTS and Retail'!$J:$J,1,0) -> #N/A | AN99: =VLOOKUP(Q99,'[2]Trip Manager Report(Updated)_V2'!$I:$Z,18,0) -> #N/A | AO99: =VLOOKUP(E99,'Ces, Esc, RTS and Retail'!$L:$L,1,0) -> #N/A | AP99: =VLOOKUP(Q99,Response!$H:$M,5,0) -> Yes
A100: Wakefit | B100: ORDER202606FqCipM | C100: Nimisha | D100: A2 702, 7, Sandeep Vihar, Kannamangla | E100: 560067 | F100: 9718378702 | G100: 9794861514 | H100: WEWB7860STAURUSR2 | I100: 78x60 inch | J100: furniture | K100: 1003000472 | L100: Engineered Wood Bed | M100: FG01 | N100: 1 | O100: ONLINE | P100: 26060590010839 | Q100: WFFI461011 | R100: BLR LOCAL | S100: Normal Order | T100: Docketed | U100: 2026-06-03 | V100: 2026-06-03 | W100: 2026-06-22 | X100: 2026-06-23 | Y100: 2026-06-22T10:51:57 | AA100: Breached | AB100: 0 | AD100: =VLOOKUP(Q100,'[1]an1asv_22-06-2026_06-23-43'!$B:$OA,3,0) -> reachedathub | AE100: =VLOOKUP(Q100,'[1]an1asv_22-06-2026_06-23-43'!$B:$OA,147,0) -> 0 | AF100: =VLOOKUP(Q100,'[1]an1asv_22-06-2026_06-23-43'!$B:$OA,48,0) -> 46195 | AG100: =VLOOKUP(F100,Response!$A:$B,2,0) -> #N/A | AH100: CNR | AJ100: =VLOOKUP(B100,'Ces, Esc, RTS and Retail'!$A:$B,2,0) -> #N/A | AK100: =VLOOKUP(F100,'Ces, Esc, RTS and Retail'!$D:$F,3,0) -> #N/A | AL100: =VLOOKUP(B100,'Ces, Esc, RTS and Retail'!$H:$H,1,0) -> #N/A | AM100: =VLOOKUP(Q100,'Ces, Esc, RTS and Retail'!$J:$J,1,0) -> #N/A | AN100: =VLOOKUP(Q100,'[2]Trip Manager Report(Updated)_V2'!$I:$Z,18,0) -> #N/A | AO100: =VLOOKUP(E100,'Ces, Esc, RTS and Retail'!$L:$L,1,0) -> #N/A | AP100: =VLOOKUP(Q100,Response!$H:$M,5,0) -> #N/A
...

Sheet Route plan  23.06.2026
A1: Platform | B1: order_random_id | C1: cx_name | D1: address | E1: pincode | F1: Route | G1: item_sku | H1: mobile_number | I1: alternate_mobile_number | J1: item_sku | K1: item_dimensions | L1: scm_master_category | M1: Material_code | N1: Product_Type | O1: storage_location | P1: item_quantity | Q1: payment_type | R1: invoice_number | S1: docket_number | T1: LP | U1: Order_Type | V1: Order_Status | W1: Order_Date | X1: Order_Confirmed_Date | Y1: promised_dispatch | Z1: Promised_EDD | AA1: docket_timestamp | AB1: shipped_timestamp | AC1: priority_local | AD1: escalated | AE1: escalation_type | AF1: Status | AG1: Previous Reason | AH1: Previous date | AI1: Response | AJ1: Planning | AK1: Date | AL1: Retail | AM1: CES | AN1: ESC | AO1: RTS | AP1: NDR | AQ1: ODA | AR1: Manual | AS1: qsqs
A2: Wakefit | B2: ORDER202606MZ0ql4 | C2: Asha P | D2: 26/1, 2, Harshith, 10th Main Road, Shivanagar, Rajajinagar | E2: 560010 | F2: 1 | G2: WEWB7230SALT | H2: 9844267875 | I2: 9844267875 | J2: WEWB7230SALT | K2: 72x30 inch | L2: furniture | M2: 1001019160 | N2: Engineered Wood Bed | O2: FG01 | P2: 1 | Q2: ONLINE | R2: 26060590010927 | S2: WFFI461091 | T2: BLR LOCAL | U2: Normal Order | V2: Docketed | W2: 2026-06-19 | X2: 2026-06-19 | Y2: 2026-06-22 | Z2: 2026-06-23 | AA2: 2026-06-22T11:07:33 | AC2: Breached | AD2: 0 | AF2: reachedathub | AG2: 0 | AH2: 46195 | AI2: 1 | AJ2: Planned | AL2: #N/A | AM2: #N/A | AN2: #N/A | AO2: #N/A | AP2: #N/A | AQ2: #N/A | AR2: #N/A | AS2: #N/A
A3: Wakefit | B3: ORDER202606wrov0N | C3: Manish Chopra | D3: 51, 2, Jaya Govindam, 51, 4th Cross Rd, Raghavendra Colony, Chamrajpet, | E3: 560018 | F3: 1 | G3: WEWB7860STAURUSR2 | H3: 8088486035 | I3: 8088486035 | J3: WEWB7860STAURUSR2 | K3: 78x60 inch | L3: furniture | M3: 1003000472 | N3: Engineered Wood Bed | O3: FG01 | P3: 1 | Q3: ONLINE | R3: 26060590010374 | S3: WFFI460706 | T3: BLR LOCAL | U3: Normal Order | V3: Docketed | W3: 2026-06-18 | X3: 2026-06-18 | Y3: 2026-06-21 | Z3: 2026-06-22 | AA3: 2026-06-21T13:37:20 | AC3: Breached | AD3: 0 | AF3: reachedathub | AG3: 0 | AH3: 46195 | AI3: 1 | AJ3: Planned | AL3: #N/A | AM3: #N/A | AN3: #N/A | AO3: #N/A | AP3: #N/A | AQ3: #N/A | AR3: #N/A | AS3: #N/A
A4: Amazon | B4: 405-5771125-9023561 | C4: Sinchana | D4: 3rd floor, #126/A, KN extension 3rd cross triveni road, Yeshwanthpur | E4: 560022 | F4: 1 | G4: WSTEDWIN | H4: 6361107591 | I4: 6361107591 | J4: WSTEDWIN | L4: furniture | M4: 1001013646 | N4: Study Table | O4: FG01 | P4: 1 | Q4: ONLINE | R4: 26060590009254 | S4: WFFI459005 | T4: BLR LOCAL | U4: Normal Order | V4: Shipped | W4: 2026-06-14 | X4: 2026-06-14 | Y4: 2026-06-17 | Z4: 2026-06-20 | AA4: 2026-06-18T17:38:08 | AB4: 2026-06-19T21:04:03 | AC4: Breached | AD4: 0 | AF4: reachedathub | AG4: INSUFFICIENT TIME | AH4: 46195 | AI4: 1 | AJ4: Planned | AL4: #N/A | AM4: #N/A | AN4: #N/A | AO4: #N/A | AP4: #N/A | AQ4: #N/A | AR4: #N/A | AS4: #N/A
A5: Wakefit | B5: ORDER202606mdgh33 | C5: Sachin Dengre | D5: 807, 8, Vaishnavi Ars Gardenia, Ayyappa Temple Road, T Dasarhalli | E5: 560057 | F5: 1 | G5: WEWB7872STAURUSMA | H5: 9902665787 | I5: 9902665787 | J5: WEWB7872STAURUSMA | K5: 78x72 inch | L5: furniture | M5: 1001024787 | N5: Engineered Wood Bed | O5: FG01 | P5: 1 | Q5: ONLINE | R5: 26060590010871 | S5: WFFI461040 | T5: BLR LOCAL | U5: Normal Order | V5: Docketed | W5: 2026-06-20 | X5: 2026-06-20 | Y5: 2026-06-22 | Z5: 2026-06-23 | AA5: 2026-06-22T10:52:36 | AC5: Breached | AD5: 0 | AF5: reachedathub | AG5: 0 | AH5: 46195 | AI5: 1 | AJ5: Planned | AL5: #N/A | AM5: #N/A | AN5: #N/A | AO5: #N/A | AP5: #N/A | AQ5: #N/A | AR5: #N/A | AS5: #N/A
A6: Wakefit | B6: ORDER202606PT4e4u | C6: Raja Singh | D6: No. 71, 4, 5th Cross Ramaiah Layout, 1st Main Road Hegganahalli | E6: 560058 | F6: 1 | G6: WEWB7860SUPOPLTAURUSR2 | H6: 8095668682 | I6: 8095668682 | J6: WEWB7860SUPOPLTAURUSR2 | K6: 78x60 inch | L6: furniture | M6: 1007003118 | N6: Engineered Wood Bed | O6: FG01 | P6: 1 | Q6: ONLINE | R6: 26060590010862 | S6: WFFI461034 | T6: BLR LOCAL | U6: Normal Order | V6: Docketed | W6: 2026-06-02 | X6: 2026-06-02 | Y6: 2026-06-22 | Z6: 2026-06-23 | AA6: 2026-06-22T10:52:26 | AC6: Breached | AD6: 0 | AF6: reachedathub | AG6: 0 | AH6: 46195 | AI6: 1 | AJ6: Planned | AL6: #N/A | AM6: #N/A | AN6: #N/A | AO6: #N/A | AP6: #N/A | AQ6: #N/A | AR6: #N/A | AS6: #N/A
A7: Wakefit | B7: ORDER202606VkHrB7 | C7: Vinod | D7: Floor-20, Flat No 25291 , 29 th floor, building 2 tower 5 | E7: 560073 | F7: 1 | G7: WEWB7236NONTAURUSR2 | H7: 9972781519 | J7: WEWB7236NONTAURUSR2 | K7: 72x36 inch | L7: furniture | M7: 1007100455 | N7: Engineered Wood Bed | O7: FG01 | P7: 1 | Q7: ONLINE | R7: 26060590010673 | S7: WFFI460906 | T7: BLR LOCAL | U7: Normal Order | V7: Docketed | W7: 2026-06-07 | X7: 2026-06-07 | Y7: 2026-06-27 | Z7: 2026-06-28 | AA7: 2026-06-22T09:36:56 | AC7: P1 | AD7: 0 | AF7: reachedathub | AG7: 0 | AH7: 46195 | AI7: 1 | AJ7: Planned | AL7: #N/A | AM7: #N/A | AN7: #N/A | AO7: #N/A | AP7: #N/A | AQ7: #N/A | AR7: #N/A | AS7: #N/A
A8: Wakefit | B8: ORDER202606VkHrB7 | C8: Vinod | D8: Floor-20, Flat No 25291 , 29 th floor, building 2 tower 5 | E8: 560073 | F8: 1 | G8: WEWB7560STAURUSR2 | H8: 9972781519 | J8: WEWB7560STAURUSR2 | K8: 75x60 inch | L8: furniture | M8: 1001024999 | N8: Engineered Wood Bed | O8: FG01 | P8: 1 | Q8: ONLINE | R8: 26060590010681 | S8: WFFI460912 | T8: BLR LOCAL | U8: Normal Order | V8: Docketed | W8: 2026-06-07 | X8: 2026-06-07 | Y8: 2026-06-23 | Z8: 2026-06-24 | AA8: 2026-06-22T09:37:01 | AC8: P0 | AD8: 0 | AF8: reachedathub | AG8: 0 | AH8: 46195 | AI8: 1 | AJ8: Planned | AL8: #N/A | AM8: #N/A | AN8: #N/A | AO8: #N/A | AP8: #N/A | AQ8: #N/A | AR8: #N/A | AS8: #N/A
A9: Wakefit | B9: ORDER202606vZLfew | C9: Vinod | D9: 25291, 29, Prestige Jindal city, 25291..Prestige Jindal city | E9: 560073 | F9: 1 | G9: WCFTLEONISCW | H9: 9972781519 | I9: 9972781519 | J9: WCFTLEONISCW | L9: furniture | M9: 1007003568 | N9: Coffee Table | O9: FG01 | P9: 1 | Q9: ONLINE | R9: 26060590010846 | S9: WFFI461018 | T9: BLR LOCAL | U9: Normal Order | V9: Docketed | W9: 2026-06-20 | X9: 2026-06-20 | Y9: 2026-06-23 | Z9: 2026-06-24 | AA9: 2026-06-22T10:52:07 | AC9: P0 | AD9: 0 | AF9: reachedathub | AG9: 0 | AH9: 46195 | AI9: 1 | AJ9: Planned | AL9: #N/A | AM9: #N/A | AN9: #N/A | AO9: #N/A | AP9: #N/A | AQ9: #N/A | AR9: #N/A | AS9: #N/A
A10: Wakefit | B10: ORDER202606fHqbC7 | C10: Markandeya BS | D10: NO 87, 1, NANDAGOKULA, ANCHEPALYA ROAD TOTADA GUDDADAHALLY | E10: 560073 | F10: 1 | G10: WEWB7230SCRX | H10: 9632329741 | I10: 9632329741 | J10: WEWB7230SCRX | K10: 72x30 inch | L10: furniture | M10: 1001019159 | N10: Engineered Wood Bed | O10: FG01 | P10: 1 | Q10: COD | R10: 26060590010829 | S10: WFFI461000 | T10: BLR LOCAL | U10: Normal Order | V10: Docketed | W10: 2026-06-20 | X10: 2026-06-20 | Y10: 2026-06-23 | Z10: 2026-06-24 | AA10: 2026-06-22T10:51:44 | AC10: P0 | AD10: 0 | AF10: reachedathub | AG10: 0 | AH10: 46195 | AI10: 1 | AJ10: Planned | AL10: #N/A | AM10: #N/A | AN10: #N/A | AO10: #N/A | AP10: #N/A | AQ10: #N/A | AR10: #N/A | AS10: #N/A
A11: Wakefit_Retail | B11: ORDER202606Ykg4cP | C11: Hemashree Gowda | D11: No 32 1st floor 6th e main 2nd stage west of chord road Mahalakshmi pura Bangalore 86 | E11: 560086 | F11: 1 | G11: WSTSAGER1 | H11: 9900117963 | J11: WSTSAGER1 | L11: furniture | M11: 1007100321 | N11: Study Table | O11: FG01 | P11: 1 | Q11: COD | R11: 26060590010275 | S11: WFFI460488 | T11: BLR LOCAL | U11: Normal Order | V11: Docketed | W11: 2026-06-02 | X11: 2026-06-02 | Y11: 2026-06-22 | Z11: 2026-06-23 | AA11: 2026-06-21T11:42:33 | AC11: Breached | AD11: 0 | AF11: reachedathub | AG11: 0 | AH11: 46195 | AI11: #N/A | AJ11: Planned | AL11: #N/A | AM11: #N/A | AN11: #N/A | AO11: #N/A | AP11: #N/A | AQ11: #N/A | AR11: Yes | AS11: #N/A
A12: RP -Esc | B12: ORDER202506yA18h0 | C12: Sohan Pawar | D12: Basaveshwaranagar banagalore | E12: 560079 | F12: 1 | G12: WEWB7860HYSTAURUSR4 | H12: 9886867003 | J12: WEWB7860HYSTAURUSR4 | R12: 25060590019302 | S12: WFRFWI116640
A13: Amazon | B13: 404-3686386-6730741 | C13: Nitin Pai | D13: No 25, 1st floor, Dee Enclave, 2nd cross, kodigehalli main road | E13: 560092 | F13: 2 | G13: WWRB4DMH1ORGANZAPCWR2 | H13: 8861625771 | J13: WWRB4DMH1ORGANZAPCWR2 | L13: furniture | M13: 1007129089 | N13: Wardrobes | O13: FG01 | P13: 1 | Q13: ONLINE | R13: 26060590010838 | S13: WFFI461009 | T13: BLR LOCAL | U13: Normal Order | V13: Docketed | W13: 2026-06-01 | X13: 2026-06-01 | Y13: 2026-06-14 | Z13: 2026-06-20 | AA13: 2026-06-22T10:51:56 | AC13: Breached | AD13: 0 | AF13: reachedathub | AG13: 0 | AH13: 46195 | AI13: 1 | AJ13: Planned | AL13: #N/A | AM13: #N/A | AN13: #N/A | AO13: #N/A | AP13: #N/A | AQ13: #N/A | AR13: #N/A | AS13: #N/A
A14: Wakefit_Retail | B14: ORDER202606SyJHQe | C14: Navyasree Yarlagadda | D14: 1402, 14th floor Tower 33, L&T Raintree Boulevard, Indra Nagar, Sahakar Nagar, Byatarayanapura, Bengaluru | E14: 560092 | F14: 2 | G14: WMCFTKAFFEOSTR1 | H14: 8867788977 | I14: 7386115415 | J14: WMCFTKAFFEOSTR1 | L14: furniture | M14: 1001024424 | N14: Metal Coffee Table | O14: FG01 | P14: 1 | Q14: PREPAID-CASH | R14: 26060590010273 | S14: WFFI460485 | T14: BLR LOCAL | U14: Normal Order | V14: Docketed | W14: 2026-06-01 | X14: 2026-06-01 | Y14: 2026-06-22 | Z14: 2026-06-23 | AA14: 2026-06-21T11:42:30 | AC14: Breached | AD14: 0 | AF14: reachedathub | AG14: 0 | AH14: 46195 | AI14: 1 | AJ14: Planned | AL14: #N/A | AM14: #N/A | AN14: #N/A | AO14: #N/A | AP14: #N/A | AQ14: #N/A | AR14: 0 | AS14: #N/A
A15: Flipkart | B15: OD437864224010997100 | C15: Manish Benziger | D15: #709, 7th Floor Fortuna Acacia, Railway Parallel Road, A Block, Sahakar Nagar, Byatarayanapura, Bengaluru, Karnataka, India | E15: 560092 | F15: 2 | G15: WSCFTLAURINAHF | H15: 8089456911 | J15: WSCFTLAURINAHF | L15: furniture | M15: 1007108850 | N15: Solid Wood Coffee Table | O15: FG01 | P15: 1 | Q15: ONLINE | R15: 26060590009866 | S15: WFFI459803 | T15: BLR LOCAL | U15: Normal Order | V15: Docketed | W15: 2026-06-18 | X15: 2026-06-18 | Y15: 2026-06-22 | Z15: 2026-06-23 | AA15: 2026-06-19T22:56:28 | AC15: Breached | AD15: 0 | AF15: reachedathub | AG15: CNR/ No Date from Customer | AH15: 46196 | AI15: #N/A | AJ15: Planned | AL15: #N/A | AM15: #N/A | AN15: #N/A | AO15: #N/A | AP15: #N/A | AQ15: #N/A | AR15: Yes | AS15: #N/A
A16: Wakefit | B16: ORDER202606BU01AW | C16: Ganesh Kumar | D16: No 23, 1, Bramhalingeshwara bakery, No 23 4th cross near sumangali sev ashram road | E16: 560024 | F16: 2 | G16: WMCFTKALTOSSW | H16: 9008409527 | I16: 9008409527 | J16: WMCFTKALTOSSW | L16: furniture | M16: 1001024708 | N16: Metal Coffee Table | O16: FG01 | P16: 1 | Q16: ONLINE | R16: 26060590008448 | S16: WFFI458188 | T16: BLR LOCAL | U16: Normal Order | V16: Shipped | W16: 2026-06-15 | X16: 2026-06-15 | Y16: 2026-06-18 | Z16: 2026-06-19 | AA16: 2026-06-17T13:35:55 | AB16: 2026-06-20T19:24:25 | AC16: Breached | AD16: 0 | AF16: reachedathub | AG16: Planned | AH16: 46195 | AI16: 1 | AJ16: Planned | AL16: #N/A | AM16: #N/A | AN16: #N/A | AO16: #N/A | AP16: CUSTOMER NOT REACHABLE | AQ16: #N/A | AR16: #N/A | AS16: #N/A
A17: Wakefit_Retail | B17: ORDER202606hoG0r4 | C17: Venkatesh K B | D17: No.76, 5th cross, CIL Layout, Near Narayana School, Cholanayakanahalli, R.T.Nagar Post, Bengaluru - 560032 Floor: 2nd Floor | E17: 560032 | F17: 2 | G17: WEWB7860HYSVENUS | H17: 8553698953 | I17: 9742682726 | J17: WEWB7860HYSVENUS | K17: 78x60 inch | L17: furniture | M17: 1007002463 | N17: Engineered Wood Bed | O17: FG01 | P17: 1 | Q17: ONLINE | R17: 26060590010841 | S17: WFFI461012 | T17: BLR LOCAL | U17: Normal Order | V17: Docketed | W17: 2026-06-08 | X17: 2026-06-08 | Y17: 2026-06-23 | Z17: 2026-06-24 | AA17: 2026-06-22T10:52:01 | AC17: P0 | AD17: 0 | AF17: reachedathub | AG17: 0 | AH17: 46195 | AI17: 1 | AJ17: Planned | AL17: #N/A | AM17: #N/A | AN17: #N/A | AO17: #N/A | AP17: #N/A | AQ17: #N/A | AR17: #N/A | AS17: #N/A
A18: Wakefit | B18: ORDER202606ZmoayV | C18: Ajith C | D18: 1, 4/2, 9th B Cross | E18: 560032 | F18: 2 | G18: WEWB7872SLEOWM | H18: 7845129012 | J18: WEWB7872SLEOWM | K18: 78x72 inch | L18: furniture | M18: 1001024217 | N18: Engineered Wood Bed | O18: FG01 | P18: 1 | Q18: ONLINE | R18: 26060590010659 | S18: WFFI460887 | T18: BLR LOCAL | U18: Normal Order | V18: Docketed | W18: 2026-06-19 | X18: 2026-06-19 | Y18: 2026-06-22 | Z18: 2026-06-23 | AA18: 2026-06-22T09:36:02 | AC18: Breached | AD18: 0 | AF18: reachedathub | AG18: 0 | AH18: 46195 | AI18: #N/A | AJ18: Planned | AL18: #N/A | AM18: #N/A | AN18: #N/A | AO18: #N/A | AP18: #N/A | AQ18: #N/A | AR18: Yes | AS18: #N/A
A19: Wakefit | B19: ORDER2026046NdGSO | C19: Shaloo Bhansali | D19: 4042, 4, Santorini 4, Sobha City, Devin Paradise enclave, Thanisandra | E19: 560045 | F19: 2 | G19: WEWB7860SUPOPLTAURUSR2 | H19: 9098121093 | I19: 9098121093 | J19: WEWB7860SUPOPLTAURUSR2 | K19: 78x60 inch | L19: furniture | M19: 1007003118 | N19: Engineered Wood Bed | O19: FG01 | P19: 1 | Q19: ONLINE | R19: 26060590002134 | S19: WFFI451258 | T19: BLR LOCAL | U19: Replacement | V19: Shipped | W19: 2026-06-04 | X19: 2026-06-04 | Y19: 2026-06-15 | Z19: 2026-06-16 | AA19: 2026-06-04T17:23:15 | AB19: 2026-06-20T19:24:25 | AC19: Breached | AD19: 0 | AF19: reachedathub | AG19: Planned-Esc | AH19: 46195 | AI19: #N/A | AJ19: Planned | AL19: #N/A | AM19: #N/A | AN19: #N/A | AO19: #N/A | AP19: INSUFFICIENT TIME | AQ19: #N/A | AR19: #N/A | AS19: #N/A
A20: Wakefit | B20: ORDER202606q0cZhk | C20: Bandi Raghunath | D20: 143, 2, Slns pg gents, 1st Main road, 3rd cross , vaiyali kaval layout, nagavara | E20: 560045 | F20: 2 | G20: WKSTSTACKL | H20: 7995126990 | I20: 7995126990 | J20: WKSTSTACKL | L20: furniture | M20: 1007111446 | N20: Kids Study Table | O20: FG01 | P20: 1 | Q20: COD | R20: 26060590010799 | S20: WFFI460984 | T20: BLR LOCAL | U20: Normal Order | V20: Docketed | W20: 2026-06-20 | X20: 2026-06-20 | Y20: 2026-06-23 | Z20: 2026-06-24 | AA20: 2026-06-22T10:27:07 | AC20: P0 | AD20: 0 | AF20: reachedathub | AG20: 0 | AH20: 46195 | AI20: 1 | AJ20: Planned | AL20: #N/A | AM20: #N/A | AN20: #N/A | AO20: #N/A | AP20: #N/A | AQ20: #N/A | AR20: #N/A | AS20: #N/A
A21: Wakefit_Retail | B21: ORDER202605TXMROy | C21: Anshuman Mohanto | D21: D-102, ITC Garden Enclave, Jakkur Plantation, Jakkur, 560064, Bengaluru (L) : Jakkur Plantation BENGALURU, KARNATAKA - 560064 | E21: 560064 | F21: 2 | G21: WDINESOMARIS6 | H21: 9659979555 | J21: WDINESOMARIS6 | L21: furniture | M21: 1001039969 | N21: Dining Set | O21: FG01 | P21: 1 | Q21: ONLINE | R21: 26060590009480 | S21: WFFI459246 | T21: BLR LOCAL | U21: Replacement | V21: Shipped | W21: 2026-05-22 | X21: 2026-05-22 | Y21: 2026-06-19 | Z21: 2026-06-22 | AA21: 2026-06-19T11:07:45 | AB21: 2026-06-20T20:45:33 | AC21: Breached | AD21: 0 | AF21: reachedathub | AG21: INSUFFICIENT TIME | AH21: 46195 | AI21: #N/A | AJ21: Planned | AL21: #N/A | AM21: #N/A | AN21: #N/A | AO21: #N/A | AP21: INSUFFICIENT TIME | AQ21: #N/A | AR21: #N/A | AS21: #N/A
A22: Wakefit_Retail | B22: ORDER202606MdJeXC | C22: Chandan N | D22: #72, 7th cross Kamagondanahalli, Abbigere main road, Jalahalli West, Bangalore 560015 | E22: 560015 | F22: 2 | G22: WEWB7836STAURUSR2 | H22: 6364821700 | J22: WEWB7836STAURUSR2 | K22: 78x36 inch | L22: furniture | M22: 1007100317 | N22: Engineered Wood Bed | O22: FG01 | P22: 1 | Q22: COD | R22: 26060590010255 | S22: WFFI460474 | T22: BLR LOCAL | U22: Normal Order | V22: Docketed | W22: 2026-06-13 | X22: 2026-06-19 | Y22: 2026-06-22 | Z22: 2026-06-23 | AA22: 2026-06-21T11:42:05 | AC22: Breached | AD22: 0 | AF22: reachedathub | AG22: 0 | AH22: 46195 | AI22: #N/A | AJ22: Planned | AL22: #N/A | AM22: #N/A | AN22: #N/A | AO22: #N/A | AP22: #N/A | AQ22: #N/A | AR22: Yes | AS22: #N/A
A23: Wakefit_Retail | B23: ORDER202605Z3H3cF | C23: Umar Lone | D23: Ajmera Lakeside Paradise, Flat No. D-205, D Block, 2nd Floor, Kempanahalli, Attur Layout, Yelahanka | E23: 560064 | F23: 3 | G23: WDINEARVWAC1NTBK | H23: 9108520725 | I23: 950117183 | J23: WDINEARVWAC1NTBK | L23: furniture | M23: 1001026062 | N23: Metal Dining Chair | O23: FG01 | P23: 1 | Q23: ONLINE | R23: 26060590010231 | S23: WFFWI223215 | T23: BLR LOCAL | U23: Normal Order | V23: Docketed | W23: 2026-05-28 | X23: 2026-05-28 | Y23: 2026-06-21 | Z23: 2026-06-22 | AA23: 2026-06-21T11:41:40 | AC23: Breached | AD23: 0 | AF23: reachedathub | AG23: 0 | AH23: 46195 | AI23: 1 | AJ23: Planned | AL23: #N/A | AM23: #N/A | AN23: #N/A | AO23: #N/A | AP23: #N/A | AQ23: #N/A | AR23: #N/A | AS23: #N/A
A24: Wakefit_Retail | B24: ORDER202605Z3H3cF | C24: Umar Lone | D24: Ajmera Lakeside Paradise, Flat No. D-205, D Block, 2nd Floor, Kempanahalli, Attur Layout, Yelahanka | E24: 560064 | F24: 3 | G24: WDINEARVWAC1NTBK | H24: 9108520725 | I24: 950117183 | J24: WDINEARVWAC1NTBK | L24: furniture | M24: 1001026062 | N24: Metal Dining Chair | O24: FG01 | P24: 1 | Q24: ONLINE | R24: 26060590010238 | S24: WFFWI223216 | T24: BLR LOCAL | U24: Normal Order | V24: Docketed | W24: 2026-05-28 | X24: 2026-05-28 | Y24: 2026-06-21 | Z24: 2026-06-22 | AA24: 2026-06-21T11:41:40 | AC24: Breached | AD24: 0 | AF24: reachedathub | AG24: 0 | AH24: 46195 | AI24: 1 | AJ24: Planned | AL24: #N/A | AM24: #N/A | AN24: #N/A | AO24: #N/A | AP24: #N/A | AQ24: #N/A | AR24: #N/A | AS24: #N/A
A25: Wakefit | B25: ORDER202606E0MfwP | C25: T Lakshmi Saroja | D25: 1641, 3, #1641, 8th Main, 23rd cross, C Block Sahakarnagar | E25: 560092 | F25: 3 | G25: WSHRKRUBBLE | H25: 9341471810 | I25: 8762706056 | J25: WSHRKRUBBLE | L25: furniture | M25: 1001021994 | N25: Shoe Rack | O25: FG01 | P25: 1 | Q25: COD | R25: 26060590010827 | S25: WFFI460999 | T25: BLR LOCAL | U25: Normal Order | V25: Docketed | W25: 2026-06-20 | X25: 2026-06-20 | Y25: 2026-06-23 | Z25: 2026-06-24 | AA25: 2026-06-22T10:51:44 | AC25: P0 | AD25: 0 | AF25: reachedathub | AG25: 0 | AH25: 46195 | AI25: 1 | AJ25: Planned | AL25: #N/A | AM25: #N/A | AN25: #N/A | AO25: #N/A | AP25: #N/A | AQ25: #N/A | AR25: #N/A | AS25: #N/A
A26: Wakefit_Retail | B26: ORDER202605oFXL2J | C26: Shrinivasan Gopalakrishnan | D26: No.13/3, Vishal Residency, 2nd cross, MLA Layout, Lottegollahalli, | E26: 560094 | F26: 3 | G26: WBDSTTINKER | H26: 9986997719 | I26: 9686578845 | J26: WBDSTTINKER | L26: furniture | M26: 1007001569 | N26: Bedside Table | O26: FG01 | P26: 1 | Q26: ONLINE | R26: 26060590010845 | S26: WFFI461017 | T26: BLR LOCAL | U26: Normal Order | V26: Docketed | W26: 2026-05-31 | X26: 2026-05-31 | Y26: 2026-06-22 | Z26: 2026-06-23 | AA26: 2026-06-22T10:52:05 | AC26: Breached | AD26: 0 | AF26: reachedathub | AG26: 0 | AH26: 46195 | AI26: 1 | AJ26: Planned | AL26: #N/A | AM26: #N/A | AN26: #N/A | AO26: #N/A | AP26: #N/A | AQ26: #N/A | AR26: #N/A | AS26: #N/A
A27: Wakefit_Retail | B27: ORDER202605E8TGII | C27: Shrinivasan Gopalakrishnan | D27: No.13/3, Vishal Residency, 2nd cross, MLA Layout, Lottegollahalli, | E27: 560094 | F27: 3 | G27: WEWB7860STAURUSR2 | H27: 9986997719 | I27: 9686578845 | J27: WEWB7860STAURUSR2 | K27: 78x60 inch | L27: furniture | M27: 1003000472 | N27: Engineered Wood Bed | O27: FG01 | P27: 1 | Q27: ONLINE | R27: 26060590010817 | S27: WFFI460988 | T27: BLR LOCAL | U27: Normal Order | V27: Docketed | W27: 2026-05-31 | X27: 2026-06-02 | Y27: 2026-06-23 | Z27: 2026-06-23 | AA27: 2026-06-22T10:51:31 | AC27: Breached | AD27: 0 | AF27: reachedathub | AG27: 0 | AH27: 46195 | AI27: 1 | AJ27: Planned | AL27: #N/A | AM27: #N/A | AN27: #N/A | AO27: #N/A | AP27: #N/A | AQ27: #N/A | AR27: #N/A | AS27: #N/A
A28: Wakefit | B28: ORDER202606S9Z6mB | C28: Sushma Gs | D28: #12,rudramsha,2nd main gowdara colony,rmv 2nd stage,nagashettyhally,bangalore | E28: 560094 | F28: 3 | G28: WWRB2TWILLNOR1 | H28: 8792492341 | J28: WWRB2TWILLNOR1 | L28: furniture | M28: 1007003996 | N28: Wardrobes | O28: FG01 | P28: 1 | Q28: ONLINE | R28: 26060590010274 | S28: WFFI460487 | T28: BLR LOCAL | U28: Normal Order | V28: Docketed | W28: 2026-06-02 | X28: 2026-06-02 | Y28: 2026-06-22 | Z28: 2026-06-23 | AA28: 2026-06-21T11:42:33 | AC28: Breached | AD28: 0 | AF28: reachedathub | AG28: 0 | AH28: 46195 | AI28: 1 | AJ28: Planned | AL28: #N/A | AM28: #N/A | AN28: #N/A | AO28: #N/A | AP28: #N/A | AQ28: #N/A | AR28: 0 | AS28: #N/A
A29: Wakefit | B29: ORDER202606epbOFY | C29: Vainateya J | D29: 107, 1, Benaka Homes Libero Apt, Seenappa Layout, New BEL Road | E29: 560094 | F29: 3 | G29: WSTFULLER | H29: 8600252427 | I29: 8600252427 | J29: WSTFULLER | L29: furniture | M29: 1007000790 | N29: Study Table | O29: FG01 | P29: 1 | Q29: ONLINE | R29: 26060590010235 | S29: WFFI460458 | T29: BLR LOCAL | U29: Normal Order | V29: Docketed | W29: 2026-06-03 | X29: 2026-06-03 | Y29: 2026-06-22 | Z29: 2026-06-23 | AA29: 2026-06-21T11:41:38 | AC29: Breached | AD29: 0 | AF29: reachedathub | AG29: 0 | AH29: 46195 | AI29: #N/A | AJ29: Planned | AL29: #N/A | AM29: #N/A | AN29: #N/A | AO29: #N/A | AP29: #N/A | AQ29: #N/A | AR29: Yes | AS29: #N/A
A30: Wakefit_Retail | B30: ORDER202606xuexhf | C30: Ajay Thete | D30: #10, T-2 4th floor, Shrishti Residency, 60ft Road, SV Layout, Sanjaynagar, Bangalore 560094 | E30: 560094 | F30: 3 | G30: WEWB7860HYSALGOL | H30: 9880877772 | J30: WEWB7860HYSALGOL | K30: 78x60 inch | L30: furniture | M30: 1007003114 | N30: Engineered Wood Bed | O30: FG01 | P30: 1 | Q30: ONLINE | R30: 26060590010856 | S30: WFFI461027 | T30: BLR LOCAL | U30: Normal Order | V30: Docketed | W30: 2026-06-20 | X30: 2026-06-20 | Y30: 2026-06-23 | Z30: 2026-06-24 | AA30: 2026-06-22T10:52:19 | AC30: P0 | AD30: 0 | AF30: reachedathub | AG30: 0 | AH30: 46195 | AI30: 1 | AJ30: Planned | AL30: #N/A | AM30: #N/A | AN30: #N/A | AO30: #N/A | AP30: #N/A | AQ30: #N/A | AR30: #N/A | AS30: #N/A
A31: Wakefit_Retail | B31: ORDER202605Mmtvak | C31: chandan GS | D31: #35, 1 st floor 17 th cross muthyalanagar Near DC golden lotus Apartment Benaglauru 560054 | E31: 560054 | F31: 3 | G31: WEWB7872HYSTESSERCW | H31: 7353939151 | I31: 9739915331 | J31: WEWB7872HYSTESSERCW | K31: 78x72 inch | L31: furniture | M31: 1001033589 | N31: Engineered Wood Bed | O31: FG01 | P31: 1 | Q31: ONLINE | R31: 26060590009793 | S31: WFFI459752 | T31: BLR LOCAL | U31: Normal Order | V31: Shipped | W31: 2026-05-24 | X31: 2026-05-24 | Y31: 2026-06-21 | Z31: 2026-06-22 | AA31: 2026-06-19T22:21:14 | AB31: 2026-06-20T20:45:33 | AC31: Breached | AD31: 0 | AF31: reachedathub | AG31: CUSTOMER FUTURE REQUEST | AH31: 46195 | AI31: 1 | AJ31: Planned | AL31: #N/A | AM31: #N/A | AN31: #N/A | AO31: #N/A | AP31: CUSTOMER FUTURE REQUEST | AQ31: #N/A | AR31: #N/A | AS31: #N/A
A32: Wakefit | B32: ORDER202606IBrXoh | C32: Navya | D32: Y-6, 3, Yugan’s residence, 10th D main, Nisarga Layout, Ananthpura, Yelahanka | E32: 560064 | F32: 3 | G32: WEWB7860NONCNTR | H32: 8951462489 | I32: 8951462489 | J32: WEWB7860NONCNTR | K32: 78x60 inch | L32: furniture | M32: 1001024342 | N32: Engineered Wood Bed | O32: FG01 | P32: 1 | Q32: ONLINE | R32: 26060590010668 | S32: WFFI460895 | T32: BLR LOCAL | U32: Normal Order | V32: Docketed | W32: 2026-06-02 | X32: 2026-06-02 | Y32: 2026-06-21 | Z32: 2026-06-22 | AA32: 2026-06-22T09:36:22 | AC32: Breached | AD32: 0 | AF32: reachedathub | AG32: 0 | AH32: 46195 | AI32: 1 | AJ32: Planned | AL32: #N/A | AM32: #N/A | AN32: #N/A | AO32: #N/A | AP32: #N/A | AQ32: #N/A | AR32: #N/A | AS32: #N/A
A33: Wakefit_Retail | B33: ORDER202606yv7S5A | C33: Meghana Prasad | D33: 400, 407 SFS, 1st floor,and 2nd floor,4th phase, yelahanka, bangalore | E33: 560064 | F33: 3 | G33: WSWB7872STUDIW | H33: 9686664134 | J33: WSWB7872STUDIW | K33: 78x72 inch | L33: furniture | M33: 1007003417 | N33: Cot | O33: FG01 | P33: 1 | Q33: ONLINE | R33: 26060590010895 | S33: WFFI461066 | T33: BLR LOCAL | U33: Normal Order | V33: Docketed | W33: 2026-06-20 | X33: 2026-06-20 | Y33: 2026-06-23 | Z33: 2026-06-24 | AA33: 2026-06-22T10:53:04 | AC33: P0 | AD33: 0 | AF33: reachedathub | AG33: 0 | AH33: 46195 | AI33: 1 | AJ33: Planned | AL33: #N/A | AM33: #N/A | AN33: #N/A | AO33: #N/A | AP33: #N/A | AQ33: #N/A | AR33: #N/A | AS33: #N/A
A34: Wakefit | B34: ORDER202606pjgjLg | C34: Sujahu Namshid | D34: NO 08, 1, NO 8, Main No 2 1st floor, ,7th Cross Amarjyothi Nagar VIjayanagar | E34: 560040 | F34: 4 | G34: WSTNAYENAPG | H34: 9895642391 | I34: 9895642391 | J34: WSTNAYENAPG | L34: furniture | M34: 1007003988 | N34: Study Table | O34: FG01 | P34: 1 | Q34: ONLINE | R34: 26060590010742 | S34: WFFI460963 | T34: BLR LOCAL | U34: Normal Order | V34: Docketed | W34: 2026-06-20 | X34: 2026-06-20 | Y34: 2026-06-23 | Z34: 2026-06-24 | AA34: 2026-06-22T09:38:03 | AC34: P0 | AD34: 0 | AF34: reachedathub | AG34: 0 | AH34: 46195 | AI34: 1 | AJ34: Planned | AL34: #N/A | AM34: #N/A | AN34: #N/A | AO34: #N/A | AP34: #N/A | AQ34: #N/A | AR34: #N/A | AS34: #N/A
A35: Wakefit_Retail | B35: ORDER202606GOc1gJ | C35: Naveen | D35: #88 GLOBAL STAY SHIVASHREE BUILDING 2ND FLOOR MYLASANDRA | E35: 560059 | F35: 4 | G35: WEWB7872SVENUS | H35: 8310591448 | I35: 8553601240 | J35: WEWB7872SVENUS | K35: 78x72 inch | L35: furniture | M35: 1007002458 | N35: Engineered Wood Bed | O35: FG01 | P35: 1 | Q35: COD | R35: 26060590010889 | S35: WFFI461060 | T35: BLR LOCAL | U35: Normal Order | V35: Docketed | W35: 2026-06-08 | X35: 2026-06-08 | Y35: 2026-06-23 | Z35: 2026-06-24 | AA35: 2026-06-22T10:52:59 | AC35: P0 | AD35: 0 | AF35: reachedathub | AG35: 0 | AH35: 46195 | AI35: 1 | AJ35: Planned | AL35: #N/A | AM35: #N/A | AN35: #N/A | AO35: #N/A | AP35: #N/A | AQ35: #N/A | AR35: #N/A | AS35: #N/A
A36: Wakefit | B36: ORDER202606xQ9Ywh | C36: Swapnajit Panda Panda | D36: T04-4083, 8, Habitat lluminar, Survey No. 49/1/2A/2B Mylasandra Village, Hobli, near R V Engineering College, Kengeri, | E36: 560059 | F36: 4 | G36: WSTATHENACWR1 | H36: 9902496905 | I36: 9902496905 | J36: WSTATHENACWR1 | L36: furniture | M36: 1007000908 | N36: Study Table | O36: FG01 | P36: 1 | Q36: ONLINE | R36: 26060590010904 | S36: WFFI461073 | T36: BLR LOCAL | U36: Normal Order | V36: Docketed | W36: 2026-06-20 | X36: 2026-06-20 | Y36: 2026-06-23 | Z36: 2026-06-24 | AA36: 2026-06-22T10:53:12 | AC36: P0 | AD36: 0 | AF36: reachedathub | AG36: 0 | AH36: 46195 | AI36: 1 | AJ36: Planned | AL36: #N/A | AM36: #N/A | AN36: #N/A | AO36: #N/A | AP36: #N/A | AQ36: #N/A | AR36: #N/A | AS36: #N/A
A37: Wakefit_Retail | B37: ORDER2026066Cm5b9 | C37: Keerthana M | D37: 3/1A3 Ganga nilaya 1st floor 3rd cross harsha layout | E37: 560060 | F37: 4 | G37: WEWB7872HYSTESSERCW | H37: 9986682349 | I37: 9449182182 | J37: WEWB7872HYSTESSERCW | K37: 78x72 inch | L37: furniture | M37: 1001033589 | N37: Engineered Wood Bed | O37: FG01 | P37: 1 | Q37: ONLINE | R37: 26060590009844 | S37: WFFI459799 | T37: BLR LOCAL | U37: Normal Order | V37: Shipped | W37: 2026-06-01 | X37: 2026-06-01 | Y37: 2026-06-21 | Z37: 2026-06-22 | AA37: 2026-06-19T22:22:16 | AB37: 2026-06-20T22:02:52 | AC37: Breached | AD37: 0 | AF37: reachedathub | AG37: Planned | AH37: 46195 | AI37: #N/A | AJ37: Planned | AL37: #N/A | AM37: #N/A | AN37: #N/A | AO37: #N/A | AP37: INSUFFICIENT TIME | AQ37: #N/A | AR37: #N/A | AS37: #N/A
A38: Wakefit_Retail | B38: ORDER202606zAikyD | C38: Yamini Ayushi | D38: Flat no 707, Block A, Casagrand Aquene, Kengeri | E38: 560060 | F38: 4 | G38: WEWB7872SVENUS | H38: 9611717829 | I38: 7828125258 | J38: WEWB7872SVENUS | K38: 78x72 inch | L38: furniture | M38: 1007002458 | N38: Engineered Wood Bed | O38: FG01 | P38: 1 | Q38: ONLINE | R38: 26060590010876 | S38: WFFI461046 | T38: BLR LOCAL | U38: Normal Order | V38: Docketed | W38: 2026-06-04 | X38: 2026-06-04 | Y38: 2026-06-22 | Z38: 2026-06-23 | AA38: 2026-06-22T10:52:41 | AC38: Breached | AD38: 0 | AF38: reachedathub | AG38: 0 | AH38: 46195 | AI38: 1 | AJ38: Planned | AL38: #N/A | AM38: #N/A | AN38: #N/A | AO38: #N/A | AP38: #N/A | AQ38: #N/A | AR38: #N/A | AS38: #N/A
A39: Wakefit_Retail | B39: ORDER202606BImSzn | C39: Abhishek Kumar | D39: Sai gangotri hill crest flat No. 503,5TH FLOOR Ramsandra | E39: 560060 | F39: 4 | G39: WDRUHEKA | H39: 9008601119 | J39: WDRUHEKA | L39: furniture | M39: 1007002430 | N39: Engineered Wood Dressing Table | O39: FG01 | P39: 1 | Q39: ONLINE | R39: 26060590010816 | S39: WFFI460987 | T39: BLR LOCAL | U39: Normal Order | V39: Docketed | W39: 2026-06-07 | X39: 2026-06-07 | Y39: 2026-06-23 | Z39: 2026-06-24 | AA39: 2026-06-22T10:51:31 | AC39: P0 | AD39: 0 | AF39: reachedathub | AG39: 0 | AH39: 46195 | AI39: 1 | AJ39: Planned | AL39: #N/A | AM39: #N/A | AN39: #N/A | AO39: #N/A | AP39: #N/A | AQ39: #N/A | AR39: #N/A | AS39: #N/A
A40: Wakefit | B40: ORDER202605ZT3dT5 | C40: CHAKRAPANI GOTUR | D40: NO-349,RAMA KURUPA,TEACHER"S COLONY,10TH CROSS,NAGARBHAVI | E40: 560072 | F40: 4 | G40: WEWB7830SNORMA | H40: 7382633198 | I40: 8143726501 | J40: WEWB7830SNORMA | K40: 78x30 inch | L40: furniture | M40: 1001021936 | N40: Engineered Wood Bed | O40: FG01 | P40: 1 | Q40: ONLINE | R40: 26060590010371 | S40: WFFI460693 | T40: BLR LOCAL | U40: Normal Order | V40: Docketed | W40: 2026-05-31 | X40: 2026-05-31 | Y40: 2026-06-22 | Z40: 2026-06-23 | AA40: 2026-06-21T13:36:49 | AC40: Breached | AD40: 0 | AF40: reachedathub | AG40: 0 | AH40: 46195 | AI40: #N/A | AJ40: Planned | AL40: #N/A | AM40: #N/A | AN40: #N/A | AO40: #N/A | AP40: #N/A | AQ40: #N/A | AR40: Yes | AS40: #N/A
A41: Wakefit_Retail | B41: ORDER202605nM80DS | C41: Hema L | D41: No-3, 2nd floor, Sapthagiri Nivasa, Karihobanahalli, Andharahalli Main Road | E41: 560091 | F41: 4 | G41: WBSWILDE | H41: 9108713224 | I41: 8453536682 | J41: WBSWILDE | L41: furniture | M41: 1003010026 | N41: Bookshelf | O41: FG01 | P41: 1 | Q41: ONLINE | R41: 26060590010828 | S41: WFFI461004 | T41: BLR LOCAL | U41: Normal Order | V41: Docketed | W41: 2026-05-29 | X41: 2026-05-29 | Y41: 2026-06-22 | Z41: 2026-06-23 | AA41: 2026-06-22T10:51:50 | AC41: Breached | AD41: 0 | AF41: reachedathub | AG41: 0 | AH41: 46195 | AI41: 1 | AJ41: Planned | AL41: #N/A | AM41: #N/A | AN41: #N/A | AO41: #N/A | AP41: #N/A | AQ41: #N/A | AR41: #N/A | AS41: #N/A
A42: Wakefit_Retail | B42: ORDER202606vuY0Xn | C42: Akash mallikarjun Jonnagirimath | D42: RBI STAFF QUARTERS VIJAYNAGAR RPC LAYOUT | E42: 560104 | F42: 4 | G42: WSWB7860TIERHBSW | H42: 9901426828 | I42: 8904512741 | J42: WSWB7860TIERHBSW | K42: 78x60 inch | L42: furniture | M42: 1007120115 | N42: Cot | O42: FG01 | P42: 1 | Q42: ONLINE | R42: 26060590010248 | S42: WFFI460469 | T42: BLR LOCAL | U42: Normal Order | V42: Shipped | W42: 2026-06-01 | X42: 2026-06-01 | Y42: 2026-06-22 | Z42: 2026-06-23 | AA42: 2026-06-21T11:41:52 | AB42: 2026-06-21T21:07:41 | AC42: Breached | AD42: 0 | AF42: reachedathub | AG42: 0 | AH42: 46195 | AI42: #N/A | AJ42: Planned | AL42: 46183 | AM42: #N/A | AN42: #N/A | AO42: #N/A | AP42: #N/A | AQ42: #N/A | AR42: Yes | AS42: #N/A
A43: Installation pending | B43: ORDER2026052HVOis | C43: Sanjay Koushik | D43: Sri vari Residency,house 101,23/18/2,srignadhakaval,D group Layout,gidada konnenahalli,annapurneshwari nagar, | E43: 560091 | F43: 4 | G43: WSWB7872OAKENHBTW | H43: 9036516018 | I43: 8951194486 | J43: WSWB7872OAKENHBTW | R43: 26060590009304 | S43: WFFI459052
A44: CP Visit- Installation- confirm | B44: ORDER202606uTwHUr | C44: Divya Bhardwaj | D44: 1945, Shardamba Nilaya, 1945, Ground floor 21st a main road, vanganhalli, Sector 1, HSR layout | E44: 560102 | F44: Blu Ser 1 | G44: WEWB7860SUPVTTMARSWM | H44: 9650947501 | I44: 9650947501 | J44: WEWB7860SUPVTTMARSWM | R44: 26062060004824 | S44: WFCPV127372
A45: Class 4 Gas-lift 100mm (Taper) | B45: ORDER202308jwxCwP | C45: Varun Menon | D45: A207, PSR Elite, Somasundarapalya HSR Layout Sector 2, Bengluru Karnataka | E45: 560102 | F45: Blu Ser 1 | G45: WSCHRGRAVIHBNBWYWEGYML | H45: 9871872641 | J45: WSCHRGRAVIHBNBWYWEGYML | R45: 23080590046965 | S45: WFPR132024
A46: CP Visit- ESC (Praful) | B46: ORDER2026050jy2wG | C46: Sundeep GUDEKOTE SREEDHARAMOORTHY | D46: Bhuvi by amsha,flat G-504, 5th floor, Tower G, Kadubeesanahalli, panathur, | E46: 560103 | F46: Blu Ser 1 | G46: WSFACRCMN3FVDO | H46: 9164587968 | J46: WSFACRCMN3FVDO | R46: 26060590008838 | S46: WFCPV127368
A47: CP Visit | B47: ORDER202509U4cLqa | C47: Shikhar Sharad | D47: D402, Adarsh Lakefront, Kaikondrahalli, Bellandur | E47: 560103 | F47: Blu Ser 1 | G47: WDINEKOVAC1MBBK | H47: 9686262880 | J47: WDINEKOVAC1MBBK | R47: 25100590113046 | S47: WFCPV127374
A48: CP Visit | B48: ORDER202509U4cLqa | C48: Shikhar Sharad | D48: D402, Adarsh Lakefront, Kaikondrahalli, Bellandur | E48: 560103 | F48: Blu Ser 1 | G48: WDINEKOVAC1MBBK | H48: 9686262880 | J48: WDINEKOVAC1MBBK | R48: 25100590113061 | S48: WFCPV127375
A49: Gravita Grey Back Rest | B49: ORDER2026059iBGA2 | C49: Mohit Mahendra | D49: 838, 11th B Main, 4th Block, Koramangala | E49: 560034 | F49: Blu Ser 1 | G49: WSCHRGRAVIHB3DCBRWYWEGYMLSSR1 | H49: 9718752320 | I49: 9718752320 | J49: WSCHRGRAVIHB3DCBRWYWEGYMLSSR1 | R49: 26062060000275 | S49: WFPR132035
A50: Gravita Grey Seat- Confirm | B50: ORDER202506kzZ0jb | C50: Shubham Singh | D50: building no. 2, 15 Main 21 a cross BTM layout, second stage pince 560076 | E50: 560037 | F50: Blu Ser 1 | G50: WSCHRSAFARHBCBBKBKBKML | H50: 8271447188 | J50: WSCHRSAFARHBCBBKBKBKML | R50: 25060590014980 | S50: WFPR132026
A51: CP Visit- Installation- confirm | B51: ORDER202606RtXNPX | C51: Ashish Bisht | D51: 269, 3, Lila parlour building, 269, 3rd floor, 4th cross, 5th main, viveknagar, Bengaluru | E51: 560047 | F51: Blu Ser 1 | G51: WWRB3S6DMH1SH1TYRIANPPB | H51: 8792547319 | I51: 8792547319 | J51: WWRB3S6DMH1SH1TYRIANPPB | R51: 26062060004055 | S51: WFCPV127371
A52: CP Visit- Installation- confirm | B52: ORDER202605yMYI0Z | C52: Manoj Balakrishnan | D52: Block 1, 2nd floor, Flat no 204, keerthi manor apartment, GM palaya road, new tippasundra, bangalore | E52: 560075 | F52: Blu Ser 1 | G52: WSTNOTIQ160CW | H52: 8095177759 | J52: WSTNOTIQ160CW | R52: 26062060003422 | S52: WFCPV127370
A53: CP Visit- Part | B53: 406-5583758-9872367 | C53: Sneha | D53: A2, 2nd Floor, Malnad Castle Kondappa layout, Kaggadasapura Main Road,Near state bank of India | E53: 560093 | F53: Blu Ser 1 | G53: WSTELAROXCW | H53: 8248629236 | I53: 7598194096 | J53: WSTELAROXCW | R53: 26052060003441 | S53: WFCPV127379
A54: CP Visit -ESC | B54: ORDER202605BB0lHy | C54: Aaditya Mahajan Mahajan | D54: 201, 2, C13, Anugraha layout | E54: 560048 | F54: Blu Ser 1 | G54: WSTNOTIQUT | H54: 8884575446 | R54: 26062060000326
A55: CP Visit- 23rd June 2026 | B55: ORDER202603oUxwCy | C55: veda | D55: 835, 2, sri gowri coffee works, Udaya nagar, near tin factory metro | E55: 560016 | F55: Blu Ser 1 | G55: WSCHRSAFARHBNBBKBKBKMLR2 | H55: 7330933939 | I55: 7330933939 | J55: WSCHRSAFARHBNBBKBKBKMLR2 | R55: 26032430003511 | S55: WFCPV127365
A56: Wakefit | B56: ORDER202605xeJwSe | C56: Vandana Dhayalan | D56: 1592, 2, Atharva, 17th A Main, 5th Block, HBR layout | E56: 560043 | F56: Bluwheel 1 | G56: WBSWILDE | H56: 9886901963 | I56: 9886901963 | J56: WBSWILDE | L56: furniture | M56: 1003010026 | N56: Bookshelf | O56: FG01 | P56: 1 | Q56: ONLINE | R56: 26060590010852 | S56: WFFI461025 | T56: BLR LOCAL | U56: Normal Order | V56: Docketed | W56: 2026-05-30 | X56: 2026-05-30 | Y56: 2026-06-22 | Z56: 2026-06-23 | AA56: 2026-06-22T10:52:15 | AC56: Breached | AD56: 0 | AF56: reachedathub | AG56: 0 | AH56: 46195 | AI56: 1 | AJ56: Planned | AL56: #N/A | AM56: #N/A | AN56: #N/A | AO56: #N/A | AP56: #N/A | AQ56: #N/A | AR56: #N/A | AS56: #N/A
A57: Wakefit | B57: ORDER202606eH98gA | C57: Prajwal Kumar | D57: House no 17, 5th B main road, HRBR layout, 2nd block, Kalyan Nagar | E57: 560043 | F57: Bluwheel 1 | G57: WEWB7560STAURUSR2 | H57: 7358075989 | J57: WEWB7560STAURUSR2 | K57: 75x60 inch | L57: furniture | M57: 1001024999 | N57: Engineered Wood Bed | O57: FG01 | P57: 1 | Q57: ONLINE | R57: 26060590010854 | S57: WFFI461028 | T57: BLR LOCAL | U57: Normal Order | V57: Docketed | W57: 2026-06-01 | X57: 2026-06-01 | Y57: 2026-06-22 | Z57: 2026-06-23 | AA57: 2026-06-22T10:52:20 | AC57: Breached | AD57: 0 | AF57: reachedathub | AG57: 0 | AH57: 46195 | AI57: 1 | AJ57: Planned | AL57: #N/A | AM57: #N/A | AN57: #N/A | AO57: #N/A | AP57: #N/A | AQ57: #N/A | AR57: #N/A | AS57: #N/A
A58: Wakefit | B58: ORDER202606bMDgrj | C58: Itikana Manna | D58: 22, sai adith nilaya, vinayaka layout,ramamurthy nagar | E58: 560016 | F58: Bluwheel 1 | G58: WEWB7872HYSALGOL | H58: 6297832717 | I58: 6297832717 | J58: WEWB7872HYSALGOL | K58: 78x72 inch | L58: furniture | M58: 1007003113 | N58: Engineered Wood Bed | O58: FG01 | P58: 1 | Q58: ONLINE | R58: 26060590010853 | S58: WFFI461026 | T58: BLR LOCAL | U58: Normal Order | V58: Docketed | W58: 2026-06-02 | X58: 2026-06-02 | Y58: 2026-06-22 | Z58: 2026-06-23 | AA58: 2026-06-22T10:52:17 | AC58: Breached | AD58: 0 | AF58: reachedathub | AG58: 0 | AH58: 46195 | AI58: 1 | AJ58: Planned | AL58: #N/A | AM58: #N/A | AN58: #N/A | AO58: #N/A | AP58: #N/A | AQ58: #N/A | AR58: #N/A | AS58: #N/A
A59: Wakefit | B59: ORDER202606Muysmf | C59: manas raj | D59: 2A, 2, House 9, A narayanapura tin factory | E59: 560016 | F59: Bluwheel 1 | G59: WCFTEXCELSA | H59: 7992358704 | I59: 7992358704 | J59: WCFTEXCELSA | L59: furniture | M59: 1003010012 | N59: Coffee Table | O59: FG01 | P59: 1 | Q59: ONLINE | R59: 26060590010931 | S59: WFFI461104 | T59: BLR LOCAL | U59: Normal Order | V59: Docketed | W59: 2026-06-03 | X59: 2026-06-03 | Y59: 2026-06-22 | Z59: 2026-06-23 | AA59: 2026-06-22T11:07:43 | AC59: Breached | AD59: 0 | AF59: reachedathub | AG59: 0 | AH59: 46195 | AI59: 1 | AJ59: Planned | AL59: #N/A | AM59: #N/A | AN59: #N/A | AO59: #N/A | AP59: #N/A | AQ59: #N/A | AR59: #N/A | AS59: #N/A
A60: Wakefit_Retail | B60: ORDER202606LCSC90 | C60: Geetha Leena DSouza | D60: EL SHADDAI HOUSE NO 54 2ND FLOOR 18TH CROSS 2ND BLOCK AKSHYANAGAR | E60: 560016 | F60: Bluwheel 1 | G60: WBSELIOT5 | H60: 9980636688 | I60: 9880179720 | J60: WBSELIOT5 | L60: furniture | M60: 1003010020 | N60: Bookshelf | O60: FG01 | P60: 1 | Q60: ONLINE | R60: 26060590010863 | S60: WFFI461035 | T60: BLR LOCAL | U60: Normal Order | V60: Docketed | W60: 2026-06-07 | X60: 2026-06-07 | Y60: 2026-06-23 | Z60: 2026-06-24 | AA60: 2026-06-22T10:52:30 | AC60: P0 | AD60: 0 | AF60: reachedathub | AG60: 0 | AH60: 46195 | AI60: 1 | AJ60: Planned | AL60: #N/A | AM60: #N/A | AN60: #N/A | AO60: #N/A | AP60: #N/A | AQ60: #N/A | AR60: #N/A | AS60: #N/A
A61: Wakefit_Retail | B61: ORDER202606xXYOPI | C61: Prerna Goel | D61: Flat No. 102, Camden Castle, 16th B Cross, Pai Layout, Bangalore - 560016 | E61: 560016 | F61: Bluwheel 1 | G61: WEWB7872HYSUPOPLMARS | H61: 8168311302 | J61: WEWB7872HYSUPOPLMARS | K61: 78x72 inch | L61: furniture | M61: 1007002500 | N61: Engineered Wood Bed | O61: FG01 | P61: 1 | Q61: ONLINE | R61: 26060590010865 | S61: WFFI461036 | T61: BLR LOCAL | U61: Normal Order | V61: Docketed | W61: 2026-06-08 | X61: 2026-06-08 | Y61: 2026-06-23 | Z61: 2026-06-24 | AA61: 2026-06-22T10:52:31 | AC61: P0 | AD61: 0 | AF61: reachedathub | AG61: 0 | AH61: 46195 | AI61: 1 | AJ61: Planned | AL61: #N/A | AM61: #N/A | AN61: #N/A | AO61: #N/A | AP61: #N/A | AQ61: #N/A | AR61: #N/A | AS61: #N/A
A62: Amazon | B62: 406-5510851-6991526 | C62: Ashwin Raj | D62: 2MGC+MXP, 4th A-cross puttamuniswamappa layout, Raghavendra Nagar, Kalkere | E62: 560016 | F62: Bluwheel 1 | G62: WEWB7860STAURUSR2 | H62: 7406513446 | J62: WEWB7860STAURUSR2 | K62: 78x60 inch | L62: furniture | M62: 1003000472 | N62: Engineered Wood Bed | O62: FG01 | P62: 1 | Q62: ONLINE | R62: 26060590010367 | S62: WFFI460692 | T62: BLR LOCAL | U62: Normal Order | V62: Docketed | W62: 2026-06-18 | X62: 2026-06-18 | Y62: 2026-06-21 | Z62: 2026-06-24 | AA62: 2026-06-21T13:36:48 | AC62: P0 | AD62: 0 | AF62: reachedathub | AG62: 0 | AH62: 46195 | AI62: 1 | AJ62: Planned | AL62: #N/A | AM62: #N/A | AN62: #N/A | AO62: #N/A | AP62: #N/A | AQ62: #N/A | AR62: #N/A | AS62: #N/A
A63: Wakefit | B63: ORDER202606uy9XIr | C63: Nikita V K V K | D63: 65, Eddys nest, First cross , kanaka Vinayaka temple road, Shanthi layout, | E63: 560016 | F63: Bluwheel 1 | G63: WEWB7872STAURUSR2 | H63: 8861023682 | I63: 8861023682 | J63: WEWB7872STAURUSR2 | K63: 78x72 inch | L63: furniture | M63: 1003000471 | N63: Engineered Wood Bed | O63: FG01 | P63: 1 | Q63: ONLINE | R63: 26060590009901 | S63: WFFI459811 | T63: BLR LOCAL | U63: Normal Order | V63: Docketed | W63: 2026-06-18 | X63: 2026-06-18 | Y63: 2026-06-21 | Z63: 2026-06-22 | AA63: 2026-06-20T02:07:51 | AC63: Breached | AD63: 0 | AF63: reachedathub | AG63: Customer Request for Future Date Delivery | AH63: 46196 | AI63: 1 | AJ63: Planned | AL63: #N/A | AM63: #N/A | AN63: #N/A | AO63: #N/A | AP63: #N/A | AQ63: #N/A | AR63: #N/A | AS63: #N/A
A64: Wakefit | B64: ORDER202606A7E5HV | C64: Prabin G | D64: No 16, Sree Valsam, 5 th Cross, Nethaji Street, Ramamurthy Nagar | E64: 560016 | F64: Bluwheel 1 | G64: WSTNAYENA | H64: 9633252438 | I64: 9633252438 | J64: WSTNAYENA | L64: furniture | M64: 1007000789 | N64: Study Table | O64: FG01 | P64: 1 | Q64: ONLINE | R64: 26060590010897 | S64: WFFI461068 | T64: BLR LOCAL | U64: Normal Order | V64: Docketed | W64: 2026-06-20 | X64: 2026-06-20 | Y64: 2026-06-23 | Z64: 2026-06-24 | AA64: 2026-06-22T10:53:07 | AC64: P0 | AD64: 0 | AF64: reachedathub | AG64: 0 | AH64: 46195 | AI64: 1 | AJ64: Planned | AL64: #N/A | AM64: #N/A | AN64: #N/A | AO64: #N/A | AP64: #N/A | AQ64: #N/A | AR64: #N/A | AS64: #N/A
A65: Wakefit | B65: ORDER202606rHFqe2 | C65: Cindy Chingthianmawi Gill | D65: 120/1, Muninanjamma compound, Church street road, Lingarajapuram | E65: 560084 | F65: Bluwheel 1 | G65: WSTCAMUSWM | H65: 6360854119 | I65: 6360854119 | J65: WSTCAMUSWM | L65: furniture | M65: 1001024026 | N65: Study Table | O65: FG01 | P65: 1 | Q65: ONLINE | R65: 26060590010375 | S65: WFFI460694 | T65: BLR LOCAL | U65: Normal Order | V65: Docketed | W65: 2026-06-18 | X65: 2026-06-18 | Y65: 2026-06-20 | Z65: 2026-06-21 | AA65: 2026-06-21T13:36:56 | AC65: Breached | AD65: 0 | AF65: reachedathub | AG65: 0 | AH65: 46195 | AI65: 1 | AJ65: Planned | AL65: #N/A | AM65: #N/A | AN65: #N/A | AO65: #N/A | AP65: #N/A | AQ65: #N/A | AR65: #N/A | AS65: #N/A
A66: Sofa Legs | B66: ORDER202602fHN9s0 | C66: Tom John | D66: Flat no: C12 28 Floor 12 DS MAX Skygrand Kalkere - Agara main road Dodda Kempaiah Layout Kalkere, Bengaluru, Karnataka 560016 | E66: 560016 | F66: Bluwheel 1 | G66: WSFACRCML3CFVBG | H66: 7829903165 | I66: 7829903165 | J66: WSFACRCML3CFVBG | R66: 26040590009983 | S66: WFPR132029
A67: Drift PU Pad | B67: ORDER202606OlS6yK | C67: Ashik Chollangi | D67: 177, 2, Shalini Nilaya, 5th Main Road, ITPL Whitefield Road, B Narayanapura, Mahadevpura | E67: 560016 | F67: Bluwheel 1 | G67: WSCHRGRAVIHBCBWESGSGMLR1 | H67: 7093749274 | I67: 7093749274 | J67: WSCHRGRAVIHBCBWESGSGMLR1 | R67: 26060590002537 | S67: WFPR132032
A68: Wakefit | B68: ORDER202606v3eyPq | C68: vijay mathew | D68: C304, 3, Shekhar Hyde Park, Nagondanahalli | E68: 560066 | F68: Bluwheel 2 | G68: WEWB7560STAURUSR2 | H68: 8867460233 | I68: 8867460233 | J68: WEWB7560STAURUSR2 | K68: 75x60 inch | L68: furniture | M68: 1001024999 | N68: Engineered Wood Bed | O68: FG01 | P68: 1 | Q68: ONLINE | R68: 26060590010913 | S68: WFFI461086 | T68: BLR LOCAL | U68: Normal Order | V68: Docketed | W68: 2026-06-05 | X68: 2026-06-05 | Y68: 2026-06-22 | Z68: 2026-06-23 | AA68: 2026-06-22T10:53:38 | AC68: Breached | AD68: 0 | AF68: reachedathub | AG68: 0 | AH68: 46195 | AI68: 1 | AJ68: Planned | AL68: #N/A | AM68: #N/A | AN68: #N/A | AO68: #N/A | AP68: #N/A | AQ68: #N/A | AR68: #N/A | AS68: #N/A
A69: Wakefit | B69: ORDER202606EDo9xc | C69: VIGNESH S | D69: 11 / 204, 2, Kurmam Residency, Site No:11,Sahasra Gardens,Victorian Layout,Borewell Rd,Nallurahalli Main Road,Whitefield | E69: 560066 | F69: Bluwheel 2 | G69: WEWB7560STAURUSR2 | H69: 8072430963 | I69: 8072430963 | J69: WEWB7560STAURUSR2 | K69: 75x60 inch | L69: furniture | M69: 1001024999 | N69: Engineered Wood Bed | O69: FG01 | P69: 1 | Q69: ONLINE | R69: 26060590010851 | S69: WFFI461022 | T69: BLR LOCAL | U69: Normal Order | V69: Docketed | W69: 2026-06-06 | X69: 2026-06-06 | Y69: 2026-06-22 | Z69: 2026-06-23 | AA69: 2026-06-22T10:52:12 | AC69: Breached | AD69: 0 | AF69: reachedathub | AG69: 0 | AH69: 46195 | AI69: 1 | AJ69: Planned | AL69: #N/A | AM69: #N/A | AN69: #N/A | AO69: #N/A | AP69: #N/A | AQ69: #N/A | AR69: #N/A | AS69: #N/A
A70: Wakefit | B70: ORDER202606fX4wEx | C70: Supriya Waghmare | D70: A-614, 6, Amrutha Platinum Towers, Nallurahalli Main Rd, Palm Meadows, Siddapura, Whitefield | E70: 560066 | F70: Bluwheel 2 | G70: WEWB7560STAURUSR2 | H70: 7028291278 | I70: 7028291278 | J70: WEWB7560STAURUSR2 | K70: 75x60 inch | L70: furniture | M70: 1001024999 | N70: Engineered Wood Bed | O70: FG01 | P70: 1 | Q70: ONLINE | R70: 26060590010909 | S70: WFFI461081 | T70: BLR LOCAL | U70: Normal Order | V70: Docketed | W70: 2026-06-07 | X70: 2026-06-07 | Y70: 2026-06-23 | Z70: 2026-06-24 | AA70: 2026-06-22T10:53:23 | AC70: P0 | AD70: 0 | AF70: reachedathub | AG70: 0 | AH70: 46195 | AI70: 1 | AJ70: Planned | AL70: #N/A | AM70: #N/A | AN70: #N/A | AO70: #N/A | AP70: #N/A | AQ70: #N/A | AR70: #N/A | AS70: #N/A
A71: Wakefit | B71: ORDER202606p6w4Um | C71: Suraj | D71: 601, 6, CR enclave, Site no 5 ,Thubarahalli extension road, Thubarahalli | E71: 560066 | F71: Bluwheel 2 | G71: WEWB7860STAURUSR2 | H71: 9740390201 | I71: 9740390201 | J71: WEWB7860STAURUSR2 | K71: 78x60 inch | L71: furniture | M71: 1003000472 | N71: Engineered Wood Bed | O71: FG01 | P71: 1 | Q71: ONLINE | R71: 26060590010930 | S71: WFFI461107 | T71: BLR LOCAL | U71: Normal Order | V71: Docketed | W71: 2026-06-10 | X71: 2026-06-10 | Y71: 2026-06-23 | Z71: 2026-06-24 | AA71: 2026-06-22T11:07:50 | AC71: P0 | AD71: 0 | AF71: reachedathub | AG71: 0 | AH71: 46195 | AI71: 1 | AJ71: Planned | AL71: #N/A | AM71: #N/A | AN71: #N/A | AO71: #N/A | AP71: #N/A | AQ71: #N/A | AR71: #N/A | AS71: #N/A
A72: Flipkart | B72: OD337699474550076100 | C72: Rajesh Saha | D72: Room no 116, Sri Lakshmi Venkateshwara Arcade, 4th Cross Thirumala Bakery Road, Chanasandra, ITBL, Kadugudi 3G Homes Crimson Layout, 4th cross, new extension, Channasandra ,Kadugodi | E72: 560067 | F72: Bluwheel 2 | G72: WBSPROSE | H72: 9435441894 | J72: WBSPROSE | L72: furniture | M72: 1003010025 | N72: Bookshelf | O72: FG01 | P72: 1 | Q72: ONLINE | R72: 26060590010860 | S72: WFFI461030 | T72: BLR LOCAL | U72: Normal Order | V72: Docketed | W72: 2026-05-30 | X72: 2026-05-30 | Y72: 2026-06-11 | Z72: 2026-06-12 | AA72: 2026-06-22T10:52:23 | AC72: Breached | AD72: 0 | AF72: reachedathub | AG72: 0 | AH72: 46195 | AI72: 1 | AJ72: Planned | AL72: #N/A | AM72: #N/A | AN72: #N/A | AO72: #N/A | AP72: #N/A | AQ72: #N/A | AR72: #N/A | AS72: #N/A
A73: Wakefit_Retail | B73: ORDER2026055Beg4w | C73: Ramakant Timsina | D73: B903 ,Block B, 9th Floor Jeevans Octave Apartment | E73: 560067 | F73: Bluwheel 2 | G73: WBSPROSE | H73: 7397492119 | I73: 7002113138 | J73: WBSPROSE | L73: furniture | M73: 1003010025 | N73: Bookshelf | O73: FG01 | P73: 1 | Q73: ONLINE | R73: 26060590010902 | S73: WFFI461074 | T73: BLR LOCAL | U73: Normal Order | V73: Docketed | W73: 2026-05-31 | X73: 2026-05-31 | Y73: 2026-06-22 | Z73: 2026-06-23 | AA73: 2026-06-22T10:53:13 | AC73: Breached | AD73: 0 | AF73: reachedathub | AG73: 0 | AH73: 46195 | AI73: 1 | AJ73: Planned | AL73: #N/A | AM73: #N/A | AN73: #N/A | AO73: #N/A | AP73: #N/A | AQ73: #N/A | AR73: #N/A | AS73: #N/A
A74: Wakefit | B74: ORDER2026062fCMBO | C74: Akshay Rajput | D74: 02141, 14, Sobha dream acre wing 2, Belegere Road, Varthur | E74: 560087 | F74: Bluwheel 2 | G74: WEWB7860HYSASTRA | H74: 9405560487 | I74: 9405560487 | J74: WEWB7860HYSASTRA | K74: 78x60 inch | L74: furniture | M74: 1001018974 | N74: Engineered Wood Bed | O74: FG01 | P74: 1 | Q74: ONLINE | R74: 26060590010820 | S74: WFFI460992 | T74: BLR LOCAL | U74: Normal Order | V74: Docketed | W74: 2026-06-03 | X74: 2026-06-03 | Y74: 2026-06-23 | Z74: 2026-06-24 | AA74: 2026-06-22T10:51:32 | AC74: P0 | AD74: 0 | AF74: reachedathub | AG74: 0 | AH74: 46195 | AI74: 1 | AJ74: Planned | AL74: #N/A | AM74: #N/A | AN74: #N/A | AO74: #N/A | AP74: #N/A | AQ74: #N/A | AR74: #N/A | AS74: #N/A
A75: Wakefit | B75: ORDER202606JARofj | C75: Ashutosh Kapoor | D75: Flat 303, 3, House 24/25, JP Residency, JCR Layout | E75: 560087 | F75: Bluwheel 2 | G75: WEWB7860STAURUSR2 | H75: 9660488660 | I75: 9660488660 | J75: WEWB7860STAURUSR2 | K75: 78x60 inch | L75: furniture | M75: 1003000472 | N75: Engineered Wood Bed | O75: FG01 | P75: 1 | Q75: ONLINE | R75: 26060590010929 | S75: WFFI461103 | T75: BLR LOCAL | U75: Normal Order | V75: Docketed | W75: 2026-06-10 | X75: 2026-06-10 | Y75: 2026-06-23 | Z75: 2026-06-24 | AA75: 2026-06-22T11:07:42 | AC75: P0 | AD75: 0 | AF75: reachedathub | AG75: 0 | AH75: 46195 | AI75: 1 | AJ75: Planned | AL75: #N/A | AM75: #N/A | AN75: #N/A | AO75: #N/A | AP75: #N/A | AQ75: #N/A | AR75: #N/A | AS75: #N/A
A76: Wakefit | B76: ORDER2026063hGDf5 | C76: AISHWARYA AGARWAL | D76: A007, 1, Shivam Agarwal, Anurag anmol apartment Bellandur railway station road ,panathur | E76: 560087 | F76: Bluwheel 2 | G76: WEWB7872NONUPOGRTAURUSR2 | H76: 6395393620 | I76: 6395393620 | J76: WEWB7872NONUPOGRTAURUSR2 | K76: 78x72 inch | L76: furniture | M76: 1007003125 | N76: Engineered Wood Bed | O76: FG01 | P76: 1 | Q76: ONLINE | R76: 26060590010664 | S76: WFFI460894 | T76: BLR LOCAL | U76: Normal Order | V76: Docketed | W76: 2026-06-19 | X76: 2026-06-19 | Y76: 2026-06-22 | Z76: 2026-06-23 | AA76: 2026-06-22T09:36:21 | AC76: Breached | AD76: 0 | AF76: reachedathub | AG76: 0 | AH76: 46195 | AI76: #N/A | AJ76: Planned | AL76: #N/A | AM76: #N/A | AN76: #N/A | AO76: #N/A | AP76: #N/A | AQ76: #N/A | AR76: Yes | AS76: #N/A
A77: Wakefit | B77: ORDER202605hrpLFf | C77: Utkarsh | D77: N035, 3, Assetz Marq - Phase 3, Kannamangala, Whitefield - Hoskote Rd. | E77: 560115 | F77: Bluwheel 2 | G77: WEWB7860SCNTR | H77: 8553178297 | I77: 8553178297 | J77: WEWB7860SCNTR | K77: 78x60 inch | L77: furniture | M77: 1001024520 | N77: Engineered Wood Bed | O77: FG01 | P77: 1 | Q77: ONLINE | R77: 26060590010652 | S77: WFFI460881 | T77: BLR LOCAL | U77: Normal Order | V77: Docketed | W77: 2026-05-28 | X77: 2026-05-28 | Y77: 2026-06-21 | Z77: 2026-06-23 | AA77: 2026-06-22T09:36:01 | AC77: Breached | AD77: 0 | AF77: reachedathub | AG77: 0 | AH77: 46195 | AI77: #N/A | AJ77: Planned | AL77: #N/A | AM77: #N/A | AN77: #N/A | AO77: #N/A | AP77: #N/A | AQ77: #N/A | AR77: Yes | AS77: #N/A
A78: Installation Pending - 23rd June 2026 | B78: ORDER202605mjbMTV | C78: NIKHIL MISHRA | D78: Building 18, Brindavan, Flat 102, 2nd floor, Balaji Layout, near Amrutha platinum towers, Nallurhalli, Whitefield | E78: 560066 | F78: Bluwheel 2 | G78: WEWB7860SUPVTTMARSWM | H78: 8982888345 | I78: 9599893739 | J78: WEWB7860SUPVTTMARSWM | R78: 26060590002754 | S78: WFFI451722
A79: CP Visit | B79: ORDER202502EzzsFX | C79: Abhishek S | D79: #111 audumbura homes maithri layout whitefield | E79: 560067 | F79: Bluwheel 2 | G79: WTWB7872SARAR3 | H79: 7012222414 | I79: 7012306764 | J79: WTWB7872SARAR3 | R79: 25020590033254 | S79: WFCPV127362
A80: Wakefit | B80: ORDER202606bm8IJv | C80: Nagaraj Palanisamy | D80: 1B, 1, Madhava Krupa, LG Layout,Balagere Road, Gunjur | E80: 560087 | F80: Bluwheel 3 | G80: WEWB7860STAURUSR2 | H80: 9384389123 | I80: 9384389123 | J80: WEWB7860STAURUSR2 | K80: 78x60 inch | L80: furniture | M80: 1003000472 | N80: Engineered Wood Bed | O80: FG01 | P80: 1 | Q80: ONLINE | R80: 26060590010864 | S80: WFFI461037 | T80: BLR LOCAL | U80: Normal Order | V80: Docketed | W80: 2026-06-11 | X80: 2026-06-11 | Y80: 2026-06-23 | Z80: 2026-06-24 | AA80: 2026-06-22T10:52:31 | AC80: P0 | AD80: 0 | AF80: reachedathub | AG80: 0 | AH80: 46195 | AI80: 1 | AJ80: Planned | AL80: #N/A | AM80: #N/A | AN80: #N/A | AO80: #N/A | AP80: #N/A | AQ80: #N/A | AR80: #N/A | AS80: #N/A
A81: Wakefit | B81: ORDER2026053qD8Zl | C81: Yogesh Bhavsar | D81: A-405, 4, Mana Candela - 2, Kodathi, Sarjapur Road, Behind Wipro Sez. | E81: 560035 | F81: Bluwheel 3 | G81: WEWB7872SASTRA | H81: 9662160875 | I81: 9662160875 | J81: WEWB7872SASTRA | K81: 78x72 inch | L81: furniture | M81: 1007100292 | N81: Engineered Wood Bed | O81: FG01 | P81: 1 | Q81: ONLINE | R81: 26060590010660 | S81: WFFI460883 | T81: BLR LOCAL | U81: Normal Order | V81: Docketed | W81: 2026-05-28 | X81: 2026-05-28 | Y81: 2026-06-21 | Z81: 2026-06-22 | AA81: 2026-06-22T09:36:01 | AC81: Breached | AD81: 0 | AF81: reachedathub | AG81: 0 | AH81: 46195 | AI81: 1 | AJ81: Planned | AL81: #N/A | AM81: #N/A | AN81: #N/A | AO81: #N/A | AP81: #N/A | AQ81: #N/A | AR81: #N/A | AS81: #N/A
A82: Wakefit_Retail | B82: ORDER202605nH70cW | C82: Soumya Singh | D82: E-601 , Godrej Park Retreat, Camelaram, Hadosiddapura, Chikkakannalli, Kodathi JHC, Bangalore, Karnataka | E82: 560035 | F82: Bluwheel 3 | G82: WEWB7860SUPOPLTAURUSR2 | H82: 8317306416 | I82: 8317306416 | J82: WEWB7860SUPOPLTAURUSR2 | K82: 78x60 inch | L82: furniture | M82: 1007003118 | N82: Engineered Wood Bed | O82: FG01 | P82: 1 | Q82: ONLINE | R82: 26060590010825 | S82: WFFI460998 | T82: BLR LOCAL | U82: Normal Order | V82: Docketed | W82: 2026-05-31 | X82: 2026-05-31 | Y82: 2026-06-22 | Z82: 2026-06-23 | AA82: 2026-06-22T10:51:43 | AC82: Breached | AD82: 0 | AF82: reachedathub | AG82: 0 | AH82: 46195 | AI82: 1 | AJ82: Planned | AL82: #N/A | AM82: #N/A | AN82: #N/A | AO82: #N/A | AP82: #N/A | AQ82: #N/A | AR82: #N/A | AS82: #N/A
A83: Wakefit | B83: ORDER20260607oraf | C83: Shantanu Dudhat | D83: 284, 8, Wing 2, DSR Eden Greens, Carmelaram bangalore 560035 | E83: 560035 | F83: Bluwheel 3 | G83: WEWB7272STAURUSR2 | H83: 8605865452 | I83: 8605865452 | J83: WEWB7272STAURUSR2 | K83: 72x72 inch | L83: furniture | M83: 1001025000 | N83: Engineered Wood Bed | O83: FG01 | P83: 1 | Q83: ONLINE | R83: 26060590010881 | S83: WFFI461053 | T83: BLR LOCAL | U83: Normal Order | V83: Docketed | W83: 2026-06-07 | X83: 2026-06-07 | Y83: 2026-06-22 | Z83: 2026-06-23 | AA83: 2026-06-22T10:52:51 | AC83: Breached | AD83: 0 | AF83: reachedathub | AG83: 0 | AH83: 46195 | AI83: 1 | AJ83: Planned | AL83: #N/A | AM83: #N/A | AN83: #N/A | AO83: #N/A | AP83: #N/A | AQ83: #N/A | AR83: #N/A | AS83: #N/A
A84: Wakefit | B84: ORDER202606IS8vcM | C84: siddhant saran | D84: D001, Premier Inspira Maplewood, Doddakanneli/Sarjapur Road | E84: 560035 | F84: Bluwheel 3 | G84: WEWB7560STAURUSR2 | H84: 8240474305 | I84: 8240474305 | J84: WEWB7560STAURUSR2 | K84: 75x60 inch | L84: furniture | M84: 1001024999 | N84: Engineered Wood Bed | O84: FG01 | P84: 1 | Q84: ONLINE | R84: 26060590010894 | S84: WFFI461065 | T84: BLR LOCAL | U84: Normal Order | V84: Docketed | W84: 2026-06-07 | X84: 2026-06-07 | Y84: 2026-06-23 | Z84: 2026-06-24 | AA84: 2026-06-22T10:53:03 | AC84: P0 | AD84: 0 | AF84: reachedathub | AG84: 0 | AH84: 46195 | AI84: 1 | AJ84: Planned | AL84: #N/A | AM84: #N/A | AN84: #N/A | AO84: #N/A | AP84: #N/A | AQ84: #N/A | AR84: #N/A | AS84: #N/A
A85: Wakefit | B85: ORDER202606IADVCX | C85: Sharath | D85: 1, Flat no.102, Galaxy building,Flat #102, Site No.75, 13th Cross, K.P.C Layout, Junnasandra Village, Varthur Hobli, Bangalore East | E85: 560035 | F85: Bluwheel 3 | G85: WEWB7860STAURUSR2 | H85: 9964691231 | J85: WEWB7860STAURUSR2 | K85: 78x60 inch | L85: furniture | M85: 1003000472 | N85: Engineered Wood Bed | O85: FG01 | P85: 1 | Q85: ONLINE | R85: 26060590010867 | S85: WFFI461043 | T85: BLR LOCAL | U85: Normal Order | V85: Docketed | W85: 2026-06-11 | X85: 2026-06-11 | Y85: 2026-06-23 | Z85: 2026-06-24 | AA85: 2026-06-22T10:52:39 | AC85: P0 | AD85: 0 | AF85: reachedathub | AG85: 0 | AH85: 46195 | AI85: 1 | AJ85: Planned | AL85: #N/A | AM85: #N/A | AN85: #N/A | AO85: #N/A | AP85: #N/A | AQ85: #N/A | AR85: #N/A | AS85: #N/A
A86: Wakefit_Retail | B86: ORDER202606A3PAvo | C86: Yatin | D86: Villa 006, Madagascar Villaments, Kaikondrahalli, Hosa Rd | E86: 560035 | F86: Bluwheel 3 | G86: WEWB7860STAURUSMA | H86: 8054442186 | I86: 8054442186 | J86: WEWB7860STAURUSMA | K86: 78x60 inch | L86: furniture | M86: 1001024789 | N86: Engineered Wood Bed | O86: FG01 | P86: 1 | Q86: ONLINE | R86: 26060590010654 | S86: WFFI460879 | T86: BLR LOCAL | U86: Normal Order | V86: Docketed | W86: 2026-06-19 | X86: 2026-06-19 | Y86: 2026-06-23 | Z86: 2026-06-24 | AA86: 2026-06-22T09:36:01 | AC86: P0 | AD86: 0 | AF86: reachedathub | AG86: 0 | AH86: 46195 | AI86: 1 | AJ86: Planned | AL86: #N/A | AM86: #N/A | AN86: #N/A | AO86: #N/A | AP86: #N/A | AQ86: #N/A | AR86: #N/A | AS86: #N/A
A87: Wakefit_Retail | B87: ORDER202605f7wbcG | C87: Paniraj thanthry | D87: #405, 4th floor, Sairam Gardenia, near RGA Tech Park & Decathlon mart, Hadosiddapura, Chikkakannalli, Kodathi JHC, Karnatak | E87: 560035 | F87: Bluwheel 3 | G87: WEWB7860STESSERCW | H87: 8431567630 | I87: 8431567630 | J87: WEWB7860STESSERCW | K87: 78x60 inch | L87: furniture | M87: 1001033592 | N87: Engineered Wood Bed | O87: FG01 | P87: 1 | Q87: ONLINE | R87: 26060590008782 | S87: WFFI458444 | T87: BLR LOCAL | U87: Normal Order | V87: Shipped | W87: 2026-05-19 | X87: 2026-05-19 | Y87: 2026-06-18 | Z87: 2026-06-19 | AA87: 2026-06-17T23:21:10 | AB87: 2026-06-18T21:32:44 | AC87: Breached | AD87: 0 | AF87: reachedathub | AG87: Customer Request for Future Date Delivery | AH87: 46196 | AI87: #N/A | AJ87: CNR | AL87: #N/A | AM87: #N/A | AN87: #N/A | AO87: #N/A | AP87: #N/A | AQ87: #N/A | AR87: #N/A | AS87: #REF!
A88: Wakefit | B88: ORDER202606bh8Ut2 | C88: Avinash Kumar | D88: B1403, 14, Godrej Park Retreat, Godrej Park Retreat, Tower B, 1403, Carmelaram, Hadosiddapura, Chikkakannalli, Kodathi JHC | E88: 560035 | F88: Bluwheel 3 | G88: WSTSHEAPG | H88: 9866277566 | I88: 8240303495 | J88: WSTSHEAPG | L88: furniture | M88: 1007004622 | N88: Study Table | O88: FG01 | P88: 1 | Q88: ONLINE | R88: 26060590010380 | S88: WFFI460698 | T88: BLR LOCAL | U88: Normal Order | V88: Docketed | W88: 2026-06-19 | X88: 2026-06-19 | Y88: 2026-06-21 | Z88: 2026-06-22 | AA88: 2026-06-21T13:37:00 | AC88: Breached | AD88: 0 | AF88: reachedathub | AG88: 0 | AH88: 46195 | AI88: #N/A | AJ88: CNR | AL88: #N/A | AM88: #N/A | AN88: #N/A | AO88: #N/A | AP88: #N/A | AQ88: #N/A | AR88: #N/A | AS88: #REF!
A89: Wakefit | B89: ORDER202606DnAnMw | C89: Yogendra Sharma | D89: 12021, 2, sobha royal pavillion, 12021,Sobha Royal Pavilion,Sarjapur - Marathahalli Road, Carmelaram, Hadosiddapura | E89: 560035 | F89: Bluwheel 3 | G89: WSTSAGEPG | H89: 9971246247 | I89: 9971246247 | J89: WSTSAGEPG | L89: furniture | M89: 1007003999 | N89: Study Table | O89: FG01 | P89: 1 | Q89: ONLINE | R89: 26060590010835 | S89: WFFI461006 | T89: BLR LOCAL | U89: Normal Order | V89: Docketed | W89: 2026-06-20 | X89: 2026-06-20 | Y89: 2026-06-23 | Z89: 2026-06-24 | AA89: 2026-06-22T10:51:53 | AC89: P0 | AD89: 0 | AF89: reachedathub | AG89: 0 | AH89: 46195 | AI89: #N/A | AJ89: CNR | AL89: #N/A | AM89: #N/A | AN89: #N/A | AO89: #N/A | AP89: #N/A | AQ89: #N/A | AR89: #N/A | AS89: #REF!
A90: Installation pending | B90: ORDER202605rBXIWu | C90: Siddharth Kothari | D90: Flat no 1502, DSR Parkway, Tower 1, Wing 5, Sarjapur Main Road, Carmelaram | E90: 560035 | F90: Bluwheel 3 | G90: WEWB7860HYSUPOPLMARS | H90: 8408820884 | I90: 7045799957 | J90: WEWB7860HYSUPOPLMARS | R90: 26050590011648 | S90: WFFI442033
A91: Installation Pending | B91: OD337709155549753100 | C91: Venkatapathy | D91: 26, First floor. second cross road C S B Layout, Hosa Road, Valliyamma Layout, Kasavanahalli Valliyamma Layout, Sarjapur Main Road, Kasavanahalli | E91: 560035 | F91: Bluwheel 3 | G91: WSTNASH | H91: 8248569774 | J91: WSTNASH | R91: 26060590001280 | S91: WFFI449955
A92: Installation pending | B92: 404-9622426-6067506 | C92: shobhna | D92: F181, sjr plazza city, Sarjapur toad, doddenakalli | E92: 560035 | F92: Bluwheel 3 | G92: WDRUMENDFU | H92: 8886878745 | I92: 8886878745 | J92: WDRUMENDFU | R92: 26060590009271 | S92: WFFI459015
A93: Wakefit | B93: ORDER202606QzKc1X | C93: Shruthi Balan | D93: 220, 3, V M Serenity, 2nd cross, Brindavan Layout, Horamavu | E93: 560043 | F93: LBL 1 | G93: WCODCNTR4DFW | H93: 9880940065 | I93: 9880940065 | J93: WCODCNTR4DFW | L93: furniture | M93: 1001023245 | N93: Engineered Wood Chest Of Drawers | O93: FG01 | P93: 1 | Q93: ONLINE | R93: 26060590010376 | S93: WFFI460696 | T93: BLR LOCAL | U93: Normal Order | V93: Docketed | W93: 2026-06-04 | X93: 2026-06-04 | Y93: 2026-06-22 | Z93: 2026-06-23 | AA93: 2026-06-21T13:36:59 | AC93: Breached | AD93: 0 | AF93: reachedathub | AG93: 0 | AH93: 46195 | AI93: #N/A | AJ93: Planned | AL93: #N/A | AM93: #N/A | AN93: #N/A | AO93: #N/A | AP93: #N/A | AQ93: #N/A | AR93: Yes | AS93: #N/A
A94: Wakefit_Retail | B94: ORDER202606k9fq4q | C94: Pawan Agrawal | D94: Nageena mansion , 102, 1st floor, 7th, 44/5-15, 3rd C Cross Rd, HBR Layout 4th Block, HBR Layout, Bengaluru, Karnataka 560043 | E94: 560043 | F94: LBL 1 | G94: WEWB7860HYSUPOPLMARS | H94: 9668798697 | J94: WEWB7860HYSUPOPLMARS | K94: 78x60 inch | L94: furniture | M94: 1007002501 | N94: Engineered Wood Bed | O94: FG01 | P94: 1 | Q94: ONLINE | R94: 26060590010919 | S94: WFFI461088 | T94: BLR LOCAL | U94: Normal Order | V94: Docketed | W94: 2026-06-06 | X94: 2026-06-06 | Y94: 2026-06-22 | Z94: 2026-06-23 | AA94: 2026-06-22T11:07:32 | AC94: Breached | AD94: 0 | AF94: reachedathub | AG94: 0 | AH94: 46195 | AI94: 1 | AJ94: Planned | AL94: #N/A | AM94: #N/A | AN94: #N/A | AO94: #N/A | AP94: #N/A | AQ94: #N/A | AR94: #N/A | AS94: #N/A
A95: Wakefit_Retail | B95: ORDER202606vJhRml | C95: Nikhil BS | D95: 105, 1st cross, Ramaiah Reddy layout, chikka banaswadi | E95: 560043 | F95: LBL 1 | G95: WEWB7860HYSUPOPLLEOR2 | H95: 9743353162 | I95: 9448856523 | J95: WEWB7860HYSUPOPLLEOR2 | K95: 78x60 inch | L95: furniture | M95: 1001019001 | N95: Engineered Wood Bed | O95: FG01 | P95: 1 | Q95: ONLINE | R95: 26060590010896 | S95: WFFI461067 | T95: BLR LOCAL | U95: Normal Order | V95: Docketed | W95: 2026-06-07 | X95: 2026-06-07 | Y95: 2026-06-23 | Z95: 2026-06-24 | AA95: 2026-06-22T10:53:07 | AC95: P0 | AD95: 0 | AF95: reachedathub | AG95: 0 | AH95: 46195 | AI95: 1 | AJ95: Planned | AL95: #N/A | AM95: #N/A | AN95: #N/A | AO95: #N/A | AP95: #N/A | AQ95: #N/A | AR95: #N/A | AS95: #N/A
A96: Wakefit | B96: ORDER202606RaZorS | C96: Vishnu Komath | D96: 3, Flat 301, ATRR Apartment 36th cross, 19th main, Hennur Rd, 5th Block, Prakruthi Layout, HBR Layout | E96: 560043 | F96: LBL 1 | G96: WSTCAMUSWM | H96: 7204543969 | J96: WSTCAMUSWM | L96: furniture | M96: 1001024026 | N96: Study Table | O96: FG01 | P96: 1 | Q96: ONLINE | R96: 26060590010381 | S96: WFFI460700 | T96: BLR LOCAL | U96: Normal Order | V96: Docketed | W96: 2026-06-18 | X96: 2026-06-18 | Y96: 2026-06-21 | Z96: 2026-06-22 | AA96: 2026-06-21T13:37:06 | AC96: Breached | AD96: 0 | AF96: reachedathub | AG96: 0 | AH96: 46195 | AI96: 1 | AJ96: Planned | AL96: #N/A | AM96: #N/A | AN96: #N/A | AO96: #N/A | AP96: #N/A | AQ96: #N/A | AR96: #N/A | AS96: #N/A
A97: Wakefit | B97: ORDER202606dZXrCz | C97: RAJENDRA SHAMANNA | D97: 4, 1, SHRI GHANDHA, N0 4, 4TH St, Ist BLOCK, PRAKRUTHI TOWNSHIP HORAMAVU AGARA MAIN RD, BABUSAPALYA, BANGALORE | E97: 560043 | F97: LBL 1 | G97: WSTAVENORCWW | H97: 9886871119 | I97: 9886871119 | J97: WSTAVENORCWW | L97: furniture | M97: 1007120466 | N97: Study Table | O97: FG01 | P97: 1 | Q97: ONLINE | R97: 26060590010222 | S97: WFFI460455 | T97: BLR LOCAL | U97: Normal Order | V97: Shipped | W97: 2026-06-19 | X97: 2026-06-19 | Y97: 2026-06-22 | Z97: 2026-06-23 | AA97: 2026-06-21T11:41:33 | AB97: 2026-06-21T21:18:51 | AC97: Breached | AD97: 0 | AF97: reachedathub | AG97: 0 | AH97: 46195 | AI97: #N/A | AJ97: Planned | AL97: #N/A | AM97: #N/A | AN97: #N/A | AO97: #N/A | AP97: #N/A | AQ97: #N/A | AR97: Yes | AS97: #N/A
A98: Wakefit_Retail | B98: ORDER202606YWyInb | C98: Kirubakaran G M | D98: 122C,1st Floor,1st Cross,Lake View Garden Layout,K.Channasandra | E98: 560043 | F98: LBL 1 | G98: WEWB7230SCRX | H98: 9980983800 | J98: WEWB7230SCRX | K98: 72x30 inch | L98: furniture | M98: 1001019159 | N98: Engineered Wood Bed | O98: FG01 | P98: 1 | Q98: ONLINE | R98: 26060590010866 | S98: WFFI461042 | T98: BLR LOCAL | U98: Normal Order | V98: Docketed | W98: 2026-06-20 | X98: 2026-06-20 | Y98: 2026-06-22 | Z98: 2026-06-23 | AA98: 2026-06-22T10:52:38 | AC98: Breached | AD98: 0 | AF98: reachedathub | AG98: 0 | AH98: 46195 | AI98: 1 | AJ98: Planned | AL98: #N/A | AM98: #N/A | AN98: #N/A | AO98: #N/A | AP98: #N/A | AQ98: #N/A | AR98: #N/A | AS98: #N/A
A99: Wakefit_Retail | B99: ORDER202606YWyInb | C99: Kirubakaran G M | D99: 122C,1st Floor,1st Cross,Lake View Garden Layout,K.Channasandra | E99: 560043 | F99: LBL 1 | G99: WBSPROSE | H99: 9980983800 | J99: WBSPROSE | L99: furniture | M99: 1003010025 | N99: Bookshelf | O99: FG01 | P99: 1 | Q99: ONLINE | R99: 26060590010873 | S99: WFFI461044 | T99: BLR LOCAL | U99: Normal Order | V99: Docketed | W99: 2026-06-20 | X99: 2026-06-20 | Y99: 2026-06-22 | Z99: 2026-06-23 | AA99: 2026-06-22T10:52:41 | AC99: Breached | AD99: 0 | AF99: reachedathub | AG99: 0 | AH99: 46195 | AI99: 1 | AJ99: Planned | AL99: #N/A | AM99: #N/A | AN99: #N/A | AO99: #N/A | AP99: #N/A | AQ99: #N/A | AR99: #N/A | AS99: #N/A
A100: Wakefit_Retail | B100: ORDER202606MKwMPk | C100: Saif Ali Khan | D100: Tnt oakwood, gf 002, 13th cross,5th block telecom layout hbr layout | E100: 560043 | F100: LBL 1 | G100: WSTCAMUSFW | H100: 7829317780 | J100: WSTCAMUSFW | L100: furniture | M100: 1001023243 | N100: Study Table | O100: FG01 | P100: 1 | Q100: ONLINE | R100: 26060590010877 | S100: WFFI461047 | T100: BLR LOCAL | U100: Normal Order | V100: Docketed | W100: 2026-06-20 | X100: 2026-06-20 | Y100: 2026-06-23 | Z100: 2026-06-24 | AA100: 2026-06-22T10:52:42 | AC100: P0 | AD100: 0 | AF100: reachedathub | AG100: 0 | AH100: 46195 | AI100: 1 | AJ100: Planned | AL100: #N/A | AM100: #N/A | AN100: #N/A | AO100: #N/A | AP100: #N/A | AQ100: #N/A | AR100: #N/A | AS100: #N/A
...

Sheet Service
A1: TYPE | B1: SERVICE | C1: order_random_id | D1: item_sku | E1: invoice_number | F1: docket_number | G1: cx_name | H1: address | I1: pincode | J1: mobile_number | K1: alternate_mobile_number | L1: Remarks
A2: CP | B2: CP Visit | C2: ORDER202502EzzsFX | D2: WTWB7872SARAR3 | E2: 25020590033254 | F2: WFCPV127362 | G2: Abhishek S | H2: #111 audumbura homes maithri layout whitefield | I2: 560067 | J2: 7012222414 | K2: 7012306764 | L2: Confirm
A3: CP | B3: CP Visit- 19th June 2026 | C3: ORDER202512FvbDhv | D3: WEWB7860HYSTESSERCW | E3: 26010590007386 | F3: WFCPV127363 | G3: Vikas Sharma | H3: 24257, 25, Prestige city sarjapur, Prestige city sarjapur-Marathahalli-Sarjapur Road,Yamare Village, Bangalore karnatka | I3: 562125 | J3: 8800599553 | K3: 8800599553 | L3: Confirm
A4: CP | B4: CP Visit | C4: ORDER202501GZpMXX | D4: WDINEMINTS4COPCBSW | E4: 26020590006651 | F4: WFCPV127364 | G4: karthik M K | H4: Prestige Primrose Hill, #2098, Tower 2, 9th floor. Sy No 52 Banshankari 6th stage, Nagegowdanapalya, Bengaluru | I4: 560109 | J4: 9900198243 | L4: Confirm
A5: CP | B5: CP Visit- 23rd June 2026 | C5: ORDER202603oUxwCy | D5: WSCHRSAFARHBNBBKBKBKMLR2 | E5: 26032430003511 | F5: WFCPV127365 | G5: veda | H5: 835, 2, sri gowri coffee works, Udaya nagar, near tin factory metro | I5: 560016 | J5: 7330933939 | K5: 7330933939 | L5: Confirm
A6: CP | B6: CP Visit- ESC | C6: ORDER202605OKyL6Q | D6: WWRB3TWILLDBR2 | E6: 26050590013617 | F6: WFCPV127366 | G6: Sabari | H6: FLAT NO -8C FIRST FLOOR Sun shine layout, tc palaya road | I6: 560036 | J6: 9688855557 | K6: 9787555644 | L6: Confirm
A7: CP | B7: CP Visit | C7: ORDER202605TzgGOb | D7: WWRB2DTWILLDBR2 | E7: 26052060003824 | F7: WFCPV127367 | G7: Aditya Kumar | H7: Radha Nivas, No 1113/H, 2nd cross, 1st G Main, Girinagar | I7: 560085 | J7: 9916919069 | L7: Confirm
A8: CP | B8: CP Visit- ESC (Praful) | C8: ORDER2026050jy2wG | D8: WSFACRCMN3FVDO | E8: 26060590008838 | F8: WFCPV127368 | G8: Sundeep GUDEKOTE SREEDHARAMOORTHY | H8: Bhuvi by amsha,flat G-504, 5th floor, Tower G, Kadubeesanahalli, panathur, | I8: 560103 | J8: 9164587968 | L8: Confirm
A9: CP | B9: CP Visit- Part | C9: ORDER202605fsyo0k | D9: WEWB7860HYSCNTRWM | E9: 26062060000068 | F9: WFCPV127369 | G9: Harshajit Kashyap | H9: 104, 1ST FLOOR, SBR TEJAS ,Avalahalli, Back side of Volkswagen Showroom | I9: 560049 | J9: 9867550740 | K9: 9867550740 | L9: Confirm
A10: CP | B10: CP Visit- Installation- confirm | C10: ORDER202605yMYI0Z | D10: WSTNOTIQ160CW | E10: 26062060003422 | F10: WFCPV127370 | G10: Manoj Balakrishnan | H10: Block 1, 2nd floor, Flat no 204, keerthi manor apartment, GM palaya road, new tippasundra, bangalore | I10: 560075 | J10: 8095177759 | L10: Confirm
A11: CP | B11: CP Visit- Installation- confirm | C11: ORDER202606RtXNPX | D11: WWRB3S6DMH1SH1TYRIANPPB | E11: 26062060004055 | F11: WFCPV127371 | G11: Ashish Bisht | H11: 269, 3, Lila parlour building, 269, 3rd floor, 4th cross, 5th main, viveknagar, Bengaluru | I11: 560047 | J11: 8792547319 | K11: 8792547319 | L11: Confirm
A12: CP | B12: CP Visit- Installation- confirm | C12: ORDER202606uTwHUr | D12: WEWB7860SUPVTTMARSWM | E12: 26062060004824 | F12: WFCPV127372 | G12: Divya Bhardwaj | H12: 1945, Shardamba Nilaya, 1945, Ground floor 21st a main road, vanganhalli, Sector 1, HSR layout | I12: 560102 | J12: 9650947501 | K12: 9650947501 | L12: Confirm
A13: CP | B13: CP Visit- Installation | C13: ORDER2026069ECxN6 | D13: WEWB7872SUPOGRMARS | E13: 26062060005484 | F13: WFCPV127373 | G13: Shubham | H13: 301, 3rd Floor,174 Sree Residency, 4th cross street | I13: 560078 | J13: 9557114830 | L13: Confirm
A14: CP | B14: CP Visit | C14: ORDER202509U4cLqa | D14: WDINEKOVAC1MBBK | E14: 25100590113046 | F14: WFCPV127374 | G14: Shikhar Sharad | H14: D402, Adarsh Lakefront, Kaikondrahalli, Bellandur | I14: 560103 | J14: 9686262880 | L14: Confirm
